Workbook

Sheet Receita Despesas 2011 
C1: Condominio Rua Vieira da Silva, 6 | J1: Queluz - Monte Abraão | W1: Ano 2011
C4: Receitas | D4: Janeiro | F4: Fevereiro | H4: Março | J4: Abril | L4: Maio | N4: Junho | P4: Julho | R4: Agosto | T4: Setembro | V4: Outubro | X4: Novembro | Z4: Dezembro | AC4: Valor Pago | AD4: Valor Esperado | AE4: Valor em atraso
C7: 6ºAndar Direito | Z7: 32.5 | AC7: =SUM(D7:Z7) -> 32.5 | AD7: =37.5*12 -> 450 | AE7: =AC7-AD7 -> -417.5
C8: 6ºAndar Esquerdo | P8: 102.5 | T8: 75 | V8: 37.5 | X8: 37.5 | Z8: 37.5 | AC8: =SUM(D8:Z8) -> 290 | AD8: =37.5*12 -> 450 | AE8: =AC8-AD8 -> -160
C9: 5ºAndar Direito | D9: 37.5 | F9: 37.5 | H9: 37.5 | J9: 37.5 | L9: 37.5 | N9: 37.5 | P9: 37.5 | R9: 37.5 | T9: 37.5 | V9: 37.5 | X9: 37.5 | Z9: 37.5 | AC9: =SUM(D9:Z9) -> 450 | AD9: =37.5*12 -> 450 | AE9: =AC9-AD9 -> 0
C10: 5 Andar Esquerdo | D10: 37.5 | F10: 37.5 | H10: 37.5 | J10: 37.5 | L10: 37.5 | N10: 37.5 | P10: 37.5 | R10: 37.5 | T10: 37.5 | V10: 37.5 | X10: 37.5 | Z10: 37.5 | AC10: =SUM(D10:Z10) -> 450 | AD10: =37.5*12 -> 450 | AE10: =AC10-AD10 -> 0
C11: 4ºAndar Direito | D11: 37.5 | F11: 37.5 | H11: 37.5 | J11: 37.5 | L11: 37.5 | N11: 37.5 | P11: 37.5 | R11: 37.5 | T11: 37.5 | V11: 37.5 | X11: 37.5 | Z11: 37.5 | AC11: =SUM(D11:Z11) -> 450 | AD11: =37.5*12 -> 450 | AE11: =AC11-AD11 -> 0
C12: 4ºAndar Esquerdo | P12: 37.5 | R12: 37.5 | T12: 37.5 | V12: 37.5 | X12: 37.5 | Z12: 37.5 | AC12: =SUM(D12:Z12) -> 225 | AD12: =37.5*12 -> 450 | AE12: =AC12-AD12 -> -225
C13: 3ºAndar Direito | L13: 37.5 | N13: 37.5 | R13: 37.5 | T13: 37.5 | V13: 37.5 | X13: 37.5 | Z13: 37.5 | AC13: =SUM(D13:Z13) -> 262.5 | AD13: =37.5*12 -> 450 | AE13: =AC13-AD13 -> -187.5
C14: 3ºAndar Esquerdo | D14: 37.5 | F14: 37.5 | H14: 37.5 | J14: 37.5 | L14: 37.5 | N14: 37.5 | P14: 37.5 | R14: 37.5 | T14: 37.5 | V14: 37.5 | X14: 37.5 | Z14: 37.5 | AC14: =SUM(D14:Z14) -> 450 | AD14: =37.5*12 -> 450 | AE14: =AC14-AD14 -> 0
C15: 2ºAndar Direito | P15: 37.5 | R15: 37.5 | T15: 37.5 | V15: 37.5 | X15: 37.5 | Z15: 37.5 | AC15: =SUM(D15:Z15) -> 225 | AD15: =37.5*12 -> 450 | AE15: =AC15-AD15 -> -225
C16: 2ºAndar Esquerdo | D16: 32.5 | F16: 32.5 | AC16: =SUM(D16:Z16) -> 65 | AD16: =37.5*12 -> 450 | AE16: =AC16-AD16 -> -385
C17: 1ºAndar Direito | D17: 35 | F17: 35 | H17: 35 | J17: 35 | L17: 35 | N17: 35 | P17: 35 | R17: 35 | T17: 35 | V17: 35 | X17: 35 | Z17: 35 | AC17: =SUM(D17:Z17) -> 420 | AD17: =37.5*12 -> 450 | AE17: =AC17-AD17 -> -30
C18: 1ºAndar Esquerdo | R18: 37.5 | T18: 37.5 | V18: 37.5 | X18: 37.5 | Z18: 37.5 | AC18: =SUM(D18:Z18) -> 187.5 | AD18: =37.5*12 -> 450 | AE18: =AC18-AD18 -> -262.5
C19: Res-Chão Direito | J19: 37.5 | L19: 75 | T19: 187.5 | V19: 37.5 | Z19: 37.5 | AC19: =SUM(D19:Z19) -> 375 | AD19: =37.5*12 -> 450 | AE19: =AC19-AD19 -> -75
C20: Res-Chão Esquerdo | D20: 37.5 | F20: 37.5 | J20: 37.5 | L20: 37.5 | N20: 37.5 | P20: 37.5 | R20: 37.5 | T20: 37.5 | V20: 37.5 | X20: 37.5 | Z20: 37.5 | AC20: =SUM(D20:Z20) -> 412.5 | AD20: =37.5*12 -> 450 | AE20: =AC20-AD20 -> -37.5
C21: Cave -1 (Garagem) | R21: 37.5 | T21: 37.5 | V21: 37.5 | X21: 37.5 | Z21: 37.5 | AC21: =SUM(D21:Z21) -> 187.5 | AD21: =37.5*12 -> 450 | AE21: =AC21-AD21 -> -262.5
C22: Cave -2 | D22: 37.5 | F22: 37.5 | H22: 37.5 | J22: 37.5 | L22: 37.5 | N22: 37.5 | P22: 37.5 | R22: 37.5 | T22: 37.5 | V22: 37.5 | X22: 37.5 | Z22: 37.5 | AC22: =SUM(D22:Z22) -> 450 | AD22: =37.5*12 -> 450 | AE22: =AC22-AD22 -> 0
C24: Entregas Numerário LDC | D24: 150 | F24: 187.5 | H24: 112.5 | J24: 300 | L24: 112.5 | N24: 150 | P24: 112.5
C27: Total Receitas | D27: =D7+D8+D9+D10+D11+D12+D13+D14+D15+D16+D17+D18+D19+D20+D21+D22+D24 -> 442.5 | F27: =F7+F8+F9+F10+F11+F12+F13+F14+F15+F16+F17+F18+F19+F20+F21+F22+F24 -> 480 | H27: =H7+H8+H9+H10+H11+H12+H13+H14+H15+H16+H17+H18+H19+H20+H21+H22+H24 -> 335 | J27: =J7+J8+J9+J10+J11+J12+J13+J14+J15+J16+J17+J18+J19+J20+J21+J22+J24 -> 597.5 | L27: =L7+L8+L9+L10+L11+L12+L13+L14+L15+L16+L17+L18+L19+L20+L21+L22+L24 -> 485 | N27: =N7+N8+N9+N10+N11+N12+N13+N14+N15+N16+N17+N18+N19+N20+N21+N22+N24 -> 447.5 | P27: =P7+P8+P9+P10+P11+P12+P13+P14+P15+P16+P17+P18+P19+P20+P21+P22+P24 -> 550 | R27: =R7+R8+R9+R10+R11+R12+R13+R14+R15+R16+R17+R18+R19+R20+R21+R22+R24 -> 447.5 | T27: =T7+T8+T9+T10+T11+T12+T13+T14+T15+T16+T17+T18+T19+T20+T21+T22+T24 -> 710 | V27: =V7+V8+V9+V10+V11+V12+V13+V14+V15+V16+V17+V18+V19+V20+V21+V22+V24 -> 522.5 | X27: =X7+X8+X9+X10+X11+X12+X13+X14+X15+X16+X17+X18+X19+X20+X21+X22+X24 -> 485 | Z27: =Z7+Z8+Z9+Z10+Z11+Z12+Z13+Z14+Z15+Z16+Z17+Z18+Z19+Z20+Z21+Z22+Z24 -> 555
C31: Despesas | D31: Janeiro | F31: Fevereiro | H31: Março | J31: Abril | L31: Maio | N31: Junho | P31: Julho | R31: Agosto | T31: Setembro | V31: Outubro | X31: Novembro | Z31: Dezembro | AC31: Valor Pago
C34: Electricidade | D34: 104.49 | F34: 133.77 | H34: 108.65 | J34: 89.85 | L34: 109.22 | N34: 102.79 | P34: 134.1 | R34: 116.17 | V34: 112.08 | X34: 115.94 | Z34: 144.25 | AC34: =SUM(D34:AB34) -> 1271.31
C35: Elevadores | D35: 147.38 | F35: 147.38 | H35: 147.38 | J35: 147.38 | L35: 147.38 | N35: 147.38 | P35: 147.38 | R35: 147.38 | T35: 147.38 | V35: 147.38 | Z35: 105.25 | AC35: =SUM(D35:AB35) -> 1579.05
C36: Inspecção Elevadores | V36: 405.6 | AC36: =SUM(D36:AB36) -> 405.6
C37: Manutenção Bombas Água | R37: 322.08 | V37: 162.36 | AC37: =SUM(D37:AB37) -> 484.44
C38: Tribunal / Julgados de Paz | V38: 35 | AC38: =SUM(D38:AB38) -> 35
C39: Produtos Limpeza | V39: 49.05 | AC39: =SUM(D39:AB39) -> 49.05
C40: Despesas Bancárias | D40: 17.68 | J40: 15.6 | N40: 1.04 | P40: 15.6 | R40: 1.04 | T40: 8.3 | V40: 12.48 | X40: 1.04 | Z40: 0.36 | AC40: =SUM(D40:AB40) -> 73.14
C41: LDC | D41: 248.05 | X41: 531.5 | AC41: =SUM(D41:AB41) -> 779.55
C42: Material Electrico | D42: 90 | X42: 49.95 | Z42: 68 | AC42: =SUM(D42:AB42) -> 207.95
C43: Antena Telhado | V43: 37.45 | AC43: =SUM(D43:AB43) -> 37.45
C44: Diversos / CTT | AC44: =SUM(D44:AB44) -> 0
C47: Total Despesas | D47: =D34+D35+D36+D37+D38+D39+D40+D41+D42+D43+D44 -> 607.6 | F47: =F34+F35+F36+F37+F38+F39+F40+F41+F42+F43+F44 -> 281.15 | H47: =H34+H35+H36+H37+H38+H39+H40+H41+H42+H43+H44 -> 256.03 | J47: =J34+J35+J36+J37+J38+J39+J40+J41+J42+J43+J44 -> 252.83 | L47: =L34+L35+L36+L37+L38+L39+L40+L41+L42+L43+L44 -> 256.6 | N47: =N34+N35+N36+N37+N38+N39+N40+N41+N42+N43+N44 -> 251.21 | P47: =P34+P35+P36+P37+P38+P39+P40+P41+P42+P43+P44 -> 297.08 | R47: =R34+R35+R36+R37+R38+R39+R40+R41+R42+R43+R44 -> 586.67 | T47: =T34+T35+T36+T37+T38+T39+T40+T41+T42+T43+T44 -> 155.68 | V47: =V34+V35+V36+V37+V38+V39+V40+V41+V42+V43+V44 -> 961.4 | X47: =X34+X35+X36+X37+X38+X39+X40+X41+X42+X43+X44 -> 698.43 | Z47: =Z34+Z35+Z36+Z37+Z38+Z39+Z40+Z41+Z42+Z43+Z44 -> 317.86 | AC47: =SUM(AC34:AC44) -> 4922.54
C53: Resultados Liquidos | D53: =D27-D47 -> -165.1 | F53: =F27-F47 -> 198.85 | H53: =H27-H47 -> 78.97 | J53: =J27-J47 -> 344.67 | L53: =L27-L47 -> 228.4 | N53: =N27-N47 -> 196.29 | P53: =P27-P47 -> 252.92 | R53: =R27-R47 -> -139.17 | T53: =T27-T47 -> 554.32 | V53: =V27-V47 -> -438.9 | X53: =X27-X47 -> -213.43 | Z53: =Z27-Z47 -> 237.14
C57: Valor Transitado do Ano 2010 | D57: 340.19 | P57: Monte Abraão, 13 de Janeiro de 2012 | X57: A Administração
C58: Receitas Ano 2011 | D58: 6057.5
D59: =SUM(D57:D58) -> 6397.69
C60: Despesas Ano 2011 - | D60: 4922.54
C61: Saldo Transitado para 2012 | D61: =D59-D60 -> 1475.15

Sheet Receitas Despesas 2012
C1: Condominio Rua Vieira da Silva, 6 | J1: Queluz - Monte Abraão | W1: Ano 2012
C4: Receitas | D4: Janeiro | F4: Fevereiro | H4: Março | J4: Abril | L4: Maio | N4: Junho | P4: Julho | R4: Agosto | T4: Setembro | V4: Outubro | X4: Novembro | Z4: Dezembro | AC4: TOTAL | AD4: Valor esperado | AE4: Valor em divida 2012
C7: 6ºAndar Direito | D7: 222.97 | AC7: =SUM(D7:AB7) -> 222.97 | AD7: =37.5*12 -> 450 | AE7: =AC7-AD7 -> -227.03
C8: 6ºAndar Esquerdo | D8: 37.5 | H8: 75 | J8: 37.5 | N8: 75 | P8: 37.5 | R8: 37.5 | T8: 37.5 | V8: 37.5 | X8: 37.5 | Z8: 37.5 | AC8: =SUM(D8:AB8) -> 450 | AD8: =37.5*12 -> 450 | AE8: =AC8-AD8 -> 0
C9: 5ºAndar Direito | D9: 37.5 | F9: 37.5 | H9: 37.5 | J9: 37.5 | L9: 37.5 | N9: 37.5 | P9: 37.5 | T9: 75 | V9: 37.5 | X9: 37.5 | Z9: 37.5 | AC9: =SUM(D9:AB9) -> 450 | AD9: =37.5*12 -> 450 | AE9: =AC9-AD9 -> 0
C10: 5 Andar Esquerdo | D10: 37.5 | F10: 37.5 | H10: 37.5 | J10: 37.5 | L10: 37.5 | N10: 37.5 | P10: 37.5 | R10: 37.5 | T10: 37.5 | V10: 37.5 | X10: 37.5 | Z10: 37.5 | AC10: =SUM(D10:AB10) -> 450 | AD10: =37.5*12 -> 450 | AE10: =AC10-AD10 -> 0
C11: 4ºAndar Direito | D11: 37.5 | F11: 37.5 | H11: 37.5 | J11: 37.5 | L11: 37.5 | N11: 37.5 | P11: 37.5 | R11: 37.5 | T11: 37.5 | V11: 37.5 | X11: 37.5 | Z11: 37.5 | AC11: =SUM(D11:AB11) -> 450 | AD11: =37.5*12 -> 450 | AE11: =AC11-AD11 -> 0
C12: 4ºAndar Esquerdo | D12: 37.5 | F12: 37.5 | H12: 37.5 | J12: 37.5 | L12: 37.5 | N12: 37.5 | P12: 37.5 | R12: 37.5 | T12: 37.5 | V12: 37.5 | X12: 37.5 | Z12: 37.5 | AC12: =SUM(D12:AB12) -> 450 | AD12: =37.5*12 -> 450 | AE12: =AC12-AD12 -> 0
C13: 3ºAndar Direito | D13: 37.5 | F13: 37.5 | H13: 37.5 | J13: 37.5 | L13: 37.5 | N13: 37.5 | P13: 37.5 | R13: 37.5 | T13: 37.5 | V13: 37.5 | X13: 37.5 | Z13: 37.5 | AC13: =SUM(D13:AB13) -> 450 | AD13: =37.5*12 -> 450 | AE13: =AC13-AD13 -> 0
C14: 3ºAndar Esquerdo | D14: 37.5 | F14: 37.5 | H14: 37.5 | J14: 37.5 | L14: 37.5 | N14: 37.5 | P14: 37.5 | R14: 37.5 | T14: 37.5 | V14: 37.5 | X14: 37.5 | Z14: 37.5 | AC14: =SUM(D14:AB14) -> 450 | AD14: =37.5*12 -> 450 | AE14: =AC14-AD14 -> 0
C15: 2ºAndar Direito | D15: 37.5 | F15: 37.5 | H15: 37.5 | J15: 37.5 | L15: 37.5 | N15: 37.5 | P15: 37.5 | R15: 37.5 | T15: 37.5 | V15: 37.5 | X15: 37.5 | Z15: 37.5 | AC15: =SUM(D15:AB15) -> 450 | AD15: =37.5*12 -> 450 | AE15: =AC15-AD15 -> 0
C16: 2ºAndar Esquerdo | D16: 120.36 | F16: 120.36 | H16: 126.7 | J16: 150.08 | L16: 125 | N16: 125 | AC16: =SUM(D16:AB16) -> 767.5 | AD16: =37.5*12 -> 450 | AE16: =AC16-AD16 -> 317.5
C17: 1ºAndar Direito | AC17: =SUM(D17:AB17) -> 0 | AD17: =37.5*12 -> 450 | AE17: =AC17-AD17 -> -450
C18: 1ºAndar Esquerdo | D18: 37.5 | F18: 37.5 | H18: 37.5 | J18: 37.5 | L18: 37.5 | N18: 37.5 | P18: 37.5 | R18: 37.5 | T18: 37.5 | V18: 37.5 | X18: 37.5 | Z18: 37.5 | AC18: =SUM(D18:AB18) -> 450 | AD18: =37.5*12 -> 450 | AE18: =AC18-AD18 -> 0
C19: Res-Chão Direito | D19: 37.5 | H19: 112.5 | J19: 37.5 | R19: 112.5 | T19: 37.5 | Z19: 112.5 | AC19: =SUM(D19:AB19) -> 450 | AD19: =37.5*12 -> 450 | AE19: =AC19-AD19 -> 0
C20: Res-Chão Esquerdo | D20: 37.5 | F20: 37.5 | H20: 37.5 | J20: 37.5 | L20: 37.5 | N20: 37.5 | P20: 37.5 | R20: 37.5 | T20: 57.5 | V20: 37.5 | X20: 37.5 | AC20: =SUM(D20:AB20) -> 432.5 | AD20: =37.5*12 -> 450 | AE20: =AC20-AD20 -> -17.5
C21: Cave -1 (Garagem) | D21: 37.5 | F21: 37.5 | H21: 37.5 | J21: 37.5 | L21: 37.5 | N21: 37.5 | P21: 37.5 | V21: 112.5 | Z21: 75 | AC21: =SUM(D21:AB21) -> 450 | AD21: =37.5*12 -> 450 | AE21: =AC21-AD21 -> 0
C22: Cave -2 | D22: 37.5 | F22: 37.5 | H22: 37.5 | J22: 37.5 | L22: 37.5 | N22: 37.5 | P22: 37.5 | R22: 37.5 | T22: 37.5 | V22: 37.5 | X22: 37.5 | Z22: 37.5 | AC22: =SUM(D22:AB22) -> 450 | AD22: =37.5*12 -> 450 | AE22: =AC22-AD22 -> 0
AE23: =AC23-AD23 -> 0
C24: Entregas em Numerário | AC24: =SUM(D24:AB24) -> 0
C27: Total Receitas | D27: =D7+D8+D9+D10+D11+D12+D13+D14+D15+D16+D17+D18+D19+D20+D21+D22+D24 -> 830.83 | F27: =F7+F8+F9+F10+F11+F12+F13+F14+F15+F16+F17+F18+F19+F20+F21+F22+F24 -> 532.86 | H27: =H7+H8+H9+H10+H11+H12+H13+H14+H15+H16+H17+H18+H19+H20+H21+H22+H24 -> 726.7 | J27: =J7+J8+J9+J10+J11+J12+J13+J14+J15+J16+J17+J18+J19+J20+J21+J22+J24 -> 637.58 | L27: =L7+L8+L9+L10+L11+L12+L13+L14+L15+L16+L17+L18+L19+L20+L21+L22+L24 -> 537.5 | N27: =N7+N8+N9+N10+N11+N12+N13+N14+N15+N16+N17+N18+N19+N20+N21+N22+N24 -> 612.5 | P27: =P7+P8+P9+P10+P11+P12+P13+P14+P15+P16+P17+P18+P19+P20+P21+P22+P24 -> 450 | R27: =R7+R8+R9+R10+R11+R12+R13+R14+R15+R16+R17+R18+R19+R20+R21+R22+R24 -> 487.5 | T27: =T7+T8+T9+T10+T11+T12+T13+T14+T15+T16+T17+T18+T19+T20+T21+T22+T24 -> 507.5 | V27: =V7+V8+V9+V10+V11+V12+V13+V14+V15+V16+V17+V18+V19+V20+V21+V22+V24 -> 525 | X27: =X7+X8+X9+X10+X11+X12+X13+X14+X15+X16+X17+X18+X19+X20+X21+X22+X24 -> 412.5 | Z27: =Z7+Z8+Z9+Z10+Z11+Z12+Z13+Z14+Z15+Z16+Z17+Z18+Z19+Z20+Z21+Z22+Z24 -> 562.5 | AC27: =SUM(D27:AB27) -> 6822.97
C28: Monte Abraão, 31 de Dezembro de 2012 | K28: A Administração
C29: Condominio Rua Vieira da Silva, 6 | J29: Queluz - Monte Abraão | W29: Ano 2012
A30: DESPESAS
C32: Despesas | D32: Janeiro | F32: Fevereiro | H32: Março | J32: Abril | L32: Maio | N32: Junho | P32: Julho | R32: Agosto | T32: Setembro | V32: Outubro | X32: Novembro | Z32: Dezembro | AC32: TOTAL
C35: Electricidade | D35: 133.93 | F35: 93.24 | H35: 270.96 | L35: 38.4 | N35: 223.75 | R35: 208.29 | V35: 133.32 | X35: 123.1 | Z35: 137.81 | AC35: =SUM(D35:AB35) -> 1362.8
C36: Elevadores | X36: 127.53 | AC36: =SUM(X36:AB36) -> 127.53
C37: Inspecção Elevadores
C38: Manutenção Bombas Água | L38: 159.9 | P38: 162.36 | AC38: =SUM(D38:AB38) -> 322.26
C39: Tribunal / Julgados de Paz | D39: 35 | AC39: =SUM(D39:AB39) -> 35
C40: Tapete | Z40: 4.99 | AC40: =SUM(Z40:AB40) -> 4.99
C41: Despesas Bancárias | D41: 12.48 | F41: 1.04 | J41: 11.44 | N41: 1.04 | P41: 11.44 | T41: 1.04 | V41: 10.4 | AC41: =SUM(D41:AB41) -> 48.88
C42: Pagamento Divída LDC | D42: 250.12 | F42: 500.24 | J42: 504.37 | N42: 508.5 | T42: 508.5 | AC42: =SUM(D42:AB42) -> 2271.73
C43: Material Electrico | D43: 54 | F43: 30.8 | J43: 20 | N43: 50 | P43: 19.79 | R43: 41.48 | X43: 8.5 | AC43: =SUM(D43:AB43) -> 224.57
C44: Material Electrico | D44: 13.5 | N44: 10 | P44: 33.83 | AC44: =SUM(D44:AB44) -> 57.33
C45: Campainhas | N45: 518.76 | P45: 400 | AC45: =SUM(D45:AB45) -> 918.76
C48: Total Despesas | D48: =D35+D36+D37+D38+D39+D40+D41+D42+D43+D44+D45 -> 499.03 | F48: =F35+F36+F37+F38+F39+F40+F41+F42+F43+F44+F45 -> 625.32 | H48: =H35+H36+H37+H38+H39+H40+H41+H42+H43+H44+H45 -> 270.96 | J48: =J35+J36+J37+J38+J39+J40+J41+J42+J43+J44+J45 -> 535.81 | L48: =L35+L36+L37+L38+L39+L40+L41+L42+L43+L44+L45 -> 198.3 | N48: =N35+N36+N37+N38+N39+N40+N41+N42+N43+N44+N45 -> 1312.05 | P48: =P35+P36+P37+P38+P39+P40+P41+P42+P43+P44+P45 -> 627.42 | R48: =R35+R36+R37+R38+R39+R40+R41+R42+R43+R44+R45 -> 249.77 | T48: =T35+T36+T37+T38+T39+T40+T41+T42+T43+T44+T45 -> 509.54 | V48: =V35+V36+V37+V38+V39+V40+V41+V42+V43+V44+V45 -> 143.72 | X48: =X35+X36+X37+X38+X39+X40+X41+X42+X43+X44+X45 -> 259.13 | Z48: =Z35+Z36+Z37+Z38+Z39+Z40+Z41+Z42+Z43+Z44+Z45 -> 142.8 | AC48: =SUM(D48:AB48) -> 5373.85
C54: Resultados Liquidos | D54: =D27-D48 -> 331.8 | F54: =F27-F48 -> -92.46 | H54: =H27-H48 -> 455.74 | J54: =J27-J48 -> 101.77 | L54: =L27-L48 -> 339.2 | N54: =N27-N48 -> -699.55 | P54: =P27-P48 -> -177.42 | R54: =R27-R48 -> 237.73 | T54: =T27-T48 -> -2.04 | V54: =V27-V48 -> 381.28 | X54: =X27-X48 -> 153.37 | Z54: =Z27-Z48 -> 419.7
C58: Valor Transitado do Ano 2011 | D58: 1475.15
C59: Receitas Ano 2012 | D59: =D27+F27+H27+J27+L27+N27+P27+R27+T27+V27+X27+Z27 -> 6822.97
D60: =SUM(D58:D59) -> 8298.12
C61: Despesas Ano 2012 - | D61: =D48+F48+H48+J48+L48+N48+P48+R48+T48+V48+X48+Z48 -> 5373.85
C62: Saldo a transitar para 2013 | D62: =D60-D61 -> 2924.27
C64: Monte Abraão, 31 de Dezembro de 2012 | L64: A Administração

Sheet Receitas Despesas 2013
B1: Condominio Rua Vieira da Silva, 6 | I1: Queluz - Monte Abraão | V1: Ano 2013
B4: Receitas | C4: Janeiro | E4: Fevereiro | G4: Março | I4: Abril | K4: Maio | M4: Junho | O4: Julho | Q4: Agosto | S4: Setembro | U4: Outubro | W4: Novembro | Y4: Dezembro | AB4: TOTAL | AC4: Valor esperado | AD4: valor em divida
B7: 6ºAndar Direito | AB7: =SUM(C7:AA7) -> 0 | AC7: =37.5*12 -> 450 | AD7: =AB7-AC7 -> -450
B8: 6ºAndar Esquerdo | C8: 37.5 | E8: 37.5 | G8: 37.5 | I8: 37.5 | K8: 37.5 | M8: 37.5 | O8: 37.5 | Q8: 37.5 | S8: 37.5 | U8: 37.5 | W8: 37.5 | Y8: 37.5 | AB8: =SUM(C8:AA8) -> 450 | AC8: =37.5*12 -> 450 | AD8: =AB8-AC8 -> 0
B9: 5ºAndar Direito | C9: 37.5 | E9: 37.5 | G9: 37.5 | I9: 37.5 | K9: 37.5 | M9: 37.5 | O9: 37.5 | Q9: 37.5 | S9: 37.5 | U9: 37.5 | W9: 37.5 | Y9: 37.5 | AB9: =SUM(C9:AA9) -> 450 | AC9: =37.5*12 -> 450 | AD9: =AB9-AC9 -> 0
B10: 5 Andar Esquerdo | C10: 37.5 | E10: 37.5 | G10: 37.5 | I10: 37.5 | K10: 37.5 | M10: 37.5 | O10: 37.5 | Q10: 37.5 | S10: 37.5 | U10: 37.5 | W10: 37.5 | Y10: 37.5 | AB10: =SUM(C10:AA10) -> 450 | AC10: =37.5*12 -> 450 | AD10: =AB10-AC10 -> 0
B11: 4ºAndar Direito | C11: 37.5 | E11: 37.5 | G11: 37.5 | I11: 37.5 | K11: 37.5 | M11: 37.5 | O11: 37.5 | Q11: 37.5 | S11: 37.5 | U11: 37.5 | W11: 37.5 | Y11: 37.5 | AB11: =SUM(C11:AA11) -> 450 | AC11: =37.5*12 -> 450 | AD11: =AB11-AC11 -> 0
B12: 4ºAndar Esquerdo | C12: 37.5 | E12: 37.5 | G12: 37.5 | I12: 37.5 | K12: 37.5 | M12: 37.5 | O12: 37.5 | Q12: 37.5 | S12: 37.5 | U12: 37.5 | W12: 37.5 | Y12: 37.5 | AB12: =SUM(C12:AA12) -> 450 | AC12: =37.5*12 -> 450 | AD12: =AB12-AC12 -> 0
B13: 3ºAndar Direito | C13: 37.5 | E13: 37.5 | G13: 37.5 | I13: 75 | K13: 37.5 | O13: 107.5 | Q13: 5 | S13: 37.5 | U13: 37.5 | W13: 37.5 | Y13: 37.5 | AB13: =SUM(C13:AA13) -> 487.5 | AC13: =37.5*12 -> 450 | AD13: =AB13-AC13 -> 37.5
B14: 3ºAndar Esquerdo | C14: 37.5 | E14: 37.5 | G14: 37.5 | I14: 37.5 | K14: 37.5 | M14: 37.5 | O14: 37.5 | Q14: 37.5 | U14: 75 | W14: 37.5 | Y14: 37.5 | AB14: =SUM(C14:AA14) -> 450 | AC14: =37.5*12 -> 450 | AD14: =AB14-AC14 -> 0
B15: 2ºAndar Direito | C15: 37.5 | E15: 37.5 | G15: 37.5 | I15: 37.5 | K15: 37.5 | M15: 37.5 | O15: 37.5 | Q15: 37.5 | U15: 75 | W15: 37.5 | Y15: 37.5 | AB15: =SUM(C15:AA15) -> 450 | AC15: =37.5*12 -> 450 | AD15: =AB15-AC15 -> 0
B16: 2ºAndar Esquerdo | AB16: =SUM(C16:AA16) -> 0 | AC16: =37.5*12 -> 450 | AD16: =AB16-AC16 -> -450
B17: 1ºAndar Direito | M17: 62.5 | O17: 67.5 | Q17: 35 | AB17: =SUM(C17:AA17) -> 165 | AC17: =37.5*12 -> 450 | AD17: =AB17-AC17 -> -285
B18: 1ºAndar Esquerdo | C18: 37.5 | E18: 37.5 | G18: 37.5 | I18: 37.5 | K18: 37.5 | M18: 37.5 | O18: 37.5 | Q18: 37.5 | S18: 37.5 | U18: 75 | Y18: 75 | AB18: =SUM(C18:AA18) -> 487.5 | AC18: =37.5*12 -> 450 | AD18: =AB18-AC18 -> 37.5
B19: Res-Chão Direito | E19: 37.5 | G19: 112.5 | S19: 187.5 | AB19: =SUM(C19:AA19) -> 337.5 | AC19: =37.5*12 -> 450 | AD19: =AB19-AC19 -> -112.5
B20: Res-Chão Esquerdo | M20: 80 | S20: 37.5 | Y20: 74.37 | AB20: =SUM(C20:AA20) -> 191.87 | AC20: =37.5*12 -> 450 | AD20: =AB20-AC20 -> -258.13
B21: Cave -1 (Garagem) | AB21: =SUM(C21:AA21) -> 0 | AC21: =37.5*12 -> 450 | AD21: =AB21-AC21 -> -450
B22: Cave -2 | C22: 37.5 | E22: 37.5 | G22: 37.5 | I22: 37.5 | K22: 37.5 | M22: 37.5 | O22: 37.5 | Q22: 37.5 | S22: 37.5 | U22: 37.5 | W22: 37.5 | Y22: 37.5 | AB22: =SUM(C22:AA22) -> 450 | AC22: =37.5*12 -> 450 | AD22: =AB22-AC22 -> 0
AC23: =37.5*12 -> 450 | AD23: =AB23-AC23 -> -450
B24: Entregas em Numerário | AB24: =SUM(C24:AA24) -> 0 | AC24: =37.5*12 -> 450 | AD24: =AB24-AC24 -> -450
B27: Total Receitas | C27: =C7+C8+C9+C10+C11+C12+C13+C14+C15+C16+C17+C18+C19+C20+C21+C22+C24 -> 375 | E27: =E7+E8+E9+E10+E11+E12+E13+E14+E15+E16+E17+E18+E19+E20+E21+E22+E24 -> 412.5 | G27: =G7+G8+G9+G10+G11+G12+G13+G14+G15+G16+G17+G18+G19+G20+G21+G22+G24 -> 487.5 | I27: =I7+I8+I9+I10+I11+I12+I13+I14+I15+I16+I17+I18+I19+I20+I21+I22+I24 -> 412.5 | K27: =K7+K8+K9+K10+K11+K12+K13+K14+K15+K16+K17+K18+K19+K20+K21+K22+K24 -> 375 | M27: =M7+M8+M9+M10+M11+M12+M13+M14+M15+M16+M17+M18+M19+M20+M21+M22+M24 -> 480 | O27: =O7+O8+O9+O10+O11+O12+O13+O14+O15+O16+O17+O18+O19+O20+O21+O22+O24 -> 512.5 | Q27: =Q7+Q8+Q9+Q10+Q11+Q12+Q13+Q14+Q15+Q16+Q17+Q18+Q19+Q20+Q21+Q22+Q24 -> 377.5 | S27: =S7+S8+S9+S10+S11+S12+S13+S14+S15+S16+S17+S18+S19+S20+S21+S22+S24 -> 525 | U27: =U7+U8+U9+U10+U11+U12+U13+U14+U15+U16+U17+U18+U19+U20+U21+U22+U24 -> 487.5 | W27: =W7+W8+W9+W10+W11+W12+W13+W14+W15+W16+W17+W18+W19+W20+W21+W22+W24 -> 337.5 | Y27: =Y7+Y8+Y9+Y10+Y11+Y12+Y13+Y14+Y15+Y16+Y17+Y18+Y19+Y20+Y21+Y22+Y24 -> 486.87 | AB27: =SUM(AB7:AB26) -> 5269.37
B31: Despesas | C31: Janeiro | E31: Fevereiro | G31: Março | I31: Abril | K31: Maio | M31: Junho | O31: Julho | Q31: Agosto | S31: Setembro | U31: Outubro | W31: Novembro | Y31: Dezembro | AB31: TOTAL
B34: Electricidade | C34: 125.99 | E34: 102.94 | G34: 133.85 | I34: 115.86 | K34: 93.13 | M34: 131.87 | O34: 117.7 | Q34: 134.58 | S34: 247.74 | W34: 103.47 | Y34: 138.19 | AB34: =SUM(C34:AA34) -> 1445.32
B35: Elevadores | C35: 299.73 | E35: 127.53 | I35: 127.53 | K35: 127.53 | M35: 127.53 | O35: 127.53 | Q35: 127.53 | S35: 127.53 | U35: 382.59 | W35: 137.74 | Y35: 137.74 | AB35: =SUM(C35:AA35) -> 1850.51
B36: Inspecção Elevadores | S36: 400 | AB36: =SUM(C36:AA36) -> 400
B37: Manutenção Bombas Água | C37: 162.36 | E37: 442.8 | AB37: =SUM(C37:AA37) -> 605.16
B38: Tribunal / Julgados de Paz | G38: 35 | AB38: =SUM(C38:AA38) -> 35
B39: Material Obras / Cimento | U39: 4.38 | AB39: =SUM(C39:AA39) -> 4.38
B40: Despesas Bancárias | C40: 6.24 | E40: 1.04 | I40: 5.2 | O40: 14.99 | U40: 6.24 | AB40: =SUM(C40:AA40) -> 33.71
B41: Pag. Factura Extintores | U41: 288.07 | AB41: =SUM(C41:AA41) -> 288.07
B42: Material Electrico | I42: 41.57 | K42: 10.89 | M42: 35.5 | O42: 94.86 | S42: 26.71 | Y42: 3.8 | AB42: =SUM(C42:AA42) -> 213.33
B43: Luzes Emergência | M43: 14.76 | S43: 239.85 | U43: 255.84 | AB43: =SUM(C43:AA43) -> 510.45
B44: Janela Telhado | S44: 16.17 | AB44: =SUM(C44:AA44) -> 16.17
B45: Diversos / CTT | W45: 5.22 | AB45: =SUM(C45:AA45) -> 5.22
B48: Total Despesas | C48: =C34+C35+C36+C37+C38+C39+C40+C41+C42+C43+C45+C44 -> 594.32 | E48: =E34+E35+E36+E37+E38+E39+E40+E41+E42+E43+E45+E44 -> 674.31 | G48: =G34+G35+G36+G37+G38+G39+G40+G41+G42+G43+G45+G44 -> 168.85 | I48: =I34+I35+I36+I37+I38+I39+I40+I41+I42+I43+I45+I44 -> 290.16 | K48: =K34+K35+K36+K37+K38+K39+K40+K41+K42+K43+K45+K44 -> 231.55 | M48: =M34+M35+M36+M37+M38+M39+M40+M41+M42+M43+M45+M44 -> 309.66 | O48: =O34+O35+O36+O37+O38+O39+O40+O41+O42+O43+O45+O44 -> 355.08 | Q48: =Q34+Q35+Q36+Q37+Q38+Q39+Q40+Q41+Q42+Q43+Q45+Q44 -> 262.11 | S48: =S34+S35+S36+S37+S38+S39+S40+S41+S42+S43+S45+S44 -> 1058 | U48: =U34+U35+U36+U37+U38+U39+U40+U41+U42+U43+U45+U44 -> 937.12 | W48: =W34+W35+W36+W37+W38+W39+W40+W41+W42+W43+W45+W44 -> 246.43 | Y48: =Y34+Y35+Y36+Y37+Y38+Y39+Y40+Y41+Y42+Y43+Y45+Y44 -> 279.73 | AB48: =SUM(AB34:AB47) -> 5407.32
B54: Resultados Liquidos | C54: =C27-C48 -> -219.32 | E54: =E27-E48 -> -261.81 | G54: =G27-G48 -> 318.65 | I54: =I27-I48 -> 122.34 | K54: =K27-K48 -> 143.45 | M54: =M27-M48 -> 170.34 | O54: =O27-O48 -> 157.42 | Q54: =Q27-Q48 -> 115.39 | S54: =S27-S48 -> -533 | U54: =U27-U48 -> -449.62 | W54: =W27-W48 -> 91.07 | Y54: =Y27-Y48 -> 207.14
B58: Valor Transitado do Ano 2012 | C58: 2924.27 | O58: Monte Abraão, 31 de Dezembro de 2013 | W58: A Administração
B59: Receitas Ano 2013 | C59: =C27+E27+G27+I27+K27+M27+O27+Q27+S27+U27+W27+Y27 -> 5269.37
C60: =SUM(C58:C59) -> 8193.64
B61: Despesas Ano 2013 - | C61: =C48+E48+G48+I48+K48+M48+O48+Q48+S48+U48+W48+Y48 -> 5407.32
B62: Saldo que transitou para 2014 | C62: =C60-C61 -> 2786.32

Sheet Receitas Despesas 2014
C1: Condominio Rua Vieira da Silva, 6 | J1: Queluz - Monte Abraão | W1: Ano 2014
C2: RECEITAS
C4: Receitas | D4: Janeiro | F4: Fevereiro | H4: Março | J4: Abril | L4: Maio | N4: Junho | P4: Julho | R4: Agosto | T4: Setembro | V4: Outubro | X4: Novembro | Z4: Dezembro | AC4: TOTAL | AD4: Valor previsto | AE4: Valor divida
C7: 6ºAndar Direito | R7: 32.5 | T7: 32.5 | AC7: =SUM(D7:AB7) -> 65 | AD7: =37.5*12 -> 450 | AE7: =AC7-AD7 -> -385
C8: 6ºAndar Esquerdo | D8: 37.5 | F8: 37.5 | H8: 37.5 | J8: 37.5 | L8: 37.5 | N8: 37.5 | P8: 37.5 | R8: 37.5 | T8: 37.5 | V8: 37.5 | X8: 37.5 | Z8: 37.5 | AC8: =SUM(D8:AB8) -> 450 | AD8: =37.5*12 -> 450 | AE8: =AC8-AD8 -> 0
C9: 5ºAndar Direito | D9: 37.5 | F9: 37.5 | H9: 37.5 | J9: 37.5 | L9: 37.5 | N9: 37.5 | P9: 37.5 | R9: 37.5 | T9: 37.5 | V9: 37.5 | X9: 37.5 | AC9: =SUM(D9:AB9) -> 412.5 | AD9: =37.5*12 -> 450 | AE9: =AC9-AD9 -> -37.5
C10: 5 Andar Esquerdo | D10: 37.5 | F10: 37.5 | H10: 37.5 | J10: 37.5 | L10: 37.5 | N10: 37.5 | P10: 37.5 | R10: 37.5 | T10: 37.5 | V10: 37.5 | X10: 37.5 | Z10: 37.5 | AC10: =SUM(D10:AB10) -> 450 | AD10: =37.5*12 -> 450 | AE10: =AC10-AD10 -> 0
C11: 4ºAndar Direito | D11: 37.5 | F11: 37.5 | H11: 37.5 | J11: 37.5 | L11: 37.5 | N11: 37.5 | P11: 37.5 | R11: 37.5 | T11: 37.5 | V11: 37.5 | X11: 37.5 | Z11: 37.5 | AC11: =SUM(D11:AB11) -> 450 | AD11: =37.5*12 -> 450 | AE11: =AC11-AD11 -> 0
C12: 4ºAndar Esquerdo | D12: 37.5 | F12: 37.5 | H12: 37.5 | J12: 37.5 | L12: 37.5 | N12: 37.5 | P12: 37.5 | R12: 37.5 | T12: 37.5 | V12: 75 | Z12: 37.5 | AC12: =SUM(D12:AB12) -> 450 | AD12: =37.5*12 -> 450 | AE12: =AC12-AD12 -> 0
C13: 3ºAndar Direito | D13: 37.5 | F13: 37.5 | H13: 37.5 | J13: 37.5 | L13: 37.5 | N13: 37.5 | P13: 37.5 | T13: 37.5 | V13: 75 | X13: 37.5 | Z13: 37.5 | AC13: =SUM(D13:AB13) -> 450 | AD13: =37.5*12 -> 450 | AE13: =AC13-AD13 -> 0
C14: 3ºAndar Esquerdo | D14: 37.5 | F14: 37.5 | H14: 37.5 | J14: 37.5 | L14: 37.5 | N14: 37.5 | P14: 37.5 | R14: 37.5 | T14: 37.5 | V14: 37.5 | Z14: 75 | AC14: =SUM(D14:AB14) -> 450 | AD14: =37.5*12 -> 450 | AE14: =AC14-AD14 -> 0
C15: 2ºAndar Direito | D15: 37.5 | F15: 37.5 | H15: 37.5 | J15: 37.5 | L15: 37.5 | N15: 37.5 | P15: 37.5 | R15: 37.5 | T15: 37.5 | V15: 37.5 | X15: 37.5 | Z15: 37.5 | AC15: =SUM(D15:AB15) -> 450 | AD15: =37.5*12 -> 450 | AE15: =AC15-AD15 -> 0
C16: 2ºAndar Esquerdo | AC16: =SUM(D16:AB16) -> 0 | AD16: =37.5*12 -> 450 | AE16: =AC16-AD16 -> -450
C17: 1ºAndar Direito | AC17: =SUM(D17:AB17) -> 0 | AD17: =37.5*12 -> 450 | AE17: =AC17-AD17 -> -450
C18: 1ºAndar Esquerdo | F18: 37.5 | H18: 37.5 | J18: 37.5 | L18: 37.5 | N18: 37.5 | P18: 75 | T18: 37.5 | V18: 75 | Z18: 37.5 | AC18: =SUM(D18:AB18) -> 412.5 | AD18: =37.5*12 -> 450 | AE18: =AC18-AD18 -> -37.5
C19: Res-Chão Direito | H19: 375 | X19: 187.5 | AC19: =SUM(D19:AB19) -> 562.5 | AD19: =37.5*12 -> 450 | AE19: =AC19-AD19 -> 112.5
C20: Res-Chão Esquerdo | D20: 50 | F20: 50 | H20: 50 | N20: 37.5 | P20: 37.5 | R20: 37.5 | T20: 37 | V20: 40 | X20: 40 | AC20: =SUM(D20:AB20) -> 379.5 | AD20: =37.5*12 -> 450 | AE20: =AC20-AD20 -> -70.5
C21: Cave -1 (Garagem) | J21: 115.5 | L21: 115.5 | N21: 115.5 | P21: 115.5 | T21: 115.5 | V21: 115.5 | X21: 115.5 | Z21: 115.5 | AC21: =SUM(D21:AB21) -> 924 | AD21: =37.5*12 -> 450 | AE21: =AC21-AD21 -> 474
C22: Cave -2 | D22: 37.5 | F22: 37.5 | H22: 37.5 | J22: 37.5 | L22: 37.5 | N22: 37.5 | P22: 37.5 | R22: 37.5 | T22: 37.5 | V22: 37.5 | X22: 37.5 | Z22: 37.5 | AC22: =SUM(D22:AB22) -> 450 | AD22: =37.5*12 -> 450 | AE22: =AC22-AD22 -> 0
AD23: =37.5*12 -> 450 | AE23: =AC23-AD23 -> -450
AC24: =SUM(D24:AB24) -> 0 | AD24: =37.5*12 -> 450 | AE24: =AC24-AD24 -> -450
AE25: =AC25-AD25 -> 0
C27: Total Receitas | D27: =D7+D8+D9+D10+D11+D12+D13+D14+D15+D16+D17+D18+D19+D20+D21+D22+D24 -> 387.5 | F27: =F7+F8+F9+F10+F11+F12+F13+F14+F15+F16+F17+F18+F19+F20+F21+F22+F24 -> 425 | H27: =H7+H8+H9+H10+H11+H12+H13+H14+H15+H16+H17+H18+H19+H20+H21+H22+H24 -> 800 | J27: =J7+J8+J9+J10+J11+J12+J13+J14+J15+J16+J17+J18+J19+J20+J21+J22+J24 -> 490.5 | L27: =L7+L8+L9+L10+L11+L12+L13+L14+L15+L16+L17+L18+L19+L20+L21+L22+L24 -> 490.5 | N27: =N7+N8+N9+N10+N11+N12+N13+N14+N15+N16+N17+N18+N19+N20+N21+N22+N24 -> 528 | P27: =P7+P8+P9+P10+P11+P12+P13+P14+P15+P16+P17+P18+P19+P20+P21+P22+P24 -> 565.5 | R27: =R7+R8+R9+R10+R11+R12+R13+R14+R15+R16+R17+R18+R19+R20+R21+R22+R24 -> 370 | T27: =T7+T8+T9+T10+T11+T12+T13+T14+T15+T16+T17+T18+T19+T20+T21+T22+T24 -> 560 | V27: =V7+V8+V9+V10+V11+V12+V13+V14+V15+V16+V17+V18+V19+V20+V21+V22+V24 -> 643 | X27: =X7+X8+X9+X10+X11+X12+X13+X14+X15+X16+X17+X18+X19+X20+X21+X22+X24 -> 605.5 | Z27: =Z7+Z8+Z9+Z10+Z11+Z12+Z13+Z14+Z15+Z16+Z17+Z18+Z19+Z20+Z21+Z22+Z24 -> 490.5 | AC27: =SUM(D27:AB27) -> 6356
C28: Monte Abraão, 31 de Dezembro de 2014 | K28: A Administração
C29: Condominio Rua Vieira da Silva, 6 | J29: Queluz - Monte Abraão | W29: Ano 2014
A30: DESPESAS
C32: Despesas | D32: Janeiro | F32: Fevereiro | H32: Março | J32: Abril | L32: Maio | N32: Junho | P32: Julho | R32: Agosto | T32: Setembro | V32: Outubro | X32: Novembro | Z32: Dezembro | AC32: TOTAL
C35: Electricidade | D35: 228.73 | H35: 151.5 | J35: 126.15 | L35: 66.76 | N35: 118.83 | P35: 116.97 | R35: 110.52 | T35: 127.62 | V35: 125.42 | X35: 90.35 | Z35: 121.61 | AC35: =SUM(D35:AB35) -> 1384.46
C36: Elevadores | D36: 137.74 | F36: 137.74 | H36: 137.74 | J36: 137.74 | L36: 137.74 | N36: 137.74 | P36: 137.74 | R36: 137.74 | T36: 137.74 | V36: 137.74 | X36: 143.25 | Z36: 143.25 | AC36: =SUM(D36:AB36) -> 1663.9
C37: Inspecção Elevadores | AC37: =SUM(X37:AB37) -> 0
C38: Reparação Elevadores | X38: 233.83 | AC38: =SUM(D38:AB38) -> 233.83
C39: Tribunal / Julgados de Paz | AC39: =SUM(D39:AB39) -> 0
C40: Manutenção Extintores | F40: 48 | AC40: =SUM(Z40:AB40) -> 0
C41: Despesas Bancárias | D41: 5.2 | J41: 5.2 | AC41: =SUM(D41:AB41) -> 10.4
AC42: =SUM(D42:AB42) -> 0
C43: Material Electrico | F43: 1.53 | AC43: =SUM(D43:AB43) -> 1.53
AC44: =SUM(D44:AB44) -> 0
AC45: =SUM(D45:AB45) -> 0
C48: Total Despesas | D48: =D35+D36+D37+D38+D39+D40+D41+D42+D43+D44+D45 -> 371.67 | F48: =F35+F36+F37+F38+F39+F40+F41+F42+F43+F44+F45 -> 187.27 | H48: =H35+H36+H37+H38+H39+H40+H41+H42+H43+H44+H45 -> 289.24 | J48: =J35+J36+J37+J38+J39+J40+J41+J42+J43+J44+J45 -> 269.09 | L48: =L35+L36+L37+L38+L39+L40+L41+L42+L43+L44+L45 -> 204.5 | N48: =N35+N36+N37+N38+N39+N40+N41+N42+N43+N44+N45 -> 256.57 | P48: =P35+P36+P37+P38+P39+P40+P41+P42+P43+P44+P45 -> 254.71 | R48: =R35+R36+R37+R38+R39+R40+R41+R42+R43+R44+R45 -> 248.26 | T48: =T35+T36+T37+T38+T39+T40+T41+T42+T43+T44+T45 -> 265.36 | V48: =V35+V36+V37+V38+V39+V40+V41+V42+V43+V44+V45 -> 263.16 | X48: =X35+X36+X37+X38+X39+X40+X41+X42+X43+X44+X45 -> 467.43 | Z48: =Z35+Z36+Z37+Z38+Z39+Z40+Z41+Z42+Z43+Z44+Z45 -> 264.86 | AC48: =SUM(D48:AB48) -> 3342.12
AC52: Total Liquido
C54: Resultados Liquidos | D54: =D27-D48 -> 15.83 | F54: =F27-F48 -> 237.73 | H54: =H27-H48 -> 510.76 | J54: =J27-J48 -> 221.41 | L54: =L27-L48 -> 286 | N54: =N27-N48 -> 271.43 | P54: =P27-P48 -> 310.79 | R54: =R27-R48 -> 121.74 | T54: =T27-T48 -> 294.64 | V54: =V27-V48 -> 379.84 | X54: =X27-X48 -> 138.07 | Z54: =Z27-Z48 -> 225.64 | AC54: =SUM(D54:AB54) -> 3013.88
C58: Valor Transitado do Ano 2013 | D58: 2786.32
C59: Receitas Ano 2014 | D59: =D27+F27+H27+J27+L27+N27+P27+R27+T27+V27+X27+Z27 -> 6356
D60: =SUM(D58:D59) -> 9142.32
C61: Despesas Ano 2014 - | D61: =D48+F48+H48+J48+L48+N48+P48+R48+T48+V48+X48+Z48 -> 3342.12
C62: Saldo a transitar para 2015 | D62: =D60-D61 -> 5800.2
C64: Monte Abraão, 31 de Dezembro de 2014 | L64: A Administração

Sheet Receitas Despesas 2015
C1: Condominio Rua Vieira da Silva, 6 | J1: Queluz - Monte Abraão | W1: Ano 2015
C2: RECEITAS
C4: Receitas | D4: Janeiro | F4: Fevereiro | H4: Março | J4: Abril | L4: Maio | N4: Junho | P4: Julho | R4: Agosto | T4: Setembro | V4: Outubro | X4: Novembro | Z4: Dezembro | AC4: TOTAL | AD4: Valor previsto | AE4: Valor em divida
C7: 6ºAndar Direito | D7: 37.5 | F7: 37.5 | H7: 37.5 | Z7: 41.81 | AC7: =SUM(D7:AB7) -> 154.31 | AD7: =37.5*12 -> 450 | AE7: =AC7-AD7 -> -295.69
C8: 6ºAndar Esquerdo | F8: 37.5 | H8: 75 | J8: 37.5 | L8: 37.5 | N8: 37.5 | P8: 37.5 | R8: 37.5 | T8: 37.5 | V8: 37.5 | X8: 37.5 | Z8: 37.5 | AC8: =SUM(D8:AB8) -> 450 | AD8: =37.5*12 -> 450 | AE8: =AC8-AD8 -> 0
C9: 5ºAndar Direito | D9: 75 | F9: 37.5 | H9: 37.5 | N9: 37.5 | V9: 37.5 | Z9: 37.5 | AC9: =SUM(D9:AB9) -> 262.5 | AD9: =37.5*12 -> 450 | AE9: =AC9-AD9 -> -187.5
C10: 5 Andar Esquerdo | D10: 37.5 | F10: 37.5 | H10: 37.5 | J10: 37.5 | L10: 37.5 | N10: 37.5 | P10: 37.5 | R10: 37.5 | T10: 37.5 | V10: 37.5 | X10: 37.5 | Z10: 37.5 | AC10: =SUM(D10:AB10) -> 450 | AD10: =37.5*12 -> 450 | AE10: =AC10-AD10 -> 0
C11: 4ºAndar Direito | D11: 37.5 | F11: 37.5 | L11: 18.75 | N11: 18.75 | P11: 18.75 | R11: 18.75 | T11: 18.75 | V11: 18.75 | X11: 18.75 | Z11: 18.75 | AC11: =SUM(D11:AB11) -> 225 | AD11: =18.75*12 -> 225 | AE11: =AC11-AD11 -> 0
C12: 4ºAndar Esquerdo | D12: 37.5 | F12: 37.5 | H12: 37.5 | J12: 37.5 | L12: 37.5 | N12: 37.5 | P12: 37.5 | R12: 37.5 | T12: 37.5 | V12: 37.5 | X12: 37.5 | Z12: 37.5 | AC12: =SUM(D12:AB12) -> 450 | AD12: =37.5*12 -> 450 | AE12: =AC12-AD12 -> 0
C13: 3ºAndar Direito | D13: 37.5 | F13: 37.5 | H13: 37.5 | J13: 37.5 | L13: 37.5 | N13: 37.5 | P13: 37.5 | R13: 37.5 | V13: 75 | Z13: 37.5 | AC13: =SUM(D13:AB13) -> 412.5 | AD13: =37.5*12 -> 450 | AE13: =AC13-AD13 -> -37.5
C14: 3ºAndar Esquerdo | D14: 37.5 | F14: 37.5 | J14: 37.5 | L14: 37.5 | N14: 37.5 | T14: 70 | V14: 42.5 | X14: 37.5 | Z14: 37.5 | AC14: =SUM(D14:AB14) -> 375 | AD14: =37.5*12 -> 450 | AE14: =AC14-AD14 -> -75
C15: 2ºAndar Direito | D15: 37.5 | F15: 37.5 | H15: 37.5 | J15: 37.5 | L15: 37.5 | N15: 37.5 | P15: 37.5 | R15: 37.5 | T15: 37.5 | V15: 37.5 | X15: 37.5 | Z15: 37.5 | AC15: =SUM(D15:AB15) -> 450 | AD15: =37.5*12 -> 450 | AE15: =AC15-AD15 -> 0
C16: 2ºAndar Esquerdo | V16: 37.5 | X16: 37.5 | Z16: 37.5 | AC16: =SUM(D16:AB16) -> 112.5 | AD16: =37.5*12 -> 450 | AE16: =AC16-AD16 -> -337.5
C17: 1ºAndar Direito | Z17: 1818.63 | AC17: =SUM(D17:AB17) -> 1818.63 | AD17: =37.5*12 -> 450 | AE17: =AC17-AD17 -> 1368.63
C18: 1ºAndar Esquerdo | D18: 37.5 | F18: 37.5 | H18: 37.5 | J18: 37.5 | L18: 37.5 | N18: 37.5 | P18: 37.5 | R18: 37.5 | T18: 37.5 | V18: 37.5 | X18: 37.5 | Z18: 75 | AC18: =SUM(D18:AB18) -> 487.5 | AD18: =37.5*12 -> 450 | AE18: =AC18-AD18 -> 37.5
C19: Res-Chão Direito | F19: 37.5 | H19: 37.5 | L19: 37.5 | N19: 112.5 | R19: 75 | X19: 75 | AC19: =SUM(D19:AB19) -> 375 | AD19: =37.5*12 -> 450 | AE19: =AC19-AD19 -> -75
C20: Res-Chão Esquerdo | D20: 45 | F20: 45 | H20: 40 | J20: 40 | N20: 50 | R20: 60 | T20: 45 | X20: 50 | Z20: 70 | AC20: =SUM(D20:AB20) -> 445 | AD20: =37.5*12 -> 450 | AE20: =AC20-AD20 -> -5
C21: Cave -1 (Garagem) | P21: 231 | V21: 231 | AC21: =SUM(D21:AB21) -> 462 | AD21: =37.5*12 -> 450 | AE21: =AC21-AD21 -> 12
C22: Cave -2 | D22: 37.5 | F22: 37.5 | H22: 37.5 | J22: 37.5 | L22: 37.5 | N22: 37.5 | P22: 37.5 | R22: 37.5 | T22: 37.5 | V22: 37.5 | X22: 37.5 | Z22: 37.5 | AC22: =SUM(D22:AB22) -> 450 | AD22: =37.5*12 -> 450 | AE22: =AC22-AD22 -> 0
AD23: =37.5*12 -> 450 | AE23: =AC23-AD23 -> -450
C24: HEFESTO 2º ESQ./EDP comercial | V24: 187.5 | X24: 85.27 | AC24: =SUM(D24:AB24) -> 272.77 | AD24: =37.5*12 -> 450 | AE24: =AC24-AD24 -> -177.23
C27: Total Receitas | D27: =D7+D8+D9+D10+D11+D12+D13+D14+D15+D16+D17+D18+D19+D20+D21+D22+D24 -> 457.5 | F27: =F7+F8+F9+F10+F11+F12+F13+F14+F15+F16+F17+F18+F19+F20+F21+F22+F24 -> 495 | H27: =H7+H8+H9+H10+H11+H12+H13+H14+H15+H16+H17+H18+H19+H20+H21+H22+H24 -> 452.5 | J27: =J7+J8+J9+J10+J11+J12+J13+J14+J15+J16+J17+J18+J19+J20+J21+J22+J24 -> 340 | L27: =L7+L8+L9+L10+L11+L12+L13+L14+L15+L16+L17+L18+L19+L20+L21+L22+L24 -> 356.25 | N27: =N7+N8+N9+N10+N11+N12+N13+N14+N15+N16+N17+N18+N19+N20+N21+N22+N24 -> 518.75 | P27: =P7+P8+P9+P10+P11+P12+P13+P14+P15+P16+P17+P18+P19+P20+P21+P22+P24 -> 512.25 | R27: =R7+R8+R9+R10+R11+R12+R13+R14+R15+R16+R17+R18+R19+R20+R21+R22+R24 -> 416.25 | T27: =T7+T8+T9+T10+T11+T12+T13+T14+T15+T16+T17+T18+T19+T20+T21+T22+T24 -> 358.75 | V27: =V7+V8+V9+V10+V11+V12+V13+V14+V15+V16+V17+V18+V19+V20+V21+V22+V24 -> 854.75 | X27: =X7+X8+X9+X10+X11+X12+X13+X14+X15+X16+X17+X18+X19+X20+X21+X22+X24 -> 529.02 | Z27: =Z7+Z8+Z9+Z10+Z11+Z12+Z13+Z14+Z15+Z16+Z17+Z18+Z19+Z20+Z21+Z22+Z24 -> 2361.69 | AC27: =SUM(D27:AB27) -> 7652.71
C28: Monte Abraão, 31 de Dezembro de 2015 | K28: A Administração
C29: Condominio Rua Vieira da Silva, 6 | J29: Queluz - Monte Abraão | W29: Ano 2015
A30: DESPESAS
C32: Despesas | D32: Janeiro | F32: Fevereiro | H32: Março | J32: Abril | L32: Maio | N32: Junho | P32: Julho | R32: Agosto | T32: Setembro | V32: Outubro | X32: Novembro | Z32: Dezembro | AC32: TOTAL
C35: Electricidade | D35: 128.03 | F35: 128.26 | H35: 133.76 | J35: 129.95 | L35: 84.47 | N35: 117.88 | P35: 118.3 | T35: 316.11 | X35: 236.67 | AC35: =SUM(D35:AB35) -> 1393.43
C36: Elevadores | D36: 143.25 | F36: 143.25 | H36: 143.25 | J36: 143.25 | L36: 143.25 | N36: 143.25 | P36: 143.25 | R36: 143.25 | T36: 143.25 | V36: 458.75 | X36: 460.62 | AC36: =SUM(D36:AB36) -> 2208.62
C37: Inspecção Elevadores | R37: 340 | AC37: =SUM(D37:AB37) -> 340
C38: Reparação Campainhas | H38: 150 | AC38: =SUM(D38:AB38) -> 150
C39: Tribunal / Julgados de Paz | V39: 400 | Z39: 350 | AC39: =SUM(D39:AB39) -> 750
C40: Manutenção Extintores | F40: 50 | AC40: =SUM(D40:AB40) -> 50
C41: Despesas Bancárias | H41: 1.04 | L41: 1.04 | V41: 1.04 | Z41: 1.04 | AC41: =SUM(D41:AB41) -> 4.16
C42: Produtos Limpeza e Limpeza | F42: 10.3 | H42: 65 | J42: 59.98 | L42: 57 | N42: 65 | P42: 65 | R42: 65 | X42: 176 | AC42: =SUM(D42:AB42) -> 563.28
C43: Manutenção Geral Edificio | F43: 20 | P43: 16.59 | T43: 72 | AC43: =SUM(D43:AB43) -> 108.59
C44: Lampadas Hall Entrada | F44: 7 | AC44: =SUM(D44:AB44) -> 7
C45: Depósitos a Prazo e Poupança | F45: 1000 | H45: 60 | J45: 60 | L45: 60 | N45: 60 | P45: 60 | R45: 60 | T45: 60 | V45: 60 | X45: 60 | Z45: 60 | AC45: =SUM(D45:AB45) -> 1600
C48: Total Despesas | D48: =D35+D36+D37+D38+D39+D40+D41+D42+D43+D44+D45 -> 271.28 | F48: =F35+F36+F37+F38+F39+F40+F41+F42+F43+F44+F45 -> 1358.81 | H48: =H35+H36+H37+H38+H39+H40+H41+H42+H43+H44+H45 -> 553.05 | J48: =J35+J36+J37+J38+J39+J40+J41+J42+J43+J44+J45 -> 393.18 | L48: =L35+L36+L37+L38+L39+L40+L41+L42+L43+L44+L45 -> 345.76 | N48: =N35+N36+N37+N38+N39+N40+N41+N42+N43+N44+N45 -> 386.13 | P48: =P35+P36+P37+P38+P39+P40+P41+P42+P43+P44+P45 -> 403.14 | R48: =R35+R36+R37+R38+R39+R40+R41+R42+R43+R44+R45 -> 608.25 | T48: =T35+T36+T37+T38+T39+T40+T41+T42+T43+T44+T45 -> 591.36 | V48: =V35+V36+V37+V38+V39+V40+V41+V42+V43+V44+V45 -> 919.79 | X48: =X35+X36+X37+X38+X39+X40+X41+X42+X43+X44+X45 -> 933.29 | Z48: =Z35+Z36+Z37+Z38+Z39+Z40+Z41+Z42+Z43+Z44+Z45 -> 411.04 | AC48: =SUM(D48:AB48) -> 7175.08
AC52: Total Liquido
C54: Resultados Liquidos | D54: =D27-D48 -> 186.22 | F54: =F27-F48 -> -863.81 | H54: =H27-H48 -> -100.55 | J54: =J27-J48 -> -53.18 | L54: =L27-L48 -> 10.49 | N54: =N27-N48 -> 132.62 | P54: =P27-P48 -> 109.11 | R54: =R27-R48 -> -192 | T54: =T27-T48 -> -232.61 | V54: =V27-V48 -> -65.04 | X54: =X27-X48 -> -404.27 | Z54: =Z27-Z48 -> 1950.65 | AC54: =SUM(D54:AB54) -> 477.63
J56: Monte Abraão, 31 de Dezembro de 2015
C58: Valor Transitado do Ano 2014 | D58: 5800.2 | M58: A Administração
C59: Receitas Ano 2015 | D59: =D27+F27+H27+J27+L27+N27+P27+R27+T27+V27+X27+Z27 -> 7652.71 | J59: Luís Dias - 5º Drt. | P59: Carlos Dias - 4º Drt.
D60: =SUM(D58:D59) -> 13452.91
C61: Despesas Ano 2015 - | D61: =D48+F48+H48+J48+L48+N48+P48+R48+T48+V48+X48+Z48 -> 7175.08
C62: Saldo a transitar para 2016 | D62: =D60-D61 -> 6277.83

Sheet Receitas Despesas 2016
C1: Condominio Rua Vieira da Silva, 6 | J1: Queluz - Monte Abraão | W1: Ano 2016
C3: RECEITAS
C5: Receitas | D5: Janeiro | F5: Fevereiro | H5: Março | J5: Abril | L5: Maio | N5: Junho | P5: Julho | R5: Agosto | T5: Setembro | V5: Outubro | X5: Novembro | Z5: Dezembro | AC5: TOTAL | AD5: Valor previsto | AE5: Valor em divida
C8: 6ºAndar Direito | D8: 37.5 | R8: 75 | V8: 75 | AC8: =SUM(D8:AB8) -> 187.5 | AD8: =37.5*12 -> 450 | AE8: =AD8-AC8 -> 262.5
C9: 6ºAndar Esquerdo | D9: 37.5 | F9: 37.5 | H9: 37.5 | J9: 37.5 | L9: 37.5 | N9: 37.5 | P9: 37.5 | T9: 75 | V9: 37.5 | Z9: 75 | AC9: =SUM(D9:AB9) -> 450 | AD9: =37.5*12 -> 450 | AE9: =AD9-AC9 -> 0
C10: 5ºAndar Direito | F10: 37.5 | J10: 37.5 | N10: 37.5 | T10: 75 | Z10: 37.5 | AC10: =SUM(D10:AB10) -> 225 | AD10: =37.5*12 -> 450 | AE10: =AD10-AC10 -> 225
C11: 5 Andar Esquerdo | D11: 37.5 | F11: 37.5 | H11: 37.5 | L11: 75 | N11: 37.5 | P11: 37.5 | R11: 37.5 | T11: 37.5 | V11: 37.5 | X11: 37.5 | Z11: 37.5 | AC11: =SUM(D11:AB11) -> 450 | AD11: =37.5*12 -> 450 | AE11: =AD11-AC11 -> 0
C12: 4ºAndar Direito | D12: 18.75 | F12: 18.75 | H12: 18.75 | J12: 18.75 | L12: 18.75 | N12: 18.75 | P12: 18.75 | T12: 18.75 | V12: 37.5 | X12: 18.75 | Z12: 18.75 | AC12: =SUM(D12:AB12) -> 225 | AD12: =18.75*12 -> 225 | AE12: =AD12-AC12 -> 0
C13: 4ºAndar Esquerdo | D13: 37.5 | F13: 37.5 | H13: 37.5 | J13: 37.5 | L13: 37.5 | N13: 37.5 | P13: 37.5 | R13: 37.5 | T13: 37.5 | V13: 37.5 | X13: 37.5 | Z13: 37.5 | AC13: =SUM(D13:AB13) -> 450 | AD13: =37.5*12 -> 450 | AE13: =AD13-AC13 -> 0
C14: 3ºAndar Direito | D14: 37.5 | F14: 37.5 | H14: 37.5 | J14: 37.5 | L14: 37.5 | N14: 37.5 | P14: 37.5 | R14: 37.5 | T14: 37.5 | V14: 37.5 | X14: 37.5 | Z14: 37.5 | AC14: =SUM(D14:AB14) -> 450 | AD14: =37.5*12 -> 450 | AE14: =AD14-AC14 -> 0
C15: 3ºAndar Esquerdo | D15: 75 | F15: 37.5 | H15: 37.5 | J15: 37.5 | L15: 75 | P15: 37.5 | R15: 37.5 | T15: 37.5 | V15: 37.5 | Z15: 112.5 | AC15: =SUM(D15:AB15) -> 525 | AD15: =37.5*12 -> 450 | AE15: =AD15-AC15 -> -75
C16: 2ºAndar Direito | D16: 37.5 | F16: 37.5 | H16: 37.5 | J16: 37.5 | L16: 37.5 | N16: 37.5 | P16: 37.5 | R16: 37.5 | T16: 37.5 | V16: 37.5 | X16: 37.5 | Z16: 37.5 | AC16: =SUM(D16:AB16) -> 450 | AD16: =37.5*12 -> 450 | AE16: =AD16-AC16 -> 0
C17: 2ºAndar Esquerdo | D17: 37.5 | F17: 37.5 | H17: 37.5 | J17: 37.5 | L17: 37.5 | N17: 37.5 | P17: 37.5 | R17: 37.5 | T17: 37.5 | V17: 37.5 | X17: 37.5 | Z17: 37.5 | AC17: =SUM(D17:AB17) -> 450 | AD17: =37.5*12 -> 450 | AE17: =AD17-AC17 -> 0
C18: 1ºAndar Direito | P18: 660 | V18: 112.5 | Z18: 75 | AC18: =SUM(D18:AB18) -> 847.5 | AD18: =37.5*12 -> 450 | AE18: =AD18-AC18 -> -397.5
C19: 1ºAndar Esquerdo | F19: 37.5 | H19: 37.5 | J19: 37.5 | L19: 37.5 | N19: 37.5 | P19: 37.5 | R19: 37.5 | T19: 37.5 | V19: 37.5 | X19: 37.5 | Z19: 37.5 | AC19: =SUM(D19:AB19) -> 412.5 | AD19: =37.5*12 -> 450 | AE19: =AD19-AC19 -> 37.5
C20: Res-Chão Direito | F20: 112.5 | P20: 37.5 | X20: 375 | Z20: 37.5 | AC20: =SUM(D20:AB20) -> 562.5 | AD20: =37.5*12 -> 450 | AE20: =AD20-AC20 -> -112.5
C21: Res-Chão Esquerdo | D21: 50 | F21: 40 | J21: 50 | L21: 40 | AC21: =SUM(D21:AB21) -> 180 | AD21: =37.5*12 -> 450 | AE21: =AD21-AC21 -> 270
C22: Cave -1 (Garagem) | AC22: =SUM(D22:AB22) -> 0 | AD22: =37.5*12 -> 450 | AE22: =AD22-AC22 -> 450
C23: Cave -2 | D23: 37.5 | F23: 37.5 | H23: 37.5 | J23: 37.5 | L23: 37.5 | N23: 37.5 | P23: 37.5 | R23: 37.5 | T23: 37.5 | V23: 37.5 | X23: 37.5 | Z23: 37.5 | AC23: =SUM(D23:AB23) -> 450 | AD23: =37.5*12 -> 450 | AE23: =AD23-AC23 -> 0
AD24: =37.5*12 -> 450 | AE24: =AD24-AC24 -> 450
C25: Não Identificado | AC25: =SUM(D25:AB25) -> 0 | AD25: =37.5*12 -> 450 | AE25: =AD25-AC25 -> 450
C28: Total Receitas | D28: =D8+D9+D10+D11+D12+D13+D14+D15+D16+D17+D18+D19+D20+D21+D22+D23+D25 -> 443.75 | F28: =F8+F9+F10+F11+F12+F13+F14+F15+F16+F17+F18+F19+F20+F21+F22+F23+F25 -> 546.25 | H28: =H8+H9+H10+H11+H12+H13+H14+H15+H16+H17+H18+H19+H20+H21+H22+H23+H25 -> 356.25 | J28: =J8+J9+J10+J11+J12+J13+J14+J15+J16+J17+J18+J19+J20+J21+J22+J23+J25 -> 406.25 | L28: =L8+L9+L10+L11+L12+L13+L14+L15+L16+L17+L18+L19+L20+L21+L22+L23+L25 -> 471.25 | N28: =N8+N9+N10+N11+N12+N13+N14+N15+N16+N17+N18+N19+N20+N21+N22+N23+N25 -> 356.25 | P28: =P8+P9+P10+P11+P12+P13+P14+P15+P16+P17+P18+P19+P20+P21+P22+P23+P25 -> 1053.75 | R28: =R8+R9+R10+R11+R12+R13+R14+R15+R16+R17+R18+R19+R20+R21+R22+R23+R25 -> 375 | T28: =T8+T9+T10+T11+T12+T13+T14+T15+T16+T17+T18+T19+T20+T21+T22+T23+T25 -> 468.75 | V28: =V8+V9+V10+V11+V12+V13+V14+V15+V16+V17+V18+V19+V20+V21+V22+V23+V25 -> 562.5 | X28: =X8+X9+X10+X11+X12+X13+X14+X15+X16+X17+X18+X19+X20+X21+X22+X23+X25 -> 656.25 | Z28: =Z8+Z9+Z10+Z11+Z12+Z13+Z14+Z15+Z16+Z17+Z18+Z19+Z20+Z21+Z22+Z23+Z25 -> 618.75 | AC28: =SUM(D28:AB28) -> 6315
C29: Monte Abraão, 31 de Dezembro de 2016 | K29: A Administração
C31: Condominio Rua Vieira da Silva, 6 | J31: Queluz - Monte Abraão | W31: Ano 2016
A33: DESPESAS
C35: Despesas | D35: Janeiro | F35: Fevereiro | H35: Março | J35: Abril | L35: Maio | N35: Junho | P35: Julho | R35: Agosto | T35: Setembro | V35: Outubro | X35: Novembro | Z35: Dezembro | AC35: TOTAL
C38: Electricidade | D38: 125.3 | F38: 105.88 | H38: 137.74 | J38: 134.63 | L38: 93.4 | N38: 119.48 | P38: 117.95 | R38: 138.18 | T38: 125.2 | V38: 123.44 | X38: 127.61 | Z38: 121.68 | AC38: =SUM(D38:AB38) -> 1470.49
C39: Elevadores | J39: 580.48 | L39: 145.12 | N39: 145.12 | P39: 145.12 | R39: 145.12 | T39: 145.12 | V39: 145.12 | X39: 147.16 | Z39: 147.16 | AC39: =SUM(D39:AB39) -> 1745.52
C40: Reparação Pedra Entrada Portão-4 | L40: 240 | T40: 90 | AC40: =SUM(D40:AB40) -> 330
C41: Manutenção Central Bombagem | J41: 98.4 | AC41: =SUM(D41:AB41) -> 98.4
C42: Tribunal / Julgados de Paz | AC42: =SUM(D42:AB42) -> 0
C43: Manutenção Extintores | F43: 54.5 | AC43: =SUM(D43:AB43) -> 54.5
C44: Despesas Bancárias | D44: 1.04 | F44: 1.04 | H44: 1.04 | J44: 2.08 | L44: 1.04 | N44: 1.04 | P44: 1.04 | R44: 1.04 | T44: 2.08 | V44: 1.04 | X44: 1.04 | Z44: 1.04 | AC44: =SUM(D44:AB44) -> 14.56
C45: Produtos Limpeza e Limpeza | H45: 352 | T45: 616 | AC45: =SUM(D45:AB45) -> 968
C46: Manutenção Geral Edificio | F46: 38 | Z46: 96.92 | AC46: =SUM(D46:AB46) -> 134.92
AC47: =SUM(D47:AB47) -> 0
C48: Depósitos Prazo Poupança Cond | D48: 60 | F48: 60 | H48: 60 | J48: 60 | L48: 60 | N48: 60 | P48: 60 | R48: 60 | T48: 60 | V48: 60 | X48: 60 | Z48: 60 | AC48: =SUM(D48:AB48) -> 720
C51: Total Despesas | D51: =D38+D39+D40+D41+D42+D43+D44+D45+D46+D47+D48 -> 186.34 | F51: =F38+F39+F40+F41+F42+F43+F44+F45+F46+F47+F48 -> 259.42 | H51: =H38+H39+H40+H41+H42+H43+H44+H45+H46+H47+H48 -> 550.78 | J51: =J38+J39+J40+J41+J42+J43+J44+J45+J46+J47+J48 -> 875.59 | L51: =L38+L39+L40+L41+L42+L43+L44+L45+L46+L47+L48 -> 539.56 | N51: =N38+N39+N40+N41+N42+N43+N44+N45+N46+N47+N48 -> 325.64 | P51: =P38+P39+P40+P41+P42+P43+P44+P45+P46+P47+P48 -> 324.11 | R51: =R38+R39+R40+R41+R42+R43+R44+R45+R46+R47+R48 -> 344.34 | T51: =T38+T39+T40+T41+T42+T43+T44+T45+T46+T47+T48 -> 1038.4 | V51: =V38+V39+V40+V41+V42+V43+V44+V45+V46+V47+V48 -> 329.6 | X51: =X38+X39+X40+X41+X42+X43+X44+X45+X46+X47+X48 -> 335.81 | Z51: =Z38+Z39+Z40+Z41+Z42+Z43+Z44+Z45+Z46+Z47+Z48 -> 426.8 | AC51: =SUM(D51:AB51) -> 5536.39
AC55: Total Liquido
C57: Resultados Liquidos | D57: =D28-D51 -> 257.41 | F57: =F28-F51 -> 286.83 | H57: =H28-H51 -> -194.53 | J57: =J28-J51 -> -469.34 | L57: =L28-L51 -> -68.31 | N57: =N28-N51 -> 30.61 | P57: =P28-P51 -> 729.64 | R57: =R28-R51 -> 30.66 | T57: =T28-T51 -> -569.65 | V57: =V28-V51 -> 232.9 | X57: =X28-X51 -> 320.44 | Z57: =Z28-Z51 -> 191.95 | AC57: =SUM(D57:AB57) -> 778.61
AC58: 720
J59: Monte Abraão, 31 de Dezembro de 2016 | AC59: =SUM(AC57:AC58) -> 1498.61
C61: Valor Transitado do Ano 2015 | D61: 6277.83 | M61: A Administração
C62: Receitas Ano 2016 | D62: =D28+F28+H28+J28+L28+N28+P28+R28+T28+V28+X28+Z28 -> 6315 | J62: Luís Dias - 5º Drt. | P62: Carlos Dias - 4º Drt.
D63: =SUM(D61:D62) -> 12592.83
C64: Despesas Ano 2016 - | D64: =D51+F51+H51+J51+L51+N51+P51+R51+T51+V51+X51+Z51 -> 5536.39
C65: Saldo a transitar para 2017 | D65: =D63-D64 -> 7056.44

Sheet Receita Despesas 2017
B1: Condominio Rua Vieira da Silva, 6 | I1: Queluz - Monte Abraão | V1: Ano 2017
B2: RECEITAS
B4: Receitas | C4: Janeiro | E4: Fevereiro | G4: Março | I4: Abril | K4: Maio | M4: Junho | O4: Julho | Q4: Agosto | S4: Setembro | U4: Outubro | W4: Novembro | Y4: Dezembro | AB4: TOTAL | AC4: Valor previsto | AD4: Valor em divida
B7: 6ºAndar Direito | O7: 37.5 | Q7: 37.5 | S7: 37.5 | U7: 37.5 | W7: 37.5 | Y7: 137.5 | AB7: =SUM(C7:AA7) -> 325 | AC7: =37.5*12 -> 450 | AD7: =AC7-AB7 -> 125
B8: 6ºAndar Esquerdo | C8: 37.5 | E8: 37.5 | I8: 75 | M8: 75 | Q8: 75 | S8: 37.5 | U8: 37.5 | W8: 37.5 | Y8: 37.5 | AB8: =SUM(C8:AA8) -> 450 | AC8: =37.5*12 -> 450 | AD8: =AC8-AB8 -> 0
B9: 5ºAndar Direito | E9: 37.5 | M9: 37.5 | S9: 75 | W9: 37.5 | Y9: 37.5 | AB9: =SUM(C9:AA9) -> 225 | AC9: =37.5*12 -> 450 | AD9: =AC9-AB9 -> 225
B10: 5 Andar Esquerdo | E10: 37.5 | G10: 37.5 | I10: 37.5 | K10: 37.5 | M10: 37.5 | O10: 37.5 | Q10: 37.5 | S10: 37.5 | U10: 37.5 | W10: 37.5 | Y10: 37.5 | AB10: =SUM(C10:AA10) -> 412.5 | AC10: =37.5*12 -> 450 | AD10: =AC10-AB10 -> 37.5
B11: 4ºAndar Direito | C11: 18.75 | E11: 18.75 | G11: 18.75 | I11: 18.75 | K11: 18.75 | M11: 18.75 | O11: 18.75 | S11: 37.5 | U11: 18.75 | W11: 18.75 | Y11: 18.75 | AB11: =SUM(C11:AA11) -> 225 | AC11: =18.75*12 -> 225 | AD11: =AC11-AB11 -> 0
B12: 4ºAndar Esquerdo | C12: 37.5 | E12: 37.5 | G12: 37.5 | I12: 37.5 | K12: 37.5 | M12: 37.5 | O12: 37.5 | Q12: 37.5 | S12: 37.5 | U12: 37.5 | W12: 37.5 | AB12: =SUM(C12:AA12) -> 412.5 | AC12: =37.5*12 -> 450 | AD12: =AC12-AB12 -> 37.5
B13: 3ºAndar Direito | C13: 37.5 | E13: 37.5 | G13: 37.5 | K13: 75 | M13: 37.5 | O13: 39.75 | Q13: 35.25 | S13: 37.5 | W13: 40 | Y13: 40 | AB13: =SUM(C13:AA13) -> 417.5 | AC13: =37.5*12 -> 450 | AD13: =AC13-AB13 -> 32.5
B14: 3ºAndar Esquerdo | C14: 37.5 | E14: 37.5 | M14: 75 | O14: 75 | S14: 75 | AB14: =SUM(C14:AA14) -> 300 | AC14: =37.5*12 -> 450 | AD14: =AC14-AB14 -> 150
B15: 2ºAndar Direito | C15: 37.5 | E15: 37.5 | G15: 37.5 | I15: 37.5 | K15: 37.5 | M15: 37.5 | O15: 37.5 | Q15: 37.5 | S15: 37.5 | U15: 37.5 | W15: 37.5 | Y15: 37.5 | AB15: =SUM(C15:AA15) -> 450 | AC15: =37.5*12 -> 450 | AD15: =AC15-AB15 -> 0
B16: 2ºAndar Esquerdo | C16: 37.5 | E16: 37.5 | G16: 37.5 | I16: 37.5 | K16: 37.5 | M16: 37.5 | O16: 37.5 | Q16: 37.5 | S16: 37.5 | U16: 37.5 | W16: 37.5 | Y16: 37.5 | AB16: =SUM(C16:AA16) -> 450 | AC16: =37.5*12 -> 450 | AD16: =AC16-AB16 -> 0
B17: 1ºAndar Direito | E17: 75 | G17: 37.5 | I17: 37.5 | K17: 37.5 | M17: 37.5 | O17: 37.5 | Q17: 37.5 | S17: 37.5 | W17: 75 | Y17: 37.5 | AB17: =SUM(C17:AA17) -> 450 | AC17: =37.5*12 -> 450 | AD17: =AC17-AB17 -> 0
B18: 1ºAndar Esquerdo | C18: 37.5 | E18: 37.5 | G18: 37.5 | I18: 37.5 | K18: 37.5 | M18: 37.5 | O18: 37.5 | Q18: 75 | U18: 75 | Y18: 37.5 | AB18: =SUM(C18:AA18) -> 450 | AC18: =37.5*12 -> 450 | AD18: =AC18-AB18 -> 0
B19: Res-Chão Direito | E19: 37.5 | G19: 75 | K19: 75 | O19: 37.5 | Q19: 37.5 | S19: 37.5 | W19: 37.5 | Y19: 37.5 | AB19: =SUM(C19:AA19) -> 375 | AC19: =37.5*12 -> 450 | AD19: =AC19-AB19 -> 75
B20: Res-Chão Esquerdo | AB20: =SUM(C20:AA20) -> 0 | AC20: =37.5*12 -> 450 | AD20: =AC20-AB20 -> 450
B21: Cave -1 (Garagem) | I21: 450 | AB21: =SUM(C21:AA21) -> 450 | AC21: =37.5*12 -> 450 | AD21: =AC21-AB21 -> 0
B22: Cave -2 | C22: 37.5 | E22: 37.5 | G22: 37.5 | I22: 37.5 | K22: 37.5 | M22: 37.5 | O22: 37.5 | Q22: 37.5 | S22: 37.5 | U22: 37.5 | W22: 37.5 | Y22: 37.5 | AB22: =SUM(C22:AA22) -> 450 | AC22: =37.5*12 -> 450 | AD22: =AC22-AB22 -> 0
AC23: =37.5*12 -> 450 | AD23: =AC23-AB23 -> 450
B24: Não Identificado
B27: Total Receitas | C27: =C7+C8+C9+C10+C11+C12+C13+C14+C15+C16+C17+C18+C19+C20+C21+C22+C24 -> 318.75 | E27: =E7+E8+E9+E10+E11+E12+E13+E14+E15+E16+E17+E18+E19+E20+E21+E22+E24 -> 506.25 | G27: =G7+G8+G9+G10+G11+G12+G13+G14+G15+G16+G17+G18+G19+G20+G21+G22+G24 -> 393.75 | I27: =I7+I8+I9+I10+I11+I12+I13+I14+I15+I16+I17+I18+I19+I20+I21+I22+I24 -> 806.25 | K27: =K7+K8+K9+K10+K11+K12+K13+K14+K15+K16+K17+K18+K19+K20+K21+K22+K24 -> 431.25 | M27: =M7+M8+M9+M10+M11+M12+M13+M14+M15+M16+M17+M18+M19+M20+M21+M22+M24 -> 506.25 | O27: =O7+O8+O9+O10+O11+O12+O13+O14+O15+O16+O17+O18+O19+O20+O21+O22+O24 -> 471 | Q27: =Q7+Q8+Q9+Q10+Q11+Q12+Q13+Q14+Q15+Q16+Q17+Q18+Q19+Q20+Q21+Q22+Q24 -> 485.25 | S27: =S7+S8+S9+S10+S11+S12+S13+S14+S15+S16+S17+S18+S19+S20+S21+S22+S24 -> 562.5 | U27: =U7+U8+U9+U10+U11+U12+U13+U14+U15+U16+U17+U18+U19+U20+U21+U22+U24 -> 356.25 | W27: =W7+W8+W9+W10+W11+W12+W13+W14+W15+W16+W17+W18+W19+W20+W21+W22+W24 -> 471.25 | Y27: =Y7+Y8+Y9+Y10+Y11+Y12+Y13+Y14+Y15+Y16+Y17+Y18+Y19+Y20+Y21+Y22+Y24 -> 533.75 | AB27: =SUM(C27:AA27) -> 5842.5
B28: Monte Abraão, 31 de Dezembro de 2017 | J28: A Administração
B30: Condominio Rua Vieira da Silva, 6 | I30: Queluz - Monte Abraão | V30: Ano 2017
A31: DESPESAS
B33: Despesas | C33: Janeiro | E33: Fevereiro | G33: Março | I33: Abril | K33: Maio | M33: Junho | O33: Julho | Q33: Agosto | S33: Setembro | U33: Outubro | W33: Novembro | Y33: Dezembro | AB33: TOTAL
B36: Electricidade | C36: 121.05 | E36: 140.29 | G36: 256.97 | K36: 254.66 | M36: 124.59 | O36: 149.77 | Q36: 133.99 | U36: 252.91 | W36: 135.76 | AB36: =SUM(C36:AA36) -> 1569.99
B37: Elevadores | C37: 147.16 | E37: 147.16 | G37: 147.16 | I37: 147.16 | K37: 147.16 | M37: 147.16 | O37: 147.16 | Q37: 342.46 | S37: 147.16 | U37: 147.16 | W37: 149.96 | Y37: 149.96 | AB37: =SUM(C37:AA37) -> 1966.82
B38: Reparação Pedra Entrada Portão-4 | AB38: =SUM(W38:AA38) -> 0
B39: Manutenção Central Bombagem | I39: 676.5 | M39: 98.4 | Y39: 35 | AB39: =SUM(C39:AA39) -> 809.9
B40: Tribunal / Julgados de Paz | AB40: =SUM(C40:AA40) -> 0
B41: Manutenção Extintores | E41: 112.5 | AB41: =SUM(C41:AA41) -> 112.5
B42: Despesas Bancárias | C42: 1.04 | E42: 1.04 | G42: 1.04 | I42: 2.08 | K42: 1.04 | M42: 2.08 | O42: 1.04 | Q42: 1.04 | S42: 1.04 | U42: 1.04 | W42: 1.04 | Y42: 1.04 | AB42: =SUM(C42:AA42) -> 14.56
B43: Produtos Limpeza e Limpeza | E43: 440 | W43: 880 | AB43: =SUM(C43:AA43) -> 1320
B44: Manutenção Geral Edificio | AB44: =SUM(C44:AA44) -> 0
B45: Inspecção Elevadores | Q45: 340 | AB45: =SUM(C45:AA45) -> 340
B46: Depósitos Prazo Poupança Cond | C46: 60 | E46: 60 | G46: 60 | I46: 60 | K46: 60 | M46: 60 | O46: 60 | Q46: 60 | S46: 60 | U46: 60 | W46: 60 | Y46: 60 | AB46: =SUM(C46:AA46) -> 720
B49: Total Despesas | C49: =C36+C37+C38+C39+C40+C41+C42+C43+C44+C45+C46 -> 329.25 | E49: =E36+E37+E38+E39+E40+E41+E42+E43+E44+E45+E46 -> 900.99 | G49: =G36+G37+G38+G39+G40+G41+G42+G43+G44+G45+G46 -> 465.17 | I49: =I36+I37+I38+I39+I40+I41+I42+I43+I44+I45+I46 -> 885.74 | K49: =K36+K37+K38+K39+K40+K41+K42+K43+K44+K45+K46 -> 462.86 | M49: =M36+M37+M38+M39+M40+M41+M42+M43+M44+M45+M46 -> 432.23 | O49: =O36+O37+O38+O39+O40+O41+O42+O43+O44+O45+O46 -> 357.97 | Q49: =Q36+Q37+Q38+Q39+Q40+Q41+Q42+Q43+Q44+Q45+Q46 -> 877.49 | S49: =S36+S37+S38+S39+S40+S41+S42+S43+S44+S45+S46 -> 208.2 | U49: =U36+U37+U38+U39+U40+U41+U42+U43+U44+U45+U46 -> 461.11 | W49: =W36+W37+W38+W39+W40+W41+W42+W43+W44+W45+W46 -> 1226.76 | Y49: =Y36+Y37+Y38+Y39+Y40+Y41+Y42+Y43+Y44+Y45+Y46 -> 246 | AB49: =SUM(C49:AA49) -> 6853.77
AB53: Total Liquido
B55: Resultados Liquidos | C55: =C27-C49 -> -10.5 | E55: =E27-E49 -> -394.74 | G55: =G27-G49 -> -71.42 | I55: =I27-I49 -> -79.49 | K55: =K27-K49 -> -31.61 | M55: =M27-M49 -> 74.02 | O55: =O27-O49 -> 113.03 | Q55: =Q27-Q49 -> -392.24 | S55: =S27-S49 -> 354.3 | U55: =U27-U49 -> -104.86 | W55: =W27-W49 -> -755.51 | Y55: =Y27-Y49 -> 287.75 | AB55: =SUM(C55:AA55) -> -1011.27
AB56: 720
I57: Monte Abraão, 31 de Dezembro de 2017 | AB57: =SUM(AB55:AB56) -> -291.27
B59: Valor Transitado do Ano 2016 | C59: 7,056,44€ | L59: A Administração
B60: Receitas Ano 2017 | C60: =C27+E27+G27+I27+K27+M27+O27+Q27+S27+U27+W27+Y27 -> 5842.5 | I60: Luís Dias - 5º Drt. | O60: Carlos Dias - 4º Drt.
C61: 12898.94
B62: Despesas Ano 2017 - | C62: =C49+E49+G49+I49+K49+M49+O49+Q49+S49+U49+W49+Y49 -> 6853.77
B63: Saldo a transitar para 2018 | C63: =C61-C62 -> 6045.17
B65: Montepio Conta Corrente

Sheet Receita Despesas 2018
C1: Condominio Rua Vieira da Silva, 6 | I1: Queluz - Monte Abraão | W1: Ano 2018
C2: RECEITAS
C4: Receitas | D4: Janeiro | F4: Fevereiro | H4: Março | J4: Abril | L4: Maio | N4: Junho | P4: Julho | R4: Agosto | T4: Setembro | V4: Outubro | X4: Novembro | Z4: Dezembro | AC4: TOTAL | AD4: Valor previsto | AE4: Quota extra + valor previsto | AF4: Valor em divida
C7: 6ºAndar Direito | F7: 175 | H7: 137.5 | L7: 75 | N7: 87.5 | P7: 112.5 | AC7: =SUM(D7:AB7) -> 587.5 | AD7: =37.5*12 -> 450 | AE7: =AD7+150 -> 600 | AF7: =AE7-AC7 -> 12.5
C8: 6ºAndar Esquerdo | D8: 37.5 | F8: 37.5 | H8: 37.5 | J8: 37.5 | L8: 37.5 | N8: 37.5 | P8: 37.5 | R8: 112.5 | V8: 75 | X8: 37.5 | AC8: =SUM(D8:AB8) -> 487.5 | AD8: =37.5*12 -> 450 | AE8: =AD8+150 -> 600 | AF8: =AE8-AC8 -> 112.5
C9: 5ºAndar Direito | F9: 37.5 | H9: 37.5 | N9: 87.5 | P9: 50 | R9: 50 | T9: 37.5 | Z9: 75 | AC9: =SUM(D9:AB9) -> 375 | AD9: =37.5*12 -> 450 | AE9: =AD9+150 -> 600 | AF9: =AE9-AC9 -> 225
C10: 5 Andar Esquerdo | D10: 37.5 | H10: 75 | J10: 37.5 | L10: 37.5 | N10: 37.5 | P10: 37.5 | R10: 37.5 | T10: 37.5 | V10: 37.5 | X10: 37.5 | Z10: 37.5 | AC10: =SUM(D10:AB10) -> 450 | AD10: =37.5*12 -> 450 | AE10: =AD10+150 -> 600 | AF10: =AE10-AC10 -> 150
C11: 4ºAndar Direito | D11: 18.75 | F11: 18.75 | H11: 18.75 | J11: 18.75 | L11: 18.75 | N11: 68.75 | P11: 68.75 | R11: 68.75 | T11: 18.75 | V11: 18.75 | X11: 18.75 | Z11: 18.75 | AC11: =SUM(D11:AB11) -> 375 | AD11: =18.75*12 -> 225 | AE11: =AD11+150 -> 375 | AF11: =AE11-AC11 -> 0
C12: 4ºAndar Esquerdo | D12: 75 | F12: 37.5 | H12: 37.5 | J12: 37.5 | L12: 37.5 | N12: 37.5 | P12: 187.5 | R12: 37.5 | T12: 37.5 | V12: 37.5 | X12: 37.5 | Z12: 37.5 | AC12: =SUM(D12:AB12) -> 637.5 | AD12: =37.5*12 -> 450 | AE12: =AD12+150 -> 600 | AF12: =AE12-AC12 -> -37.5
C13: 3ºAndar Direito | D13: 40 | F13: 40 | H13: 40 | J13: 40 | L13: 80 | P13: 115 | R13: 77.5 | T13: 40 | V13: 75 | X13: 37.5 | Z13: 37.5 | AC13: =SUM(D13:AB13) -> 622.5 | AD13: =37.5*12 -> 450 | AE13: =AD13+150 -> 600 | AF13: =AE13-AC13 -> -22.5
C14: 3ºAndar Esquerdo | F14: 100 | J14: 130 | N14: 80 | P14: 100 | R14: 100 | T14: 80 | V14: 37.5 | X14: 37.5 | AC14: =SUM(D14:AB14) -> 665 | AD14: =37.5*12 -> 450 | AE14: =AD14+150 -> 600 | AF14: =AE14-AC14 -> -65
C15: 2ºAndar Direito | D15: 37.5 | F15: 412.5 | N15: 150 | AC15: =SUM(D15:AB15) -> 600 | AD15: =37.5*12 -> 450 | AE15: =AD15+150 -> 600 | AF15: =AE15-AC15 -> 0
C16: 2ºAndar Esquerdo | D16: 37.5 | F16: 412.5 | N16: 150 | AC16: =SUM(D16:AB16) -> 600 | AD16: =37.5*12 -> 450 | AE16: =AD16+150 -> 600 | AF16: =AE16-AC16 -> 0
C17: 1ºAndar Direito | D17: 37.5 | F17: 37.5 | J17: 75 | N17: 125 | P17: 100 | T17: 75 | V17: 75 | Z17: 75 | AC17: =SUM(D17:AB17) -> 600 | AD17: =37.5*12 -> 450 | AE17: =AD17+150 -> 600 | AF17: =AE17-AC17 -> 0
C18: 1ºAndar Esquerdo | D18: 37.5 | F18: 37.5 | H18: 37.5 | J18: 37.5 | L18: 37.5 | N18: 187.5 | P18: 37.5 | R18: 37.5 | T18: 37.5 | V18: 37.5 | X18: 37.5 | Z18: 37.5 | AC18: =SUM(D18:AB18) -> 600 | AD18: =37.5*12 -> 450 | AE18: =AD18+150 -> 600 | AF18: =AE18-AC18 -> 0
C19: Res-Chão Direito | F19: 112.5 | H19: 75 | L19: 37.5 | P19: 187.5 | R19: 37.5 | T19: 37.5 | V19: 37.5 | X19: 37.5 | Z19: 37.5 | AC19: =SUM(D19:AB19) -> 600 | AD19: =37.5*12 -> 450 | AE19: =AD19+150 -> 600 | AF19: =AE19-AC19 -> 0
C20: Res-Chão Esquerdo | J20: 210 | P20: 50 | V20: 150 | X20: 50 | AC20: =SUM(D20:AB20) -> 460 | AD20: =37.5*12 -> 450 | AE20: =AD20+150 -> 600 | AF20: =AE20-AC20 -> 140
C21: Cave -1 (Garagem) | L21: 433 | N21: 230 | R21: 150 | V21: 225 | AC21: =SUM(D21:AB21) -> 1038 | AD21: =37.5*12 -> 450 | AE21: =AD21+150 -> 600 | AF21: =AE21-AC21 -> -438
C22: Cave -2 | D22: 37.5 | F22: 37.5 | H22: 37.5 | J22: 37.5 | L22: 37.5 | N22: 187.5 | P22: 37.5 | R22: 37.5 | T22: 37.5 | V22: 37.5 | X22: 37.5 | Z22: 37.5 | AC22: =SUM(D22:AB22) -> 600 | AD22: =37.5*12 -> 450 | AE22: =AD22+150 -> 600 | AF22: =AE22-AC22 -> 0
AD23: =37.5*12 -> 450 | AF23: =AE23-AC23 -> 0
C24: levantamento deposito a prazo | R24: 3000
C25: Crédito Luz Endesa | L25: 73.95 | R25: 76.47
C26: Juros Deposito Prazo / devolução | P26: 1.04 | R26: 1.28
C27: Não Identificado | AC27: =SUM(D27:AB27) -> 0
C30: Total Receitas | D30: =D7+D8+D9+D10+D11+D12+D13+D14+D15+D16+D17+D18+D19+D20+D21+D22+D27 -> 396.25 | F30: =F7+F8+F9+F10+F11+F12+F13+F14+F15+F16+F17+F18+F19+F20+F21+F22+F27 -> 1496.25 | H30: =H7+H8+H9+H10+H11+H12+H13+H14+H15+H16+H17+H18+H19+H20+H21+H22+H27 -> 533.75 | J30: =J7+J8+J9+J10+J11+J12+J13+J14+J15+J16+J17+J18+J19+J20+J21+J22+J27 -> 661.25 | L30: =L7+L8+L9+L10+L11+L12+L13+L14+L15+L16+L17+L18+L19+L20+L21+L22+L25+L27 -> 905.7 | N30: =N7+N8+N9+N10+N11+N12+N13+N14+N15+N16+N17+N18+N19+N20+N21+N22+N27 -> 1466.25 | P30: =P7+P8+P9+P10+P11+P12+P13+P14+P15+P16+P17+P18+P19+P20+P21+P22+P26+P27 -> 1122.29 | R30: =R7+R8+R9+R10+R11+R12+R13+R14+R15+R16+R17+R18+R19+R20+R21+R22+R24+R25+R26+R27 -> 3824 | T30: =T7+T8+T9+T10+T11+T12+T13+T14+T15+T16+T17+T18+T19+T20+T21+T22+T27 -> 438.75 | V30: =V7+V8+V9+V10+V11+V12+V13+V14+V15+V16+V17+V18+V19+V20+V21+V22+V27 -> 843.75 | X30: =X7+X8+X9+X10+X11+X12+X13+X14+X15+X16+X17+X18+X19+X20+X21+X22+X27 -> 368.75 | Z30: =Z7+Z8+Z9+Z10+Z11+Z12+Z13+Z14+Z15+Z16+Z17+Z18+Z19+Z20+Z21+Z22+Z27 -> 393.75 | AC30: =SUM(D30:AB30) -> 12450.74
C31: Monte Abraão, 31 de Dezembro de 2018 | K31: A Administração
C32: Condominio Rua Vieira da Silva, 6 | J32: Queluz - Monte Abraão | W32: Ano 2018
A33: DESPESAS
C35: Despesas | D35: Janeiro | F35: Fevereiro | H35: Março | J35: Abril | L35: Maio | N35: Junho | P35: Julho | R35: Agosto | T35: Setembro | V35: Outubro | X35: Novembro | Z35: Dezembro | AC35: TOTAL
C38: Electricidade | F38: 321.18 | H38: 241.48 | J38: 207.33 | N38: 214.61 | P38: 226.14 | T38: 121.06 | V38: 133.83 | X38: 125.03 | Z38: 126.07 | AC38: =SUM(D38:AB38) -> 1716.73
C39: Elevadores | D39: 149.96 | F39: 149.96 | H39: 149.96 | J39: 149.96 | L39: 149.96 | N39: 149.96 | P39: 149.96 | R39: 149.96 | T39: 149.96 | V39: 149.96 | AC39: =SUM(D39:AB39) -> 1499.6
C40: Pintura Edificio | P40: 8500 | R40: 1600 | AC40: =SUM(X40:AB40) -> 0
C41: Manutenção Central Bombagem | AC41: =SUM(D41:AB41) -> 0
C42: Tribunal / Julgados de Paz | AC42: =SUM(D42:AB42) -> 0
C43: Manutenção Extintores | F43: 48 | AC43: =SUM(Z43:AB43) -> 0
C44: Despesas Bancárias | D44: 1.04 | F44: 1.04 | H44: 1.04 | J44: 1.04 | L44: 1.04 | N44: 1.04 | P44: 2.08 | R44: 1.36 | T44: 6.24 | V44: 6.24 | X44: 6.24 | Z44: 6.24 | AC44: =SUM(D44:AB44) -> 34.64
C45: Produtos Limpeza e Limpeza | P45: 528 | Z45: 528 | AC45: =SUM(D45:AB45) -> 1056
C46: Manutenção Geral Edificio | F46: 6.95 | H46: 16.2 | AC46: =SUM(D46:AB46) -> 23.15
C47: Inspecção Elevadores | H47: 280 | AC47: =SUM(D47:AB47) -> 280
C48: Depósitos Prazo Poupança Cond | D48: 60 | F48: 60 | H48: 60 | J48: 60 | L48: 60 | N48: 60 | P48: 60 | R48: 60 | T48: 60 | V48: 60 | X48: 60 | Z48: 60 | AC48: =SUM(D48:AB48) -> 720
C51: Total Despesas | D51: =D38+D39+D40+D41+D42+D43+D44+D45+D46+D47+D48 -> 211 | F51: =F38+F39+F40+F41+F42+F43+F44+F45+F46+F47+F48 -> 587.13 | H51: =H38+H39+H40+H41+H42+H43+H44+H45+H46+H47+H48 -> 748.68 | J51: =J38+J39+J40+J41+J42+J43+J44+J45+J46+J47+J48 -> 418.33 | L51: =L38+L39+L40+L41+L42+L43+L44+L45+L46+L47+L48 -> 211 | N51: =N38+N39+N40+N41+N42+N43+N44+N45+N46+N47+N48 -> 425.61 | P51: =P38+P39+P40+P41+P42+P43+P44+P45+P46+P47+P48 -> 9466.18 | R51: =R38+R39+R40+R41+R42+R43+R44+R45+R46+R47+R48 -> 1811.32 | T51: =T38+T39+T40+T41+T42+T43+T44+T45+T46+T47+T48 -> 337.26 | V51: =V38+V39+V40+V41+V42+V43+V44+V45+V46+V47+V48 -> 350.03 | X51: =X38+X39+X40+X41+X42+X43+X44+X45+X46+X47+X48 -> 191.27 | Z51: =Z38+Z39+Z40+Z41+Z42+Z43+Z44+Z45+Z46+Z47+Z48 -> 720.31 | AC51: =SUM(D51:AB51) -> 15478.12
AC55: Total Liquido
C57: Resultados Liquidos | D57: =D30-D51 -> 185.25 | F57: =F30-F51 -> 909.12 | H57: =H30-H51 -> -214.93 | J57: =J30-J51 -> 242.92 | L57: =L30-L51 -> 694.7 | N57: =N30-N51 -> 1040.64 | P57: =P30-P51 -> -8343.89 | R57: =R30-R51 -> 2012.68 | T57: =T30-T51 -> 101.49 | V57: =V30-V51 -> 493.72 | X57: =X30-X51 -> 177.48 | Z57: =Z30-Z51 -> -326.56 | AC57: =SUM(D57:AB57) -> -3027.38
AC58: 720 | AD58: POUPANÇA
J59: Monte Abraão, 31 de Dezembro de 2018 | AC59: =SUM(AC57:AC58) -> -2307.38 | AD59: TOTAL
C61: Valor Transitado do Ano 2017 | D61: 6045.17 | M61: A Administração
C62: Receitas Ano 2018 | D62: =D30+F30+H30+J30+L30+N30+P30+R30+T30+V30+X30+Z30 -> 12450.74 | J62: Luís Dias - 5º Drt. | P62: Carlos Dias - 4º Drt.
D63: =SUM(D61:D62) -> 18495.91
C64: Despesas Ano 2018 - | D64: =D51+F51+H51+J51+L51+N51+P51+R51+T51+V51+X51+Z51 -> 15478.12
C65: Saldo a transitar para 2019 | D65: =D63-D64 -> 3017.79
C67: Montepio Conta Corrente

Sheet Receita Despesas 2019
C1: Condominio Rua Vieira da Silva, 6 | J1: Queluz - Monte Abraão | W1: Ano 2019
C2: RECEITAS
C4: Receitas | D4: Janeiro | F4: Fevereiro | H4: Março | J4: Abril | L4: Maio | N4: Junho | P4: Julho | R4: Agosto | T4: Setembro | V4: Outubro | X4: Novembro | Z4: Dezembro | AC4: TOTAL | AD4: Valor previsto | AE4: Valor em divida
C7: 6ºAndar Direito | H7: 32.5 | AC7: =SUM(D7:AB7) -> 32.5 | AD7: =37.5*12 -> 450 | AE7: =AD7-AC7 -> 417.5
C8: 6ºAndar Esquerdo | D8: 75 | F8: 37.5 | J8: 75 | N8: 75 | R8: 150 | T8: 37.5 | X8: 75 | AC8: =SUM(D8:AB8) -> 525 | AD8: =37.5*12 -> 450 | AE8: =AD8-AC8 -> -75
C9: 5ºAndar Direito | D9: 37.5 | V9: 75 | X9: 75 | Z9: 75 | AC9: =SUM(D9:AB9) -> 262.5 | AD9: =37.5*12 -> 450 | AE9: =AD9-AC9 -> 187.5
C10: 5 Andar Esquerdo | D10: 37.5 | F10: 37.5 | H10: 37.5 | J10: 37.5 | L10: 37.5 | N10: 37.5 | P10: 37.5 | R10: 37.5 | T10: 37.5 | V10: 37.5 | X10: 37.5 | Z10: 37.5 | AC10: =SUM(D10:AB10) -> 450 | AD10: =37.5*12 -> 450 | AE10: =AD10-AC10 -> 0
C11: 4ºAndar Direito | D11: 18.75 | F11: 18.75 | H11: 18.75 | J11: 18.75 | L11: 18.75 | N11: 18.75 | P11: 18.75 | R11: 18.75 | T11: 18.75 | V11: 18.75 | X11: 18.75 | Z11: 18.75 | AC11: =SUM(D11:AB11) -> 225 | AD11: =18.75*12 -> 225 | AE11: =AD11-AC11 -> 0
C12: 4ºAndar Esquerdo | D12: 37.5 | F12: 37.5 | H12: 37.5 | J12: 37.5 | L12: 37.5 | P12: 75 | R12: 37.5 | T12: 37.5 | V12: 37.5 | X12: 37.5 | Z12: 37.5 | AC12: =SUM(D12:AB12) -> 450 | AD12: =37.5*12 -> 450 | AE12: =AD12-AC12 -> 0
C13: 3ºAndar Direito | D13: 47.5 | F13: 37.5 | H13: 37.5 | J13: 37.5 | L13: 37.5 | N13: 37.5 | P13: 37.5 | R13: 37.5 | T13: 37.5 | V13: 37.5 | X13: 37.5 | Z13: 37.5 | AC13: =SUM(D13:AB13) -> 460 | AD13: =37.5*12 -> 450 | AE13: =AD13-AC13 -> -10
C14: 3ºAndar Esquerdo | D14: 37.5 | F14: 40 | H14: 30 | J14: 40 | L14: 33 | N14: 120 | T14: 37.5 | X14: 75 | AC14: =SUM(D14:AB14) -> 413 | AD14: =37.5*12 -> 450 | AE14: =AD14-AC14 -> 37
C15: 2ºAndar Direito | F15: 450 | AC15: =SUM(D15:AB15) -> 450 | AD15: =37.5*12 -> 450 | AE15: =AD15-AC15 -> 0
C16: 2ºAndar Esquerdo | F16: 450 | AC16: =SUM(D16:AB16) -> 450 | AD16: =37.5*12 -> 450 | AE16: =AD16-AC16 -> 0
C17: 1ºAndar Direito | F17: 75 | J17: 75 | N17: 75 | T17: 75 | V17: 75 | AC17: =SUM(D17:AB17) -> 375 | AD17: =37.5*12 -> 450 | AE17: =AD17-AC17 -> 75
C18: 1ºAndar Esquerdo | D18: 37.5 | F18: 37.5 | H18: 37.5 | J18: 37.5 | L18: 37.5 | N18: 37.5 | P18: 37.5 | R18: 37.5 | T18: 37.5 | V18: 37.5 | X18: 37.5 | Z18: 75 | AC18: =SUM(D18:AB18) -> 487.5 | AD18: =37.5*12 -> 450 | AE18: =AD18-AC18 -> -37.5
C19: Res-Chão Direito | D19: 37.5 | F19: 37.5 | J19: 35 | N19: 35 | P19: 65 | T19: 35 | V19: 35 | AC19: =SUM(D19:AB19) -> 280 | AD19: =37.5*12 -> 450 | AE19: =AD19-AC19 -> 170
C20: Res-Chão Esquerdo | F20: 50 | L20: 180 | R20: 40 | V20: 40 | Z20: 40 | AC20: =SUM(D20:AB20) -> 350 | AD20: =37.5*12 -> 450 | AE20: =AD20-AC20 -> 100
C21: Cave -1 (Garagem) | AC21: =SUM(D21:AB21) -> 0 | AD21: =37.5*12 -> 450 | AE21: =AD21-AC21 -> 450
C22: Cave -2 | D22: 37.5 | F22: 37.5 | H22: 37.5 | J22: 37.5 | L22: 37.5 | N22: 37.5 | P22: 37.5 | R22: 37.5 | T22: 37.5 | V22: 37.5 | X22: 37.5 | Z22: 37.5 | AC22: =SUM(D22:AB22) -> 450 | AD22: =37.5*12 -> 450 | AE22: =AD22-AC22 -> 0
AD23: =37.5*12 -> 450 | AE23: =AD23-AC23 -> 450
C24: Levantamento Prazo | AD24: =37.5*12 -> 450 | AE24: =AD24-AC24 -> 450
C25: Reparação Portão -4 | N25: 40 | P25: 35
AC27: =SUM(D27:AB27) -> 0
C30: Total Receitas | D30: =D7+D8+D9+D10+D11+D12+D13+D14+D15+D16+D17+D18+D19+D20+D21+D22+D27 -> 403.75 | F30: =F7+F8+F9+F10+F11+F12+F13+F14+F15+F16+F17+F18+F19+F20+F21+F22+F27 -> 1346.25 | H30: =H7+H8+H9+H10+H11+H12+H13+H14+H15+H16+H17+H18+H19+H20+H21+H22+H27 -> 268.75 | J30: =J7+J8+J9+J10+J11+J12+J13+J14+J15+J16+J17+J18+J19+J20+J21+J22+J27 -> 431.25 | L30: =L7+L8+L9+L10+L11+L12+L13+L14+L15+L16+L17+L18+L19+L20+L21+L22+L25+L27 -> 419.25 | N30: =N7+N8+N9+N10+N11+N12+N13+N14+N15+N16+N17+N18+N19+N20+N21+N22+N24+N25+N27 -> 513.75 | P30: =P7+P8+P9+P10+P11+P12+P13+P14+P15+P16+P17+P18+P19+P20+P21+P22+P25+P27 -> 343.75 | R30: =R7+R8+R9+R10+R11+R12+R13+R14+R15+R16+R17+R18+R19+R20+R21+R22+R24+R25+R26+R27 -> 396.25 | T30: =T7+T8+T9+T10+T11+T12+T13+T14+T15+T16+T17+T18+T19+T20+T21+T22+T27 -> 391.25 | V30: =V7+V8+V9+V10+V11+V12+V13+V14+V15+V16+V17+V18+V19+V20+V21+V22+V27 -> 431.25 | X30: =X7+X8+X9+X10+X11+X12+X13+X14+X15+X16+X17+X18+X19+X20+X21+X22+X27 -> 431.25 | Z30: =Z7+Z8+Z9+Z10+Z11+Z12+Z13+Z14+Z15+Z16+Z17+Z18+Z19+Z20+Z21+Z22+Z27 -> 358.75 | AC30: =SUM(D30:AB30) -> 5735.5
C31: Monte Abraão, 31 de Dezembro de 2019 | K31: A Administração
C32: Condominio Rua Vieira da Silva, 6 | J32: Queluz - Monte Abraão | W32: Ano 2019
A33: DESPESAS
C35: Despesas | D35: Janeiro | F35: Fevereiro | H35: Março | J35: Abril | L35: Maio | N35: Junho | P35: Julho | R35: Agosto | T35: Setembro | V35: Outubro | X35: Novembro | Z35: Dezembro | AC35: TOTAL
C38: Electricidade | D38: 141 | F38: 130.78 | H38: 126.69 | J38: 113.73 | L38: 126.89 | N38: 123.04 | P38: 130.62 | R38: 125.44 | T38: 127.77 | V38: 123.41 | X38: 122.81 | Z38: 131.7 | AC38: =SUM(D38:AB38) -> 1523.88
C39: Elevadores | D39: 460.65 | F39: 153.55 | H39: 153.55 | J39: 153.55 | L39: 153.55 | N39: 153.55 | P39: 153.55 | R39: 146.05 | T39: 153.55 | V39: 153.55 | Z39: 161.23 | AC39: =SUM(D39:AB39) -> 1996.33
C40: Pintura Edificio | V40: 1250 | X40: 650 | AC40: =SUM(X40:AB40) -> 650
C41: Manutenção Central Bombagem | J41: 110.7 | AC41: =SUM(D41:AB41) -> 110.7
C42: Limpeza Escadas | P42: 616 | AC42: =SUM(D42:AB42) -> 616
C43: Manutenção Extintores | F43: 48 | AC43: =SUM(Z43:AB43) -> 0
C44: Despesas Bancárias | D44: 6.24 | F44: 6.24 | H44: 6.24 | J44: 7.28 | L44: 6.24 | N44: 6.24 | P44: 6.24 | R44: 6.24 | T44: 6.24 | V44: 6.24 | X44: 6.24 | Z44: 6.24 | AC44: =SUM(D44:AB44) -> 75.92
C45: Sarralheiro | V45: 78.19 | AC45: =SUM(D45:AB45) -> 78.19
C46: Manutenção Geral Edificio | D46: 4.97 | H46: 472.45 | N46: 120 | P46: 90 | AC46: =SUM(D46:AB46) -> 687.42
C47: Inspecção Elevadores | AC47: =SUM(D47:AB47) -> 0
C48: Depósitos Prazo Poupança | D48: 60 | F48: 60 | H48: 60 | J48: 60 | L48: 60 | N48: 60 | P48: 60 | R48: 60 | T48: 60 | V48: 60 | X48: 60 | Z48: 60 | AC48: =SUM(D48:AB48) -> 720
C51: Total Despesas | D51: =D38+D39+D40+D41+D42+D43+D44+D45+D46+D47+D48 -> 672.86 | F51: =F38+F39+F40+F41+F42+F43+F44+F45+F46+F47+F48 -> 398.57 | H51: =H38+H39+H40+H41+H42+H43+H44+H45+H46+H47+H48 -> 818.93 | J51: =J38+J39+J40+J41+J42+J43+J44+J45+J46+J47+J48 -> 445.26 | L51: =L38+L39+L40+L41+L42+L43+L44+L45+L46+L47+L48 -> 346.68 | N51: =N38+N39+N40+N41+N42+N43+N44+N45+N46+N47+N48 -> 462.83 | P51: =P38+P39+P40+P41+P42+P43+P44+P45+P46+P47+P48 -> 1056.41 | R51: =R38+R39+R40+R41+R42+R43+R44+R45+R46+R47+R48 -> 337.73 | T51: =T38+T39+T40+T41+T42+T43+T44+T45+T46+T47+T48 -> 347.56 | V51: =V38+V39+V40+V41+V42+V43+V44+V45+V46+V47+V48 -> 1671.39 | X51: =X38+X39+X40+X41+X42+X43+X44+X45+X46+X47+X48 -> 839.05 | Z51: =Z38+Z39+Z40+Z41+Z42+Z43+Z44+Z45+Z46+Z47+Z48 -> 359.17 | AC51: =SUM(D51:AB51) -> 7756.44
AC55: Total Liquido
C57: Resultados Liquidos | D57: =D30-D51 -> -269.11 | F57: =F30-F51 -> 947.68 | H57: =H30-H51 -> -550.18 | J57: =J30-J51 -> -14.01 | L57: =L30-L51 -> 72.57 | N57: =N30-N51 -> 50.92 | P57: =P30-P51 -> -712.66 | R57: =R30-R51 -> 58.52 | T57: =T30-T51 -> 43.69 | V57: =V30-V51 -> -1240.14 | X57: =X30-X51 -> -407.8 | Z57: =Z30-Z51 -> -0.42 | AC57: =SUM(D57:AB57) -> -2020.94
AC58: 720
J59: Monte Abraão, 31 de Dezembro de 2019 | AC59: =SUM(AC57:AC58) -> -1300.94
C61: Valor Transitado do Ano 2018 | D61: 3017.79 | M61: A Administração
C62: Receitas Ano 2019 | D62: =D30+F30+H30+J30+L30+N30+P30+R30+T30+V30+X30+Z30 -> 5735.5 | J62: Luís Dias - 5º Drt. | P62: Carlos Dias - 4º Drt.
D63: =SUM(D61:D62) -> 8753.29
C64: Despesas Ano 2019 - | D64: =D51+F51+H51+J51+L51+N51+P51+R51+T51+V51+X51+Z51 -> 7756.44
C65: Saldo a transitar para 2020 | D65: =D63-D64 -> 996.85
C67: Montepio Conta Corrente

Sheet Receita Despesa 2020
B1: Condominio Rua Vieira da Silva, 6 | I1: Queluz - Monte Abraão | V1: Ano 2020
B2: RECEITAS
B4: Receitas | C4: Janeiro | E4: Fevereiro | G4: Março | I4: Abril | K4: Maio | M4: Junho | O4: Julho | Q4: Agosto | S4: Setembro | U4: Outubro | W4: Novembro | Y4: Dezembro | AB4: TOTAL | AC4: Valor previsto | AD4: Valor em divida
B7: 6ºAndar Direito | C7: 75 | G7: 87.5 | I7: 77.5 | K7: 37.5 | M7: 37.5 | O7: 37.5 | Q7: 37.5 | U7: 37.5 | W7: 37.5 | Y7: 75 | AB7: =SUM(C7:AA7) -> 540 | AC7: =37.5*12 -> 450 | AD7: =AC7-AB7 -> -90
B8: 6ºAndar Esquerdo | C8: 75 | E8: 37.5 | I8: 75 | K8: 37.5 | M8: 37.5 | Q8: 75 | S8: 37.05 | U8: 40 | AB8: =SUM(C8:AA8) -> 414.55 | AC8: =37.5*12 -> 450 | AD8: =AC8-AB8 -> 35.45
B9: 5ºAndar Direito | I9: 37.5 | W9: 75 | Y9: 75 | AB9: =SUM(C9:AA9) -> 187.5 | AC9: =37.5*12 -> 450 | AD9: =AC9-AB9 -> 262.5
B10: 5 Andar Esquerdo | E10: 75 | G10: 37.5 | I10: 37.5 | K10: 37.5 | M10: 37.5 | O10: 37.5 | Q10: 37.5 | S10: 37.5 | U10: 37.5 | W10: 37.5 | Y10: 37.5 | AB10: =SUM(C10:AA10) -> 450 | AC10: =37.5*12 -> 450 | AD10: =AC10-AB10 -> 0
B11: 4ºAndar Direito | C11: 18.75 | E11: 18.75 | G11: 18.75 | I11: 18.75 | K11: 18.75 | M11: 18.75 | O11: 18.75 | Q11: 18.75 | S11: 18.75 | U11: 18.75 | W11: 18.75 | Y11: 18.75 | AB11: =SUM(C11:AA11) -> 225 | AC11: =18.75*12 -> 225 | AD11: =AC11-AB11 -> 0
B12: 4ºAndar Esquerdo | C12: 37.5 | E12: 37.5 | G12: 37.5 | I12: 37.5 | K12: 37.5 | M12: 37.5 | O12: 37.5 | Q12: 37.5 | S12: 37.5 | U12: 37.5 | W12: 37.5 | Y12: 37.5 | AB12: =SUM(C12:AA12) -> 450 | AC12: =37.5*12 -> 450 | AD12: =AC12-AB12 -> 0
B13: 3ºAndar Direito | C13: 37.5 | E13: 37.5 | G13: 37.5 | I13: 37.5 | K13: 37.5 | M13: 37.5 | O13: 37.5 | Q13: 37.5 | S13: 37.5 | U13: 37.5 | W13: 37.5 | Y13: 37.5 | AB13: =SUM(C13:AA13) -> 450 | AC13: =37.5*12 -> 450 | AD13: =AC13-AB13 -> 0
B14: 3ºAndar Esquerdo | C14: 75 | E14: 37.5 | G14: 37.5 | K14: 40 | O14: 100 | Q14: 80 | W14: 150 | Y14: 120 | AB14: =SUM(C14:AA14) -> 640 | AC14: =37.5*12 -> 450 | AD14: =AC14-AB14 -> -190
B15: 2ºAndar Direito | C15: 450 | AB15: =SUM(C15:AA15) -> 450 | AC15: =37.5*12 -> 450 | AD15: =AC15-AB15 -> 0
B16: 2ºAndar Esquerdo | C16: 450 | AB16: =SUM(C16:AA16) -> 450 | AC16: =37.5*12 -> 450 | AD16: =AC16-AB16 -> 0
B17: 1ºAndar Direito | C17: 75 | E17: 75 | I17: 75 | O17: 37.5 | S17: 75 | Y17: 75 | AB17: =SUM(C17:AA17) -> 412.5 | AC17: =37.5*12 -> 450 | AD17: =AC17-AB17 -> 37.5
B18: 1ºAndar Esquerdo | E18: 37.5 | G18: 37.5 | I18: 37.5 | K18: 37.5 | M18: 37.5 | O18: 37.5 | Q18: 37.5 | S18: 37.5 | U18: 37.5 | W18: 37.5 | Y18: 75 | AB18: =SUM(C18:AA18) -> 450 | AC18: =37.5*12 -> 450 | AD18: =AC18-AB18 -> 0
B19: Res-Chão Direito | E19: 105 | G19: 35 | I19: 35 | K19: 35 | M19: 35 | O19: 35 | Q19: 35 | S19: 35 | U19: 35 | W19: 35 | Y19: 70 | AB19: =SUM(C19:AA19) -> 490 | AC19: =37.5*12 -> 450 | AD19: =AC19-AB19 -> -40
B20: Res-Chão Esquerdo | E20: 40 | G20: 40 | I20: 40 | K20: 40 | M20: 40 | O20: 40 | Q20: 40 | W20: 40 | Y20: 40 | AB20: =SUM(C20:AA20) -> 360 | AC20: =37.5*12 -> 450 | AD20: =AC20-AB20 -> 90
B21: Cave -1 (Garagem) | C21: 450 | Y21: 450 | AB21: =SUM(C21:AA21) -> 900 | AC21: =37.5*12 -> 450 | AD21: =AC21-AB21 -> -450
B22: Cave -2 | C22: 37.5 | E22: 37.5 | G22: 37.5 | I22: 37.5 | K22: 37.5 | M22: 37.5 | O22: 37.5 | Q22: 37.5 | S22: 37.5 | U22: 37.5 | W22: 37.5 | Y22: 37.5 | AB22: =SUM(C22:AA22) -> 450 | AC22: =37.5*12 -> 450 | AD22: =AC22-AB22 -> 0
AC23: =37.5*12 -> 450 | AD23: =AC23-AB23 -> 450
B24: Levantamento Prazo | AC24: =37.5*12 -> 450 | AD24: =AC24-AB24 -> 450
B25: Claudia Rute Nunes Carriço
B26: Alfredo Santos Pereira 1ºDrt.
B30: Total Receitas | C30: =C7+C8+C9+C10+C11+C12+C13+C14+C15+C16+C17+C18+C19+C20+C21+C22+C27 -> 1781.25 | E30: =E7+E8+E9+E10+E11+E12+E13+E14+E15+E16+E17+E18+E19+E20+E21+E22+E27 -> 538.75 | G30: =G7+G8+G9+G10+G11+G12+G13+G14+G15+G16+G17+G18+G19+G20+G21+G22+G27 -> 406.25 | I30: =I7+I8+I9+I10+I11+I12+I13+I14+I15+I16+I17+I18+I19+I20+I21+I22+I27 -> 546.25 | K30: =K7+K8+K9+K10+K11+K12+K13+K14+K15+K16+K17+K18+K19+K20+K21+K22+K25+K27 -> 396.25 | M30: =M7+M8+M9+M10+M11+M12+M13+M14+M15+M16+M17+M18+M19+M20+M21+M22+M25+M27 -> 356.25 | O30: =O7+O8+O9+O10+O11+O12+O13+O14+O15+O16+O17+O18+O19+O20+O21+O22+O25+O26+O27 -> 456.25 | Q30: =Q7+Q8+Q9+Q10+Q11+Q12+Q13+Q14+Q15+Q16+Q17+Q18+Q19+Q20+Q21+Q22+Q24+Q25+Q26+Q27 -> 473.75 | S30: =S7+S8+S9+S10+S11+S12+S13+S14+S15+S16+S17+S18+S19+S20+S21+S22+S25+S27 -> 353.3 | U30: =U7+U8+U9+U10+U11+U12+U13+U14+U15+U16+U17+U18+U19+U20+U21+U22+U25+U27 -> 318.75 | W30: =W7+W8+W9+W10+W11+W12+W13+W14+W15+W16+W17+W18+W19+W20+W21+W22+W25+W27 -> 543.75 | Y30: =Y7+Y8+Y9+Y10+Y11+Y12+Y13+Y14+Y15+Y16+Y17+Y18+Y19+Y20+Y21+Y22+Y25+Y27 -> 1148.75 | AB30: =SUM(C30:AA30) -> 7319.55
B32: Condominio Rua Vieira da Silva, 6 | V32: Ano 2020
A33: DESPESAS
B35: Despesas | C35: Janeiro | E35: Fevereiro | G35: Março | I35: Abril | K35: Maio | M35: Junho | O35: Julho | Q35: Agosto | S35: Setembro | U35: Outubro | W35: Novembro | Y35: Dezembro | AB35: TOTAL
B38: Electricidade | C38: 126.32 | E38: 127.15 | G38: 131.21 | I38: 117.85 | K38: 118.83 | M38: 112.27 | O38: 120.39 | Q38: 117.59 | S38: 122.26 | U38: 116.55 | W38: 117.25 | Y38: 123.17 | AB38: =SUM(C38:AA38) -> 1450.84
B39: Elevadores | C39: 322.46 | E39: 161.23 | G39: 161.23 | I39: 161.23 | K39: 161.23 | M39: 161.23 | O39: 161.23 | Q39: 161.23 | S39: 161.23 | U39: 161.23 | W39: 168.49 | Y39: 168.49 | AB39: =SUM(C39:AA39) -> 2110.51
B40: Reparação Extra Elevadores | G40: 120.54 | I40: 120.54 | Q40: 405.9 | U40: 270.6 | W40: 135.3 | AB40: =SUM(C40:AA40) -> 1052.88
B41: Manutenção Central Bombagem | G41: 110.7 | AB41: =SUM(C41:AA41) -> 110.7
B42: Limpeza Escadas | C42: 616 | S42: 704 | AB42: =SUM(C42:AA42) -> 1320
B43: Manutenção Extintores | G43: 48 | AB43: =SUM(C43:AA43) -> 48
B44: Despesas Bancárias | C44: 6.24 | E44: 6.24 | G44: 5.2 | I44: 5.2 | K44: 5.2 | M44: 5.2 | O44: 5.2 | Q44: 5.2 | S44: 6.24 | U44: 5.2 | W44: 5.2 | Y44: 5.2 | AB44: =SUM(C44:AA44) -> 65.52
B45: Sarralheiro | AB45: =SUM(C45:AA45) -> 0
B46: Manutenção Geral Edificio | AB46: =SUM(C46:AA46) -> 0
B47: Inspecção Elevadores | C47: 280 | AB47: =SUM(C47:AA47) -> 280
B48: Depósitos Prazo Poupança | C48: 60 | E48: 60 | G48: 60 | I48: 60 | K48: 60 | M48: 60 | O48: 60 | Q48: 60 | S48: 60 | U48: 60 | W48: 60 | Y48: 60 | AB48: =SUM(C48:AA48) -> 720
B51: Total Despesas | C51: =C38+C39+C40+C41+C42+C43+C44+C45+C46+C47+C48 -> 1411.02 | E51: =E38+E39+E40+E41+E42+E43+E44+E45+E46+E47+E48 -> 354.62 | G51: =G38+G39+G40+G41+G42+G43+G44+G45+G46+G47+G48 -> 636.88 | I51: =I38+I39+I40+I41+I42+I43+I44+I45+I46+I47+I48 -> 464.82 | K51: =K38+K39+K40+K41+K42+K43+K44+K45+K46+K47+K48 -> 345.26 | M51: =M38+M39+M40+M41+M42+M43+M44+M45+M46+M47+M48 -> 338.7 | O51: =O38+O39+O40+O41+O42+O43+O44+O45+O46+O47+O48 -> 346.82 | Q51: =Q38+Q39+Q40+Q41+Q42+Q43+Q44+Q45+Q46+Q47+Q48 -> 749.92 | S51: =S38+S39+S40+S41+S42+S43+S44+S45+S46+S47+S48 -> 1053.73 | U51: =U38+U39+U40+U41+U42+U43+U44+U45+U46+U47+U48 -> 613.58 | W51: =W38+W39+W40+W41+W42+W43+W44+W45+W46+W47+W48 -> 486.24 | Y51: =Y38+Y39+Y40+Y41+Y42+Y43+Y44+Y45+Y46+Y47+Y48 -> 356.86 | AB51: =SUM(C51:AA51) -> 7158.45
AB55: Total Liquido
B57: Resultados Liquidos | C57: =C30-C51 -> 370.23 | E57: =E30-E51 -> 184.13 | G57: =G30-G51 -> -230.63 | I57: =I30-I51 -> 81.43 | K57: =K30-K51 -> 50.99 | M57: =M30-M51 -> 17.55 | O57: =O30-O51 -> 109.43 | Q57: =Q30-Q51 -> -276.17 | S57: =S30-S51 -> -700.43 | U57: =U30-U51 -> -294.83 | W57: =W30-W51 -> 57.51 | Y57: =Y30-Y51 -> 791.89 | AB57: =SUM(C57:AA57) -> 161.1
I59: Monte Abraão, 31 de Dezembro de 2020
B61: Valor Transitado do Ano 2019 | C61: 996.85 | L61: A Administração
B62: Receitas Ano 2020 | C62: =C30+E30+G30+I30+K30+M30+O30+Q30+S30+U30+W30+Y30 -> 7319.55 | I62: Luís Dias - 5º Drt. | O62: Carlos Dias - 4º Drt.
C63: =SUM(C61:C62) -> 8316.4
B64: Despesas Ano 2020 - | C64: =C51+E51+G51+I51+K51+M51+O51+Q51+S51+U51+W51+Y51 -> 7158.45
B65: Saldo a transitar para 2021 | C65: =C63-C64 -> 1157.95
B67: Montepio Conta Corrente

Sheet Receita Despesas 2021
B1: Condominio Rua Vieira da Silva, 6 | I1: Queluz - Monte Abraão | V1: Ano 2021
B2: RECEITAS
B4: Receitas | C4: Janeiro | E4: Fevereiro | G4: Março | I4: Abril | K4: Maio | M4: Junho | O4: Julho | Q4: Agosto | S4: Setembro | U4: Outubro | W4: Novembro | Y4: Dezembro | AB4: TOTAL | AC4: Valor previsto Valor em divida
B7: 6ºAndar Direito | C7: 205.22 | E7: 37.5 | G7: 37.5 | I7: 37.5 | K7: 37.5 | M7: 37.5 | O7: 37.5 | Q7: 37.5 | S7: 37.5 | U7: 37.5 | W7: 37.5 | Y7: 37.5 | AB7: =SUM(C7:AA7) -> 617.72 | AC7: =37.5*12 -> 450 | AD7: =AC7-AB7 -> -167.72
B8: 6ºAndar Esquerdo | C8: 73 | E8: 37.5 | G8: 37.5 | I8: 37.5 | M8: 75 | Q8: 75 | S8: 37.5 | U8: 37.5 | AB8: =SUM(C8:AA8) -> 410.5 | AC8: =37.5*12 -> 450 | AD8: =AC8-AB8 -> 39.5
B9: 5ºAndar Direito | C9: 37.5 | G9: 37.5 | U9: 75 | Y9: 75 | AB9: =SUM(C9:AA9) -> 225 | AC9: =37.5*12 -> 450 | AD9: =AC9-AB9 -> 225
B10: 5 Andar Esquerdo | C10: 37.5 | E10: 37.5 | G10: 37.5 | I10: 37.5 | K10: 37.5 | M10: 37.5 | O10: 37.5 | Q10: 37.5 | S10: 37.5 | U10: 37.5 | W10: 37.5 | Y10: 37.5 | AB10: =SUM(C10:AA10) -> 450 | AC10: =37.5*12 -> 450 | AD10: =AC10-AB10 -> 0
B11: 4ºAndar Direito | C11: 18.75 | E11: 18.75 | G11: 18.75 | I11: 18.75 | K11: 18.75 | M11: 18.75 | O11: 18.75 | Q11: 18.75 | S11: 18.75 | U11: 18.75 | W11: 18.75 | Y11: 18.75 | AB11: =SUM(C11:AA11) -> 225 | AC11: =18.75*12 -> 225 | AD11: =AC11-AB11 -> 0
B12: 4ºAndar Esquerdo | C12: 37.5 | E12: 37.5 | G12: 37.5 | I12: 37.5 | K12: 37.5 | M12: 37.5 | O12: 37.5 | Q12: 37.5 | S12: 37.5 | U12: 37.5 | W12: 37.5 | Y12: 37.5 | AB12: =SUM(C12:AA12) -> 450 | AC12: =37.5*12 -> 450 | AD12: =AC12-AB12 -> 0
B13: 3ºAndar Direito | C13: 37.5 | E13: 37.5 | G13: 37.5 | I13: 37.5 | K13: 37.5 | M13: 37.5 | O13: 37.5 | Q13: 37.5 | S13: 37.5 | U13: 37.5 | W13: 37.5 | Y13: 37.5 | AB13: =SUM(C13:AA13) -> 450 | AC13: =37.5*12 -> 450 | AD13: =AC13-AB13 -> 0
B14: 3ºAndar Esquerdo | G14: 120 | O14: 37.5 | S14: 120 | W14: 75 | AB14: =SUM(C14:AA14) -> 352.5 | AC14: =37.5*12 -> 450 | AD14: =AC14-AB14 -> 97.5
B15: 2ºAndar Direito | C15: 450 | AB15: =SUM(C15:AA15) -> 450 | AC15: =37.5*12 -> 450 | AD15: =AC15-AB15 -> 0
B16: 2ºAndar Esquerdo | C16: 450 | AB16: =SUM(C16:AA16) -> 450 | AC16: =37.5*12 -> 450 | AD16: =AC16-AB16 -> 0
B17: 1ºAndar Direito | C17: 112.5 | E17: 75 | G17: 37.5 | K17: 75 | O17: 75 | S17: 75 | U17: 37.5 | W17: 37.5 | Y17: 37.5 | AB17: =SUM(C17:AA17) -> 562.5 | AC17: =37.5*12 -> 450 | AD17: =AC17-AB17 -> -112.5
B18: 1ºAndar Esquerdo | E18: 37.5 | G18: 75 | I18: 37.5 | M18: 37.5 | O18: 37.5 | Q18: 37.5 | S18: 37.5 | U18: 37.5 | W18: 37.5 | Y18: 75 | AB18: =SUM(C18:AA18) -> 450 | AC18: =37.5*12 -> 450 | AD18: =AC18-AB18 -> 0
B19: Res-Chão Direito | E19: 35 | G19: 55 | I19: 35 | K19: 35 | M19: 70 | Q19: 45 | S19: 45 | U19: 45 | W19: 45 | Y19: 45 | AB19: =SUM(C19:AA19) -> 455 | AC19: =37.5*12 -> 450 | AD19: =AC19-AB19 -> -5
B20: Res-Chão Esquerdo | C20: 40 | G20: 40 | I20: 40 | K20: 40 | O20: 40 | Q20: 40 | W20: 40 | Y20: 40 | AB20: =SUM(C20:AA20) -> 320 | AC20: =37.5*12 -> 450 | AD20: =AC20-AB20 -> 130
B21: Cave -1 (Garagem) | W21: 450 | AB21: =SUM(C21:AA21) -> 450 | AC21: =37.5*12 -> 450 | AD21: =AC21-AB21 -> 0
B22: Cave -2 | C22: 37.5 | E22: 37.5 | G22: 37.5 | I22: 37.5 | K22: 37.5 | M22: 37.5 | O22: 37.5 | Q22: 37.5 | S22: 37.5 | U22: 37.5 | W22: 37.5 | Y22: 37.5 | AB22: =SUM(C22:AA22) -> 450 | AC22: =37.5*12 -> 450 | AD22: =AC22-AB22 -> 0
B24: Levantamento Prazo
B30: Total Receitas | C30: =C7+C8+C9+C10+C11+C12+C13+C14+C15+C16+C17+C18+C19+C20+C21+C22+C27 -> 1536.97 | E30: =E7+E8+E9+E10+E11+E12+E13+E14+E15+E16+E17+E18+E19+E20+E21+E22+E27 -> 391.25 | G30: =G7+G8+G9+G10+G11+G12+G13+G14+G15+G16+G17+G18+G19+G20+G21+G22+G27 -> 608.75 | I30: =I7+I8+I9+I10+I11+I12+I13+I14+I15+I16+I17+I18+I19+I20+I21+I22+I27 -> 356.25 | K30: =K7+K8+K9+K10+K11+K12+K13+K14+K15+K16+K17+K18+K19+K20+K21+K22+K25+K27 -> 356.25 | M30: =M7+M8+M9+M10+M11+M12+M13+M14+M15+M16+M17+M18+M19+M20+M21+M22+M25+M27 -> 388.75 | O30: =O7+O8+O9+O10+O11+O12+O13+O14+O15+O16+O17+O18+O19+O20+O21+O22+O25+O26+O27 -> 396.25 | Q30: =Q7+Q8+Q9+Q10+Q11+Q12+Q13+Q14+Q15+Q16+Q17+Q18+Q19+Q20+Q21+Q22+Q24+Q25+Q26+Q27 -> 403.75 | S30: =S7+S8+S9+S10+S11+S12+S13+S14+S15+S16+S17+S18+S19+S20+S21+S22+S25+S27 -> 521.25 | U30: =U7+U8+U9+U10+U11+U12+U13+U14+U15+U16+U17+U18+U19+U20+U21+U22+U25+U27 -> 438.75 | W30: =W7+W8+W9+W10+W11+W12+W13+W14+W15+W16+W17+W18+W19+W20+W21+W22+W25+W27 -> 891.25 | Y30: =Y7+Y8+Y9+Y10+Y11+Y12+Y13+Y14+Y15+Y16+Y17+Y18+Y19+Y20+Y21+Y22+Y25+Y27 -> 478.75 | AB30: =SUM(C30:AA30) -> 6768.22
B32: Condominio Rua Vieira da Silva, 6 | V32: Ano 2021
A33: DESPESAS
B35: Despesas | C35: Janeiro | E35: Fevereiro | G35: Março | I35: Abril | K35: Maio | M35: Junho | O35: Julho | Q35: Agosto | S35: Setembro | U35: Outubro | W35: Novembro | Y35: Dezembro | AB35: TOTAL
B38: Electricidade | C38: 114.58 | E38: 123.65 | G38: 125.06 | I38: 98.38 | K38: 110.58 | M38: 107.76 | O38: 108.59 | Q38: 108.87 | S38: 111.47 | U38: 105.85 | W38: 106.5 | Y38: 112.04 | AB38: =SUM(C38:AA38) -> 1333.33
B39: Elevadores | C39: 168.49 | E39: 168.49 | G39: 168.49 | I39: 168.49 | K39: 168.49 | M39: 168.49 | O39: 168.49 | Q39: 168.49 | S39: 168.49 | U39: 168.49 | Y39: 352.12 | AB39: =SUM(C39:AA39) -> 2037.02
B40: Reparação Extra Elevadores | Y40: 516.6 | AB40: =SUM(C40:AA40) -> 516.6
B41: Manutenção Central Bombagem | C41: 110.7 | AB41: =SUM(C41:AA41) -> 110.7
B42: Limpeza Escadas | G42: 528 | S42: 528 | AB42: =SUM(C42:AA42) -> 1056
B43: Manutenção Extintores | E43: 54.5 | AB43: =SUM(C43:AA43) -> 54.5
B44: Despesas Bancárias | C44: 5.2 | E44: 5.2 | G44: 5.2 | I44: 5.2 | K44: 5.2 | M44: 5.2 | O44: 5.2 | Q44: 5.2 | S44: 5.2 | U44: 5.2 | W44: 5.2 | Y44: 5.2 | AB44: =SUM(C44:AA44) -> 62.4
B45: Lampada parqueamento -3 | G45: 5.15 | S45: 6.95 | AB45: =SUM(C45:AA45) -> 12.1
B46: Manutenção Geral Edificio | AB46: =SUM(C46:AA46) -> 0
B47: Inspecção Elevadores | AB47: =SUM(C47:AA47) -> 0
B48: Depósitos Prazo Poupança | C48: 60 | E48: 60 | G48: 60 | I48: 60 | K48: 60 | M48: 60 | O48: 60 | Q48: 60 | S48: 60 | U48: 60 | W48: 60 | Y48: 60 | AB48: =SUM(C48:AA48) -> 720
B51: Total Despesas | C51: =SUM(C38:C48) -> 458.97 | E51: =SUM(E38:E48) -> 411.84 | G51: =SUM(G38:G48) -> 891.9 | I51: =SUM(I38:I48) -> 332.07 | K51: =SUM(K38:K48) -> 344.27 | M51: =SUM(M38:M48) -> 341.45 | O51: =SUM(O38:O48) -> 342.28 | Q51: =SUM(Q38:Q48) -> 342.56 | S51: =SUM(S38:S48) -> 880.11 | U51: =SUM(U38:U48) -> 339.54 | W51: =SUM(W38:W48) -> 171.7 | Y51: =SUM(Y38:Y48) -> 1045.96 | AB51: =SUM(C51:AA51) -> 5902.65
AB55: Total Liquido
B57: Resultados Liquidos | C57: =C30-C51 -> 1078 | E57: =E30-E51 -> -20.59 | G57: =G30-G51 -> -283.15 | I57: =I30-I51 -> 24.18 | K57: =K30-K51 -> 11.98 | M57: =M30-M51 -> 47.3 | O57: =O30-O51 -> 53.97 | Q57: =Q30-Q51 -> 61.19 | S57: =S30-S51 -> -358.86 | U57: =U30-U51 -> 99.21 | W57: =W30-W51 -> 719.55 | Y57: =Y30-Y51 -> -567.21 | AB57: =SUM(C57:AA57) -> 865.57
I59: Monte Abraão, 31 de Dezembro de 2021
B61: Valor Transitado do Ano 2019 | C61: 1157.95 | L61: A Administração
B62: Receitas Ano 2020 | C62: =C30+E30+G30+I30+K30+M30+O30+Q30+S30+U30+W30+Y30 -> 6768.22 | I62: Luís Dias - 5º Drt. | O62: Carlos Dias - 4º Drt.
C63: =SUM(C61:C62) -> 7926.17
B64: Despesas Ano 2020 - | C64: =C51+E51+G51+I51+K51+M51+O51+Q51+S51+U51+W51+Y51 -> 5902.65
B65: Saldo a transitar para 2021 | C65: =C63-C64 -> 2023.52
B67: Montepio Conta Corrente

Sheet Receita Despesas 2022
B1: Condominio Rua Vieira da Silva, 6 | I1: Queluz - Monte Abraão | V1: Ano 2022
B2: RECEITAS
B4: Receitas | C4: Janeiro | E4: Fevereiro | G4: Março | I4: Abril | K4: Maio | M4: Junho | O4: Julho | Q4: Agosto | S4: Setembro | U4: Outubro | W4: Novembro | Y4: Dezembro | AB4: TOTAL | AC4: valor esperado | AD4: valor em divida
B7: 6ºAndar Direito | C7: 37.5 | K7: 75 | M7: 37.5 | O7: 37.5 | Y7: 37.5 | AB7: =SUM(C7:AA7) -> 225 | AC7: =37.5*12+200 -> 650 | AD7: =AC7-AB7 -> 425
B8: 6ºAndar Esquerdo | C8: 75 | G8: 75 | K8: 75 | O8: 75 | Q8: 37.5 | U8: 75 | W8: 37.5 | AB8: =SUM(C8:AA8) -> 450 | AC8: =37.5*12+200 -> 650 | AD8: =AC8-AB8 -> 200
B9: 5ºAndar Direito | C9: 37.5 | E9: 37.5 | G9: 150 | W9: 200 | AB9: =SUM(C9:AA9) -> 425 | AC9: =37.5*12+200 -> 650 | AD9: =AC9-AB9 -> 225
B10: 5 Andar Esquerdo | C10: 37.5 | E10: 37.5 | G10: 37.5 | I10: 37.5 | K10: 37.5 | M10: 37.5 | O10: 37.5 | Q10: 37.5 | S10: 37.5 | U10: 37.5 | W10: 37.5 | Y10: 37.5 | AB10: =SUM(C10:AA10) -> 450 | AC10: =37.5*12+200 -> 650 | AD10: =AC10-AB10 -> 200
B11: 4ºAndar Direito | C11: 18.75 | E11: 18.75 | G11: 18.75 | I11: 43.75 | K11: 43.75 | M11: 43.75 | O11: 43.75 | Q11: 43.75 | S11: 43.75 | U11: 43.75 | W11: 43.75 | Y11: 18.75 | AB11: =SUM(C11:AA11) -> 425 | AC11: =37.5*12+200 -> 650 | AD11: =AC11-AB11 -> 225
B12: 4ºAndar Esquerdo | C12: 37.5 | E12: 37.5 | G12: 37.5 | I12: 37.5 | K12: 137.5 | M12: 37.5 | O12: 137.5 | Q12: 37.5 | S12: 37.5 | U12: 37.5 | W12: 37.5 | Y12: 37.5 | AB12: =SUM(C12:AA12) -> 650 | AC12: =37.5*12+200 -> 650 | AD12: =AC12-AB12 -> 0
B13: 3ºAndar Direito | C13: 37.5 | E13: 37.5 | G13: 37.5 | I13: 37.5 | K13: 75 | M13: 37.5 | O13: 37.5 | Q13: 37.5 | S13: 37.5 | U13: 37.5 | W13: 37.5 | Y13: 37.5 | AB13: =SUM(C13:AA13) -> 487.5 | AC13: =37.5*12+200 -> 650 | AD13: =AC13-AB13 -> 162.5
B14: 3ºAndar Esquerdo | E14: 75 | I14: 37.5 | K14: 75 | S14: 75 | W14: 75 | AB14: =SUM(C14:AA14) -> 337.5 | AC14: =37.5*12+200 -> 650 | AD14: =AC14-AB14 -> 312.5
B15: 2ºAndar Direito | G15: 450 | AB15: =SUM(C15:AA15) -> 450 | AC15: =37.5*12+200 -> 650 | AD15: =AC15-AB15 -> 200
B16: 2ºAndar Esquerdo | G16: 450 | AB16: =SUM(C16:AA16) -> 450 | AC16: =37.5*12+200 -> 650 | AD16: =AC16-AB16 -> 200
B17: 1ºAndar Direito | C17: 37.5 | E17: 37.5 | G17: 37.5 | I17: 37.5 | K17: 37.5 | M17: 37.5 | O17: 37.5 | Q17: 37.5 | S17: 37.5 | U17: 37.5 | AB17: =SUM(C17:AA17) -> 375 | AC17: =37.5*12+200 -> 650 | AD17: =AC17-AB17 -> 275
B18: 1ºAndar Esquerdo | E18: 37.5 | G18: 75 | K18: 87.5 | M18: 87.5 | O18: 50 | Q18: 87.5 | S18: 37.5 | U18: 37.5 | W18: 37.5 | Y18: 37.5 | AB18: =SUM(C18:AA18) -> 575 | AC18: =37.5*12+200 -> 650 | AD18: =AC18-AB18 -> 75
B19: Res-Chão Direito | C19: 45 | E19: 45 | G19: 42.5 | I19: 70 | K19: 50 | M19: 55 | O19: 50 | Q19: 50 | S19: 50 | U19: 50 | W19: 35 | Y19: 50 | AB19: =SUM(C19:AA19) -> 592.5 | AC19: =37.5*12+200 -> 650 | AD19: =AC19-AB19 -> 57.5
B20: Res-Chão Esquerdo | C20: 40 | E20: 40 | I20: 40 | O20: 40 | Q20: 40 | S20: 40 | U20: 40 | W20: 40 | Y20: 40 | AB20: =SUM(C20:AA20) -> 360 | AC20: =37.5*12+200 -> 650 | AD20: =AC20-AB20 -> 290
B21: Cave -1 (Garagem) | W21: 450 | AB21: =SUM(C21:AA21) -> 450 | AC21: =37.5*12+200 -> 650 | AD21: =AC21-AB21 -> 200
B22: Cave -2 | C22: 37.5 | E22: 37.5 | G22: 37.5 | I22: 37.5 | K22: 237.5 | M22: 37.5 | O22: 37.5 | Q22: 37.5 | S22: 37.5 | U22: 37.5 | W22: 37.5 | Y22: 37.5 | AB22: =SUM(C22:AA22) -> 650 | AC22: =37.5*12+200 -> 650 | AD22: =AC22-AB22 -> 0
AC23: =37.5*12+200 -> 650
B24: Levantamento Prazo | AB24: =SUM(C24:AA24) -> 0
B25: Processo 6º Drt. | I25: 789.75 | AB25: =SUM(C25:AA25) -> 789.75
AB26: =SUM(C26:AA26) -> 0
AB27: =SUM(C27:AA27) -> 0
B30: Total Receitas | C30: =C7+C8+C9+C10+C11+C12+C13+C14+C15+C16+C17+C18+C19+C20+C21+C22+C27 -> 441.25 | E30: =E7+E8+E9+E10+E11+E12+E13+E14+E15+E16+E17+E18+E19+E20+E21+E22+E27 -> 441.25 | G30: =G7+G8+G9+G10+G11+G12+G13+G14+G15+G16+G17+G18+G19+G20+G21+G22+G27 -> 1448.75 | I30: =I7+I8+I9+I10+I11+I12+I13+I14+I15+I16+I17+I18+I19+I20+I21+I22+I27+I25 -> 1168.5 | K30: =K7+K8+K9+K10+K11+K12+K13+K14+K15+K16+K17+K18+K19+K20+K21+K22+K25+K27 -> 931.25 | M30: =M7+M8+M9+M10+M11+M12+M13+M14+M15+M16+M17+M18+M19+M20+M21+M22+M25+M27 -> 411.25 | O30: =O7+O8+O9+O10+O11+O12+O13+O14+O15+O16+O17+O18+O19+O20+O21+O22+O25+O26+O27 -> 583.75 | Q30: =Q7+Q8+Q9+Q10+Q11+Q12+Q13+Q14+Q15+Q16+Q17+Q18+Q19+Q20+Q21+Q22+Q24+Q25+Q26+Q27 -> 446.25 | S30: =S7+S8+S9+S10+S11+S12+S13+S14+S15+S16+S17+S18+S19+S20+S21+S22+S25+S27 -> 433.75 | U30: =U7+U8+U9+U10+U11+U12+U13+U14+U15+U16+U17+U18+U19+U20+U21+U22+U25+U27 -> 433.75 | W30: =W7+W8+W9+W10+W11+W12+W13+W14+W15+W16+W17+W18+W19+W20+W21+W22+W25+W27 -> 1068.75 | Y30: =Y7+Y8+Y9+Y10+Y11+Y12+Y13+Y14+Y15+Y16+Y17+Y18+Y19+Y20+Y21+Y22+Y25+Y27 -> 333.75 | AB30: =SUM(C30:AA30) -> 8142.25
B32: Condominio Rua Vieira da Silva, 6 | V32: Ano 2022
A33: DESPESAS
B35: Despesas | C35: Janeiro | E35: Fevereiro | G35: Março | I35: Abril | K35: Maio | M35: Junho | O35: Julho | Q35: Agosto | S35: Setembro | U35: Outubro | W35: Novembro | Y35: Dezembro | AB35: TOTAL
B38: Electricidade | C38: 108.29 | E38: 104.74 | G38: 84.26 | I38: 77.22 | K38: 84.99 | M38: 82.24 | O38: 105.37 | Q38: 99.77 | S38: 91.65 | U38: 88.53 | W38: 87.65 | Y38: 89.08 | AB38: =SUM(C38:AA38) -> 1103.79
B39: Elevadores | C39: 176.06 | E39: 176.06 | G39: 176.06 | I39: 176.06 | K39: 176.06 | M39: 176.06 | O39: 176.06 | Q39: 176.06 | S39: 176.06 | U39: 176.06 | AB39: =SUM(C39:AA39) -> 1760.6
B40: Reparação Extra Elevadores | G40: 866.42 | I40: 381.3 | AB40: =SUM(C40:AA40) -> 1247.72
B41: Manutenção Central Bombagem | O41: 110.7 | AB41: =SUM(C41:AA41) -> 110.7
B42: Limpeza Escadas | G42: 543 | S42: 744 | AB42: =SUM(C42:AA42) -> 1287
B43: Manutenção Extintores | E43: 94 | G43: 1.77 | AB43: =SUM(C43:AA43) -> 95.77
B44: Despesas Bancárias | C44: 5.2 | E44: 5.2 | G44: 5.2 | I44: 5.2 | K44: 5.2 | M44: 5.2 | O44: 5.2 | Q44: 5.2 | S44: 5.2 | U44: 6.24 | W44: 5.2 | Y44: 5.2 | AB44: =SUM(C44:AA44) -> 63.44
B45: Lampada parqueamento -3 | AB45: =SUM(C45:AA45) -> 0
B46: Manutenção Geral Edificio | AB46: =SUM(C46:AA46) -> 0
B47: Inspecção Elevadores | C47: 280 | AB47: =SUM(C47:AA47) -> 280
B48: Depósitos Prazo Poupança | C48: 60 | E48: 60 | G48: 60 | I48: 60 | K48: 60 | M48: 60 | O48: 60 | Q48: 60 | S48: 60 | U48: 60 | W48: 60 | Y48: 60 | AB48: =SUM(C48:AA48) -> 720
B51: Total Despesas | C51: =SUM(C38:C48) -> 629.55 | E51: =SUM(E38:E48) -> 440 | G51: =SUM(G38:G48) -> 1736.71 | I51: =SUM(I38:I48) -> 699.78 | K51: =SUM(K38:K48) -> 326.25 | M51: =SUM(M38:M48) -> 323.5 | O51: =SUM(O38:O48) -> 457.33 | Q51: =SUM(Q38:Q48) -> 341.03 | S51: =SUM(S38:S48) -> 1076.91 | U51: =SUM(U38:U48) -> 330.83 | W51: =SUM(W38:W48) -> 152.85 | Y51: =SUM(Y38:Y48) -> 154.28 | AB51: =SUM(C51:AA51) -> 6669.02
AB55: Total Liquido
B57: Resultados Liquidos | C57: =C30-C51 -> -188.3 | E57: =E30-E51 -> 1.25 | G57: =G30-G51 -> -287.96 | I57: =I30-I51 -> 468.72 | K57: =K30-K51 -> 605 | M57: =M30-M51 -> 87.75 | O57: =O30-O51 -> 126.42 | Q57: =Q30-Q51 -> 105.22 | S57: =S30-S51 -> -643.16 | U57: =U30-U51 -> 102.92 | W57: =W30-W51 -> 915.9 | Y57: =Y30-Y51 -> 179.47 | AB57: =SUM(C57:AA57) -> 1473.23
I59: Monte Abraão, 31 de Dezembro de 2022
B61: Valor Transitado do Ano 2021 | C61: 2023.52 | L61: A Administração
B62: Receitas Ano 2022 | C62: =C30+E30+G30+I30+K30+M30+O30+Q30+S30+U30+W30+Y30 -> 8142.25 | I62: Luís Dias - 5º Drt. | O62: Carlos Dias - 4º Drt.
C63: =SUM(C61:C62) -> 10165.77
B64: Despesas Ano 2022 - | C64: =C51+E51+G51+I51+K51+M51+O51+Q51+S51+U51+W51+Y51 -> 6669.02
B65: Saldo a transitar para 2023 | C65: =C63-C64 -> 3496.75
B67: Montepio Conta Corrente

Sheet Receitas Despesas 2023
B1: Condominio Rua Vieira da Silva, 6 | I1: Queluz - Monte Abraão | V1: Ano 2023
B2: RECEITAS
B4: Receitas | C4: Janeiro | E4: Fevereiro | G4: Março | I4: Abril | K4: Maio | M4: Junho | O4: Julho | Q4: Agosto | S4: Setembro | U4: Outubro | W4: Novembro | Y4: Dezembro | AB4: TOTAL
B7: 6ºAndar Direito | C7: 37.5 | I7: 37.5 | U7: 37.5 | AB7: =SUM(C7:AA7) -> 112.5 | AC7: =37.5*12 -> 450 | AD7: =AC7-AB7 -> 337.5
B8: 6ºAndar Esquerdo | C8: 75 | E8: 237.5 | G8: 37.5 | I8: 37.5 | K8: 37.5 | M8: 37.5 | O8: 37.5 | Q8: 37.5 | S8: 37.5 | U8: 37.5 | W8: 37.5 | Y8: 37.5 | AB8: =SUM(C8:AA8) -> 687.5 | AC8: =37.5*12 -> 450 | AD8: =AC8-AB8 -> -237.5
B9: 5ºAndar Direito | C9: 150 | M9: 75 | O9: 75 | S9: 75 | W9: 75 | AB9: =SUM(C9:AA9) -> 450 | AC9: =37.5*12 -> 450 | AD9: =AC9-AB9 -> 0
B10: 5 Andar Esquerdo | C10: 37.5 | E10: 37.5 | G10: 37.5 | I10: 37.5 | K10: 37.5 | M10: 237.5 | O10: 37.5 | Q10: 37.5 | S10: 37.5 | U10: 37.5 | W10: 37.5 | Y10: 37.5 | AB10: =SUM(C10:AA10) -> 650 | AC10: =37.5*12 -> 450 | AD10: =AC10-AB10 -> -200
B11: 4ºAndar Direito | C11: 37.5 | E11: 237.5 | G11: 37.5 | I11: 37.5 | K11: 37.5 | M11: 37.5 | O11: 37.5 | Q11: 37.5 | S11: 37.5 | U11: 37.5 | W11: 37.5 | Y11: 37.5 | AB11: =SUM(C11:AA11) -> 650 | AC11: =37.5*12 -> 450 | AD11: =AC11-AB11 -> -200
B12: 4ºAndar Esquerdo | C12: 37.5 | E12: 37.5 | G12: 37.5 | I12: 37.5 | K12: 37.5 | M12: 37.5 | O12: 37.5 | Q12: 37.5 | S12: 37.5 | U12: 37.5 | W12: 37.5 | Y12: 37.5 | AB12: =SUM(C12:AA12) -> 450 | AC12: =37.5*12 -> 450 | AD12: =AC12-AB12 -> 0
B13: 3ºAndar Direito | C13: 37.5 | E13: 137.5 | G13: 87.5 | I13: 37.5 | K13: 37.5 | M13: 37.5 | O13: 37.5 | Q13: 37.5 | S13: 37.5 | U13: 37.5 | W13: 37.5 | Y13: 37.5 | AB13: =SUM(C13:AA13) -> 600 | AC13: =37.5*12 -> 450 | AD13: =AC13-AB13 -> -150
B14: 3ºAndar Esquerdo | C14: 120 | E14: 117.5 | G14: 37.5 | I14: 200 | K14: 150 | O14: 37.5 | S14: 75 | U14: 75 | W14: 37.5 | AB14: =SUM(C14:AA14) -> 850 | AC14: =37.5*12 -> 450 | AD14: =AC14-AB14 -> -400
B15: 2ºAndar Direito | C15: 650 | AB15: =SUM(C15:AA15) -> 650 | AC15: =37.5*12 -> 450 | AD15: =AC15-AB15 -> -200
B16: 2ºAndar Esquerdo | C16: 650 | AB16: =SUM(C16:AA16) -> 650 | AC16: =37.5*12 -> 450 | AD16: =AC16-AB16 -> -200
B17: 1ºAndar Direito | C17: 112.5 | E17: 237.5 | G17: 37.5 | I17: 37.5 | K17: 37.5 | O17: 75 | Q17: 37.5 | S17: 37.5 | U17: 37.5 | W17: 37.5 | Y17: 37.5 | AB17: =SUM(C17:AA17) -> 725 | AC17: =37.5*12 -> 450 | AD17: =AC17-AB17 -> -275
B18: 1ºAndar Esquerdo | C18: 112.5 | G18: 37.5 | K18: 75 | M18: 37.5 | S18: 75 | U18: 37.5 | W18: 37.5 | Y18: 37.5 | AB18: =SUM(C18:AA18) -> 450 | AC18: =37.5*12 -> 450 | AD18: =AC18-AB18 -> 0
B19: Res-Chão Direito | C19: 35 | E19: 32.5 | G19: 32.5 | I19: 35 | K19: 40 | M19: 17.5 | O19: 17.5 | Q19: 17.5 | S19: 17.5 | U19: 17.5 | W19: 17.5 | Y19: 17.5 | AB19: =SUM(C19:AA19) -> 297.5 | AC19: =32.5*5+17.5*7 -> 285 | AD19: =AC19-AB19 -> -12.5
B20: Res-Chão Esquerdo | C20: 40 | E20: 140 | G20: 50 | I20: 100 | M20: 50 | O20: 50 | Q20: 50 | S20: 50 | U20: 50 | W20: 50 | Y20: 50 | AB20: =SUM(C20:AA20) -> 680 | AC20: =37.5*12 -> 450 | AD20: =AC20-AB20 -> -230
B21: Cave -1 (Garagem) | Y21: 450 | AB21: =SUM(C21:AA21) -> 450 | AC21: =37.5*12 -> 450 | AD21: =AC21-AB21 -> 0
B22: Cave -2 | C22: 37.5 | E22: 37.5 | G22: 37.5 | I22: 37.5 | K22: 37.5 | M22: 37.5 | O22: 37.5 | Q22: 37.5 | S22: 37.5 | U22: 37.5 | W22: 37.5 | Y22: 37.5 | AB22: =SUM(C22:AA22) -> 450 | AC22: =37.5*12 -> 450 | AD22: =AC22-AB22 -> 0
B24: Levantamento Prazo | AB24: =SUM(C24:AA24) -> 0
B25: Processo 6º Drt. | AB25: =SUM(C25:AA25) -> 0
AB26: =SUM(C26:AA26) -> 0
AB27: =SUM(C27:AA27) -> 0
B30: Total Receitas | C30: =C7+C8+C9+C10+C11+C12+C13+C14+C15+C16+C18+C19+C20+C21+C22+C27+C17 -> 2170 | E30: =E7+E8+E9+E10+E11+E12+E13+E14+E15+E16+E17+E18+E19+E20+E21+E22+E27 -> 1252.5 | G30: =G7+G8+G9+G10+G11+G12+G13+G14+G15+G16+G17+G18+G19+G20+G21+G22+G27 -> 470 | I30: =I7+I8+I9+I10+I11+I12+I13+I14+I15+I16+I17+I18+I19+I20+I21+I22+I27+I25 -> 635 | K30: =K7+K8+K9+K10+K11+K12+K13+K14+K15+K16+K17+K18+K19+K20+K21+K22+K25+K27 -> 527.5 | M30: =M7+M8+M9+M10+M11+M12+M13+M14+M15+M16+M17+M18+M19+M20+M21+M22+M25+M27 -> 605 | O30: =O7+O8+O9+O10+O11+O12+O13+O14+O15+O16+O17+O18+O19+O20+O21+O22+O25+O26+O27 -> 480 | Q30: =Q7+Q8+Q9+Q10+Q11+Q12+Q13+Q14+Q15+Q16+Q17+Q18+Q19+Q20+Q21+Q22+Q24+Q25+Q26+Q27 -> 330 | S30: =S7+S8+S9+S10+S11+S12+S13+S14+S15+S16+S17+S18+S19+S20+S21+S22+S25+S27 -> 555 | U30: =U7+U8+U9+U10+U11+U12+U13+U14+U15+U16+U17+U18+U19+U20+U21+U22+U25+U27 -> 480 | W30: =W7+W8+W9+W10+W11+W12+W13+W14+W15+W16+W17+W18+W19+W20+W21+W22+W25+W27 -> 480 | Y30: =Y7+Y8+Y9+Y10+Y11+Y12+Y13+Y14+Y15+Y16+Y17+Y18+Y19+Y20+Y21+Y22+Y25+Y27 -> 817.5 | AB30: =SUM(C30:AA30) -> 8802.5
B32: Condominio Rua Vieira da Silva, 6 | V32: Ano 2023
A33: DESPESAS
B35: Despesas | C35: Janeiro | E35: Fevereiro | G35: Março | I35: Abril | K35: Maio | M35: Junho | O35: Julho | Q35: Agosto | S35: Setembro | U35: Outubro | W35: Novembro | Y35: Dezembro | AB35: TOTAL
B38: Electricidade | C38: 88.22 | E38: 84.95 | G38: 95.34 | I38: 98.84 | K38: 108.27 | M38: 118.39 | O38: 114.8 | Q38: 88.43 | S38: 111.11 | U38: 109.28 | W38: 109.63 | Y38: 110.73 | AB38: =SUM(C38:AA38) -> 1237.99
B39: Elevadores | C39: 950.8 | E39: 190.16 | I39: 190.16 | M39: 190.16 | O39: 190.16 | Q39: 357.56 | S39: 463.84 | U39: 463.84 | W39: 480 | Y39: 480 | AB39: =SUM(C39:AA39) -> 3956.68
B40: Reparação Extra Elevadores | AB40: =SUM(C40:AA40) -> 0
B41: Manutenção Central Bombagem | I41: 224.48 | AB41: =SUM(C41:AA41) -> 224.48
B42: Limpeza Escadas | C42: 100 | E42: 100 | G42: 100 | I42: 100 | K42: 100 | M42: 100 | O42: 100 | Q42: 100 | S42: 100 | U42: 100 | W42: 100 | Y42: 100 | AB42: =SUM(C42:AA42) -> 1200
B43: Manutenção Extintores | E43: 56 | AB43: =SUM(C43:AA43) -> 56
B44: Despesas Bancárias | C44: 5.2 | E44: 5.2 | G44: 13.2 | I44: 5.2 | K44: 5.2 | M44: 5.2 | O44: 23.4 | Q44: 5.2 | S44: 5.2 | U44: 5.2 | W44: 5.2 | Y44: 5.2 | AB44: =SUM(C44:AA44) -> 88.6
B45: Curva Agua | G45: 400 | AB45: =SUM(C45:AA45) -> 400
B46: Video Poreiro | C46: 2812.11 | E46: 502.3
B47: Manutenção Geral Edificio | AB47: =SUM(C47:AA47) -> 0
B48: Inspecção Elevadores | AB48: =SUM(C48:AA48) -> 0
B49: Depósitos Prazo Poupança | C49: 60 | E49: 60 | G49: 60 | I49: 60 | K49: 60 | M49: 60 | O49: 60 | Q49: 60 | S49: 60 | U49: 60 | W49: 60 | Y49: 60 | AB49: =SUM(C49:AA49) -> 720
B52: Total Despesas | C52: =SUM(C38:C49) -> 4016.33 | E52: =SUM(E38:E49) -> 998.61 | G52: =SUM(G38:G49) -> 668.54 | I52: =SUM(I38:I49) -> 678.68 | K52: =SUM(K38:K49) -> 273.47 | M52: =SUM(M38:M49) -> 473.75 | O52: =SUM(O38:O49) -> 488.36 | Q52: =SUM(Q38:Q49) -> 611.19 | S52: =SUM(S38:S49) -> 740.15 | U52: =SUM(U38:U49) -> 738.32 | W52: =SUM(W38:W49) -> 754.83 | Y52: =SUM(Y38:Y49) -> 755.93 | AB52: =SUM(C52:AA52) -> 11198.16
AB56: Total Liquido
B58: Resultados Liquidos | C58: =C30-C52 -> -1846.33 | E58: =E30-E52 -> 253.89 | G58: =G30-G52 -> -198.54 | I58: =I30-I52 -> -43.68 | K58: =K30-K52 -> 254.03 | M58: =M30-M52 -> 131.25 | O58: =O30-O52 -> -8.36 | Q58: =Q30-Q52 -> -281.19 | S58: =S30-S52 -> -185.15 | U58: =U30-U52 -> -258.32 | W58: =W30-W52 -> -274.83 | Y58: =Y30-Y52 -> 61.57 | AB58: =SUM(C58:AA58) -> -2395.66
B62: Valor Transitado do Ano 2022 | C62: 3496.75 | L62: A Administração
B63: Receitas Ano 2023 | C63: =C30+E30+G30+I30+K30+M30+O30+Q30+S30+U30+W30+Y30 -> 8802.5
C64: =SUM(C62:C63) -> 12299.25
B65: Despesas Ano 2023 - | C65: =C52+E52+G52+I52+K52+M52+O52+Q52+S52+U52+W52+Y52 -> 11198.16
B66: Saldo a transitar para 2024 | C66: =C64-C65 -> 1101.09
B68: Montepio Conta Corrente

Sheet Receitas Despesas 2024
B1: Condominio Rua Vieira da Silva, 6 | I1: Queluz - Monte Abraão | V1: Ano 2024
B2: RECEITAS
B4: Receitas | C4: Janeiro | E4: Fevereiro | G4: Março | I4: Abril | K4: Maio | M4: Junho | O4: Julho | Q4: Agosto | S4: Setembro | U4: Outubro | W4: Novembro | Y4: Dezembro | AB4: TOTAL
B7: 6ºAndar Direito | E7: 37.5 | K7: 37.5 | W7: 558.25 | AB7: =SUM(C7:AA7) -> 633.25 | AC7: =37.5*5+45*7 -> 502.5 | AD7: =AC7-AB7 -> -130.75
B8: 6ºAndar Esquerdo | C8: 37.5 | G8: 75 | I8: 37.5 | K8: 37.5 | M8: 45 | O8: 45 | Q8: 45 | S8: 45 | U8: 45 | W8: 45 | Y8: 45 | AB8: =SUM(C8:AA8) -> 502.5 | AC8: =37.5*5+45*7 -> 502.5 | AD8: =AC8-AB8 -> 0
B9: 5ºAndar Direito | C9: 75 | G9: 112.5 | M9: 45 | O9: 45 | S9: 45 | U9: 45 | W9: 45 | Y9: 45 | AB9: =SUM(C9:AA9) -> 457.5 | AC9: =37.5*5+45*7 -> 502.5 | AD9: =AC9-AB9 -> 45
B10: 5 Andar Esquerdo | C10: 37.5 | E10: 37.5 | G10: 37.5 | I10: 37.5 | K10: 37.5 | M10: 45 | O10: 45 | Q10: 45 | S10: 45 | U10: 45 | W10: 45 | Y10: 45 | AB10: =SUM(C10:AA10) -> 502.5 | AC10: =37.5*5+45*7 -> 502.5 | AD10: =AC10-AB10 -> 0
B11: 4ºAndar Direito | C11: 37.5 | E11: 37.5 | G11: 37.5 | I11: 37.5 | K11: 37.5 | M11: 45 | O11: 45 | Q11: 45 | S11: 45 | U11: 45 | W11: 45 | Y11: 45 | AB11: =SUM(C11:AA11) -> 502.5 | AC11: =37.5*5+45*7 -> 502.5 | AD11: =AC11-AB11 -> 0
B12: 4ºAndar Esquerdo | C12: 37.5 | E12: 37.5 | G12: 37.5 | I12: 37.5 | K12: 37.5 | M12: 45 | O12: 45 | Q12: 45 | S12: 45 | U12: 45 | W12: 45 | Y12: 45 | AB12: =SUM(C12:AA12) -> 502.5 | AC12: =37.5*5+45*7 -> 502.5 | AD12: =AC12-AB12 -> 0
B13: 3ºAndar Direito | C13: 37.5 | E13: 37.5 | G13: 37.5 | I13: 37.5 | K13: 37.5 | M13: 45 | O13: 45 | S13: 45 | U13: 45 | W13: 45 | Y13: 45 | AB13: =SUM(C13:AA13) -> 457.5 | AC13: =37.5*5+45*7 -> 502.5 | AD13: =AC13-AB13 -> 45
B14: 3ºAndar Esquerdo | C14: 75 | E14: 75 | I14: 75 | O14: 90 | Q14: 45 | S14: 45 | W14: 90 | AB14: =SUM(C14:AA14) -> 495 | AC14: =37.5*5+45*7 -> 502.5 | AD14: =AC14-AB14 -> 7.5
B15: 2ºAndar Direito | C15: 37.5 | E15: 37.5 | G15: 37.5 | I15: 37.5 | K15: 37.5 | M15: 45 | O15: 45 | Q15: 45 | S15: 45 | U15: 45 | W15: 45 | Y15: 45 | AB15: =SUM(C15:AA15) -> 502.5 | AC15: =37.5*5+45*7 -> 502.5 | AD15: =AC15-AB15 -> 0
B16: 2ºAndar Esquerdo | C16: 37.5 | E16: 37.5 | G16: 37.5 | I16: 37.5 | K16: 37.5 | M16: 37.5 | U16: 277.5 | AB16: =SUM(C16:AA16) -> 502.5 | AC16: =37.5*5+45*7 -> 502.5 | AD16: =AC16-AB16 -> 0
B17: 1ºAndar Direito | C17: 37.5 | E17: 37.5 | G17: 37.5 | I17: 37.5 | K17: 37.5 | M17: 45 | O17: 45 | Q17: 45 | S17: 45 | U17: 45 | W17: 45 | Y17: 45 | AB17: =SUM(C17:AA17) -> 502.5 | AC17: =37.5*5+45*7 -> 502.5 | AD17: =AC17-AB17 -> 0
B18: 1ºAndar Esquerdo | C18: 37.5 | E18: 37.5 | G18: 37.5 | I18: 37.5 | K18: 37.5 | M18: 90 | Q18: 45 | U18: 45 | AB18: =SUM(C18:AA18) -> 367.5 | AC18: =37.5*5+45*7 -> 502.5 | AD18: =AC18-AB18 -> 135
B19: Res-Chão Direito | C19: 17.5 | E19: 17.5 | G19: 17.5 | I19: 17.5 | K19: 20 | M19: 20 | O19: 20 | Q19: 20 | S19: 20 | U19: 60 | AB19: =SUM(C19:AA19) -> 230 | AC19: =17.5*5+20*7 -> 227.5 | AD19: =AC19-AB19 -> -2.5
B20: Res-Chão Esquerdo | C20: 50 | E20: 50 | G20: 50 | I20: 50 | K20: 50 | M20: 50 | O20: 50 | S20: 50 | U20: 50 | W20: 50 | Y20: 50 | AB20: =SUM(C20:AA20) -> 550 | AC20: =37.5*5+45*7 -> 502.5 | AD20: =AC20-AB20 -> -47.5
B21: Cave -1 (Garagem) | Y21: 450 | AB21: =SUM(C21:AA21) -> 450 | AC21: =37.5*5+45*7 -> 502.5 | AD21: =AC21-AB21 -> 52.5
B22: Cave -2 | C22: 37.5 | E22: 37.5 | G22: 37.5 | I22: 37.5 | K22: 37.5 | M22: 45 | O22: 45 | Q22: 45 | S22: 45 | U22: 45 | W22: 45 | Y22: 45 | AB22: =SUM(C22:AA22) -> 502.5 | AC22: =37.5*5+45*7 -> 502.5 | AD22: =AC22-AB22 -> 0
B24: Levantamento Prazo | AB24: =SUM(C24:AA24) -> 0
B25: Processo 6º Drt. | AB25: =SUM(C25:AA25) -> 0
AB26: =SUM(C26:AA26) -> 0
AB27: =SUM(C27:AA27) -> 0
B30: Total Receitas | C30: =C7+C8+C9+C10+C11+C12+C13+C14+C15+C16+C18+C19+C20+C21+C22+C27+C17 -> 592.5 | E30: =E7+E8+E9+E10+E11+E12+E13+E14+E15+E16+E17+E18+E19+E20+E21+E22+E27 -> 517.5 | G30: =G7+G8+G9+G10+G11+G12+G13+G14+G15+G16+G17+G18+G19+G20+G21+G22+G27 -> 592.5 | I30: =I7+I8+I9+I10+I11+I12+I13+I14+I15+I16+I17+I18+I19+I20+I21+I22+I27+I25 -> 517.5 | K30: =K7+K8+K9+K10+K11+K12+K13+K14+K15+K16+K17+K18+K19+K20+K21+K22+K25+K27 -> 482.5 | M30: =M7+M8+M9+M10+M11+M12+M13+M14+M15+M16+M17+M18+M19+M20+M21+M22+M25+M27 -> 602.5 | O30: =O7+O8+O9+O10+O11+O12+O13+O14+O15+O16+O17+O18+O19+O20+O21+O22+O25+O26+O27 -> 565 | Q30: =Q7+Q8+Q9+Q10+Q11+Q12+Q13+Q14+Q15+Q16+Q17+Q18+Q19+Q20+Q21+Q22+Q24+Q25+Q26+Q27 -> 425 | S30: =S7+S8+S9+S10+S11+S12+S13+S14+S15+S16+S17+S18+S19+S20+S21+S22+S25+S27 -> 520 | U30: =U7+U8+U9+U10+U11+U12+U13+U14+U15+U16+U17+U18+U19+U20+U21+U22+U25+U27 -> 837.5 | W30: =W7+W8+W9+W10+W11+W12+W13+W14+W15+W16+W17+W18+W19+W20+W21+W22+W25+W27 -> 1103.25 | Y30: =Y7+Y8+Y9+Y10+Y11+Y12+Y13+Y14+Y15+Y16+Y17+Y18+Y19+Y20+Y21+Y22+Y25+Y27 -> 905 | AB30: =SUM(C30:AA30) -> 7660.75
B32: Condominio Rua Vieira da Silva, 6 | V32: Ano 2024
A33: DESPESAS
B35: Despesas | C35: Janeiro | E35: Fevereiro | G35: Março | I35: Abril | K35: Maio | M35: Junho | O35: Julho | Q35: Agosto | S35: Setembro | U35: Outubro | W35: Novembro | Y35: Dezembro | AB35: TOTAL
B38: Electricidade | C38: 109.08 | E38: 114.08 | G38: 140.07 | I38: 128.33 | K38: 137.08 | M38: 150.24 | O38: 149.81 | Q38: 148.06 | S38: 144.77 | U38: 146.47 | AB38: =SUM(C38:AA38) -> 1367.99
B39: Elevadores | C39: 480 | E39: 480 | G39: 206.32 | I39: 206.32 | K39: 206.32 | M39: 206.32 | O39: 206.32 | Q39: 206.32 | S39: 206.32 | U39: 218.92 | W39: 218.92 | Y39: 218.92 | AB39: =SUM(C39:AA39) -> 3061
B40: Reparação Extra Elevadores | E40: 51.82 | U40: 514.16 | AB40: =SUM(C40:AA40) -> 565.98
B41: Manutenção Central Bombagem | Y41: 198.65 | AB41: =SUM(C41:AA41) -> 198.65
B42: Limpeza Escadas | C42: 100 | E42: 107 | G42: 107 | I42: 107 | K42: 107 | M42: 107 | O42: 107 | Q42: 107 | S42: 107 | U42: 107 | W42: 107 | Y42: 107 | AB42: =SUM(C42:AA42) -> 1277
B43: Manutenção Extintores | E43: 56 | AB43: =SUM(C43:AA43) -> 56
B44: Despesas Bancárias | C44: 9.36 | E44: 8.32 | G44: 8.32 | I44: 8.32 | K44: 8.32 | M44: 8.32 | O44: 8.32 | Q44: 8.32 | S44: 8.32 | U44: 8.32 | W44: 9.28 | Y44: 8.32 | AB44: =SUM(C44:AA44) -> 101.84
B45: Curva Agua | AB45: =SUM(C45:AA45) -> 0
B46: Eletrecista | Y46: 140 | AB46: =SUM(C46:AA46) -> 140
B47: Manutenção Geral Edificio | AB47: =SUM(C47:AA47) -> 0
B48: Inspecção Elevadores | E48: 280 | AB48: =SUM(C48:AA48) -> 280
B49: Depósitos Prazo Poupança | C49: 60 | E49: 60 | G49: 60 | I49: 60 | K49: 60 | M49: 60 | O49: 60 | Q49: 60 | S49: 60 | U49: 60 | W49: 60 | Y49: 60 | AB49: =SUM(C49:AA49) -> 720
B52: Total Despesas | C52: =SUM(C38:C49) -> 758.44 | E52: =SUM(E38:E49) -> 1157.22 | G52: =SUM(G38:G49) -> 521.71 | I52: =SUM(I38:I49) -> 509.97 | K52: =SUM(K38:K49) -> 518.72 | M52: =SUM(M38:M49) -> 531.88 | O52: =SUM(O38:O49) -> 531.45 | Q52: =SUM(Q38:Q49) -> 529.7 | S52: =SUM(S38:S49) -> 526.41 | U52: =SUM(U38:U49) -> 1054.87 | W52: =SUM(W38:W49) -> 395.2 | Y52: =SUM(Y38:Y49) -> 732.89 | AB52: =SUM(C52:AA52) -> 7768.46
AB56: Total Liquido
B58: Resultados Liquidos | C58: =C30-C52 -> -165.94 | E58: =E30-E52 -> -639.72 | G58: =G30-G52 -> 70.79 | I58: =I30-I52 -> 7.53 | K58: =K30-K52 -> -36.22 | M58: =M30-M52 -> 70.62 | O58: =O30-O52 -> 33.55 | Q58: =Q30-Q52 -> -104.7 | S58: =S30-S52 -> -6.41 | U58: =U30-U52 -> -217.37 | W58: =W30-W52 -> 708.05 | Y58: =Y30-Y52 -> 172.11 | AB58: =SUM(C58:AA58) -> -107.71
B62: Valor Transitado do Ano 2023 | C62: 1101.09 | L62: A Administração
B63: Receitas Ano 2024 | C63: =C30+E30+G30+I30+K30+M30+O30+Q30+S30+U30+W30+Y30 -> 7660.75
C64: =SUM(C62:C63) -> 8761.84
B65: Despesas Ano 2024 | C65: =C52+E52+G52+I52+K52+M52+O52+Q52+S52+U52+W52+Y52 -> 7768.46
B66: Saldo a transitar para 2025 | C66: =C64-C65 -> 993.38
B68: Montepio Conta Corrente

Sheet Receitas Despesas 2025
B1: Condominio Rua Vieira da Silva, 6 | I1: Queluz - Monte Abraão | V1: Ano 2024
B2: RECEITAS
B4: Receitas | C4: Janeiro | E4: Fevereiro | G4: Março | I4: Abril | K4: Maio | M4: Junho | O4: Julho | Q4: Agosto | S4: Setembro | U4: Outubro | W4: Novembro | Y4: Dezembro | AB4: TOTAL | AC4: Valor Esperado | AD4: Divida
B7: 6ºAndar Direito | I7: 45 | M7: 37.5 | O7: 37.5 | W7: 37.5 | Y7: 37.5 | AB7: =SUM(C7:AA7) -> 195 | AC7: =45*12 -> 540 | AD7: =AC7-AB7 -> 345
B8: 6ºAndar Esquerdo | C8: 45 | E8: 45 | G8: 45 | I8: 45 | K8: 45 | M8: 45 | O8: 45 | S8: 90 | U8: 45 | W8: 45 | Y8: 45 | AB8: =SUM(C8:AA8) -> 540 | AC8: =45*12 -> 540 | AD8: =AC8-AB8 -> 0
B9: 5ºAndar Direito | C9: 45 | E9: 45 | G9: 45 | I9: 45 | K9: 45 | M9: 45 | O9: 45 | Q9: 45 | S9: 45 | U9: 45 | W9: 45 | Y9: 45 | AB9: =SUM(C9:AA9) -> 540 | AC9: =45*12 -> 540 | AD9: =AC9-AB9 -> 0
B10: 5 Andar Esquerdo | C10: 45 | E10: 45 | G10: 45 | I10: 45 | K10: 45 | M10: 45 | O10: 45 | Q10: 45 | S10: 45 | U10: 45 | W10: 45 | Y10: 45 | AB10: =SUM(C10:AA10) -> 540 | AC10: =45*12 -> 540 | AD10: =AC10-AB10 -> 0
B11: 4ºAndar Direito | C11: 45 | E11: 45 | G11: 45 | I11: 45 | K11: 45 | M11: 45 | O11: 45 | Q11: 45 | S11: 45 | U11: 45 | W11: 45 | Y11: 45 | AB11: =SUM(C11:AA11) -> 540 | AC11: =45*12 -> 540 | AD11: =AC11-AB11 -> 0
B12: 4ºAndar Esquerdo | C12: 45 | E12: 45 | G12: 45 | K12: 45 | M12: 45 | O12: 45 | Q12: 45 | S12: 45 | U12: 45 | W12: 45 | Y12: 45 | AB12: =SUM(C12:AA12) -> 495 | AC12: =45*12 -> 540 | AD12: =AC12-AB12 -> 45
B13: 3ºAndar Direito | C13: 90 | E13: 45 | G13: 45 | I13: 45 | K13: 45 | M13: 45 | O13: 45 | Q13: 45 | U13: 45 | W13: 45 | Y13: 45 | AB13: =SUM(C13:AA13) -> 540 | AC13: =45*12 -> 540 | AD13: =AC13-AB13 -> 0
B14: 3ºAndar Esquerdo | E14: 80 | G14: 40 | M14: 120 | Q14: 40 | U14: 80 | W14: 80 | AB14: =SUM(C14:AA14) -> 440 | AC14: =45*12 -> 540 | AD14: =AC14-AB14 -> 100
B15: 2ºAndar Direito | C15: 45 | E15: 45 | G15: 45 | I15: 45 | K15: 45 | M15: 45 | O15: 45 | Q15: 45 | S15: 45 | U15: 45 | W15: 45 | Y15: 45 | AB15: =SUM(C15:AA15) -> 540 | AC15: =45*12 -> 540 | AD15: =AC15-AB15 -> 0
B16: 2ºAndar Esquerdo | C16: 90 | I16: 180 | AB16: =SUM(C16:AA16) -> 270 | AC16: =45*12 -> 540 | AD16: =AC16-AB16 -> 270
B17: 1ºAndar Direito | C17: 45 | E17: 45 | G17: 45 | I17: 45 | K17: 45 | M17: 45 | O17: 45 | Q17: 45 | S17: 45 | U17: 45 | W17: 45 | Y17: 45 | AB17: =SUM(C17:AA17) -> 540 | AC17: =45*12 -> 540 | AD17: =AC17-AB17 -> 0
B18: 1ºAndar Esquerdo | C18: 45 | E18: 45 | G18: 45 | I18: 45 | K18: 45 | M18: 45 | O18: 45 | Q18: 45 | S18: 45 | U18: 45 | W18: 45 | Y18: 45 | AB18: =SUM(C18:AA18) -> 540 | AC18: =45*12 -> 540 | AD18: =AC18-AB18 -> 0
B19: Res-Chão Direito | C19: 40 | E19: 20 | G19: 20 | I19: 20 | K19: 20 | M19: 20 | O19: 20 | Q19: 20 | S19: 20 | U19: 20 | W19: 20 | Y19: 20 | AB19: =SUM(C19:AA19) -> 260 | AC19: =20*12 -> 240 | AD19: =AC19-AB19 -> -20
B20: Res-Chão Esquerdo | C20: 50 | E20: 50 | G20: 50 | I20: 50 | K20: 50 | M20: 50 | O20: 50 | S20: 50 | U20: 50 | W20: 50 | Y20: 50 | AB20: =SUM(C20:AA20) -> 550 | AC20: =45*12 -> 540 | AD20: =AC20-AB20 -> -10
B21: Cave -1 (Garagem) | Y21: 450 | AB21: =SUM(C21:AA21) -> 450 | AC21: =45*12 -> 540 | AD21: =AC21-AB21 -> 90
B22: Cave -2 | C22: 45 | E22: 45 | G22: 45 | I22: 45 | K22: 45 | M22: 45 | O22: 45 | Q22: 45 | S22: 45 | U22: 45 | W22: 45 | Y22: 45 | AB22: =SUM(C22:AA22) -> 540 | AC22: =45*12 -> 540 | AD22: =AC22-AB22 -> 0
B24: Levantamento Prazo | AB24: =SUM(C24:AA24) -> 0
B25: Processo 6º Drt. | AB25: =SUM(C25:AA25) -> 0
AB26: =SUM(C26:AA26) -> 0
AB27: =SUM(C27:AA27) -> 0
B30: Total Receitas | C30: =C7+C8+C9+C10+C11+C12+C13+C14+C15+C16+C18+C19+C20+C21+C22+C27+C17 -> 675 | E30: =E7+E8+E9+E10+E11+E12+E13+E14+E15+E16+E17+E18+E19+E20+E21+E22+E27 -> 600 | G30: =G7+G8+G9+G10+G11+G12+G13+G14+G15+G16+G17+G18+G19+G20+G21+G22+G27 -> 560 | I30: =I7+I8+I9+I10+I11+I12+I13+I14+I15+I16+I17+I18+I19+I20+I21+I22+I27+I25 -> 700 | K30: =K7+K8+K9+K10+K11+K12+K13+K14+K15+K16+K17+K18+K19+K20+K21+K22+K25+K27 -> 520 | M30: =M7+M8+M9+M10+M11+M12+M13+M14+M15+M16+M17+M18+M19+M20+M21+M22+M25+M27 -> 677.5 | O30: =O7+O8+O9+O10+O11+O12+O13+O14+O15+O16+O17+O18+O19+O20+O21+O22+O25+O26+O27 -> 557.5 | Q30: =Q7+Q8+Q9+Q10+Q11+Q12+Q13+Q14+Q15+Q16+Q17+Q18+Q19+Q20+Q21+Q22+Q24+Q25+Q26+Q27 -> 465 | S30: =S7+S8+S9+S10+S11+S12+S13+S14+S15+S16+S17+S18+S19+S20+S21+S22+S25+S27 -> 520 | U30: =U7+U8+U9+U10+U11+U12+U13+U14+U15+U16+U17+U18+U19+U20+U21+U22+U25+U27 -> 600 | W30: =W7+W8+W9+W10+W11+W12+W13+W14+W15+W16+W17+W18+W19+W20+W21+W22+W25+W27 -> 637.5 | Y30: =Y7+Y8+Y9+Y10+Y11+Y12+Y13+Y14+Y15+Y16+Y17+Y18+Y19+Y20+Y21+Y22+Y25+Y27 -> 1007.5 | AB30: =SUM(C30:AA30) -> 7520
B32: Condominio Rua Vieira da Silva, 6 | V32: Ano 2024
A33: DESPESAS
B35: Despesas | C35: Janeiro | E35: Fevereiro | G35: Março | I35: Abril | K35: Maio | M35: Junho | O35: Julho | Q35: Agosto | S35: Setembro | U35: Outubro | W35: Novembro | Y35: Dezembro | AB35: TOTAL
B38: Electricidade | C38: 109.08 | E38: 114.08 | G38: 140.07 | I38: 128.33 | K38: 137.08 | M38: 150.24 | O38: 149.81 | Q38: 148.06 | S38: 144.77 | U38: 146.47 | AB38: =SUM(C38:AA38) -> 1367.99
B39: Elevadores | C39: 480 | E39: 480 | G39: 206.32 | I39: 206.32 | K39: 206.32 | M39: 206.32 | O39: 206.32 | Q39: 206.32 | S39: 206.32 | U39: 218.92 | W39: 218.92 | Y39: 218.92 | AB39: =SUM(C39:AA39) -> 3061
B40: Reparação Extra Elevadores | E40: 51.82 | U40: 514.16 | AB40: =SUM(C40:AA40) -> 565.98
B41: Manutenção Central Bombagem | Y41: 198.65 | AB41: =SUM(C41:AA41) -> 198.65
B42: Limpeza Escadas | C42: 100 | E42: 107 | G42: 107 | I42: 107 | K42: 107 | M42: 107 | O42: 107 | Q42: 107 | S42: 107 | U42: 107 | W42: 107 | Y42: 107 | AB42: =SUM(C42:AA42) -> 1277
B43: Manutenção Extintores | E43: 56 | AB43: =SUM(C43:AA43) -> 56
B44: Despesas Bancárias | C44: 9.36 | E44: 8.32 | G44: 8.32 | I44: 8.32 | K44: 8.32 | M44: 8.32 | O44: 8.32 | Q44: 8.32 | S44: 8.32 | U44: 8.32 | W44: 9.28 | Y44: 8.32 | AB44: =SUM(C44:AA44) -> 101.84
B45: Curva Agua | AB45: =SUM(C45:AA45) -> 0
B46: Eletrecista | Y46: 140 | AB46: =SUM(C46:AA46) -> 140
B47: Manutenção Geral Edificio | AB47: =SUM(C47:AA47) -> 0
B48: Inspecção Elevadores | E48: 280 | AB48: =SUM(C48:AA48) -> 280
B49: Depósitos Prazo Poupança | C49: 60 | E49: 60 | G49: 60 | I49: 60 | K49: 60 | M49: 60 | O49: 60 | Q49: 60 | S49: 60 | U49: 60 | W49: 60 | Y49: 60 | AB49: =SUM(C49:AA49) -> 720
B52: Total Despesas | C52: =SUM(C38:C49) -> 758.44 | E52: =SUM(E38:E49) -> 1157.22 | G52: =SUM(G38:G49) -> 521.71 | I52: =SUM(I38:I49) -> 509.97 | K52: =SUM(K38:K49) -> 518.72 | M52: =SUM(M38:M49) -> 531.88 | O52: =SUM(O38:O49) -> 531.45 | Q52: =SUM(Q38:Q49) -> 529.7 | S52: =SUM(S38:S49) -> 526.41 | U52: =SUM(U38:U49) -> 1054.87 | W52: =SUM(W38:W49) -> 395.2 | Y52: =SUM(Y38:Y49) -> 732.89 | AB52: =SUM(C52:AA52) -> 7768.46
AB56: Total Liquido
B58: Resultados Liquidos | C58: =C30-C52 -> -83.44 | E58: =E30-E52 -> -557.22 | G58: =G30-G52 -> 38.29 | I58: =I30-I52 -> 190.03 | K58: =K30-K52 -> 1.28 | M58: =M30-M52 -> 145.62 | O58: =O30-O52 -> 26.05 | Q58: =Q30-Q52 -> -64.7 | S58: =S30-S52 -> -6.41 | U58: =U30-U52 -> -454.87 | W58: =W30-W52 -> 242.3 | Y58: =Y30-Y52 -> 274.61 | AB58: =SUM(C58:AA58) -> -248.46
B62: Valor Transitado do Ano 2023 | C62: 1101.09 | L62: A Administração
B63: Receitas Ano 2024 | C63: =C30+E30+G30+I30+K30+M30+O30+Q30+S30+U30+W30+Y30 -> 7520
C64: =SUM(C62:C63) -> 8621.09
B65: Despesas Ano 2024 | C65: =C52+E52+G52+I52+K52+M52+O52+Q52+S52+U52+W52+Y52 -> 7768.46
B66: Saldo a transitar para 2025 | C66: =C64-C65 -> 852.63
B68: Montepio Conta Corrente

Sheet Folha1
A3: Andar | B3: 2020 | C3: 2022 | D3: 2024
A4: Valor em divida | B4: 2011 | C4: 2012 | D4: 2013 | E4: 2014 | F4: 2015 | G4: 2016 | H4: 2017 | I4: 2018 | J4: 2019 | K4: 2020 | L4: 2021 | M4: 2022 | N4: 2023 | O4: 2024 | P4: 2025 | Q4: Total
A5: 6ºAndar Direito | B5: =_xlfn.XLOOKUP(A5,'Receita Despesas 2011 '!C:C,'Receita Despesas 2011 '!AE:AE) -> -417.5 | C5: =_xlfn.XLOOKUP(A5,'Receitas Despesas 2012'!C:C,'Receitas Despesas 2012'!AE:AE) -> -227.03 | D5: =_xlfn.XLOOKUP(A5,'Receitas Despesas 2013'!B:B,'Receitas Despesas 2013'!AD:AD) -> -450 | E5: =_xlfn.XLOOKUP(A5,'Receitas Despesas 2014'!C:C,'Receitas Despesas 2014'!AE:AE) -> -385 | F5: =_xlfn.XLOOKUP(A5,'Receitas Despesas 2014'!C:C,'Receitas Despesas 2015'!AE:AE) -> -295.69 | G5: =_xlfn.XLOOKUP(A5,'Receitas Despesas 2015'!C:C,'Receitas Despesas 2016'!AE:AE) -> 0 | H5: =_xlfn.XLOOKUP(A5,'Receita Despesas 2017'!B:B,'Receita Despesas 2017'!AD:AD) -> 125 | I5: =_xlfn.XLOOKUP(A5,'Receita Despesas 2018'!C:C,'Receita Despesas 2018'!AF:AF) -> 12.5 | J5: =_xlfn.XLOOKUP(A5,'Receita Despesas 2019'!C:C,'Receita Despesas 2019'!AE:AE) -> 417.5 | K5: =_xlfn.XLOOKUP(A5,'Receita Despesa 2020'!B:B,'Receita Despesa 2020'!AD:AD) -> -90 | L5: =_xlfn.XLOOKUP(A5,'Receita Despesas 2021'!B:B,'Receita Despesas 2021'!AD:AD) -> -167.72 | M5: =_xlfn.XLOOKUP(A5,'Receita Despesas 2022'!B:B,'Receita Despesas 2022'!AD:AD) -> 425 | N5: =_xlfn.XLOOKUP(A5,'Receitas Despesas 2023'!B:B,'Receitas Despesas 2023'!AD:AD) -> 337.5 | O5: =_xlfn.XLOOKUP(Folha1!A5,'Receitas Despesas 2024'!B:B,'Receitas Despesas 2024'!AD:AD) -> -130.75 | Q5: =SUM(B5:P5) -> -846.19
A6: 6ºAndar Esquerdo | B6: =_xlfn.XLOOKUP(A6,'Receita Despesas 2011 '!C:C,'Receita Despesas 2011 '!AE:AE) -> -160 | C6: =_xlfn.XLOOKUP(A6,'Receitas Despesas 2012'!C:C,'Receitas Despesas 2012'!AE:AE) -> 0 | D6: =_xlfn.XLOOKUP(A6,'Receitas Despesas 2013'!B:B,'Receitas Despesas 2013'!AD:AD) -> 0 | E6: =_xlfn.XLOOKUP(A6,'Receitas Despesas 2014'!C:C,'Receitas Despesas 2014'!AE:AE) -> 0 | F6: =_xlfn.XLOOKUP(A6,'Receitas Despesas 2014'!C:C,'Receitas Despesas 2015'!AE:AE) -> 0 | G6: =_xlfn.XLOOKUP(A6,'Receitas Despesas 2015'!C:C,'Receitas Despesas 2016'!AE:AE) -> 262.5 | H6: =_xlfn.XLOOKUP(A6,'Receita Despesas 2017'!B:B,'Receita Despesas 2017'!AD:AD) -> 0 | I6: =_xlfn.XLOOKUP(A6,'Receita Despesas 2018'!C:C,'Receita Despesas 2018'!AF:AF) -> 112.5 | J6: =_xlfn.XLOOKUP(A6,'Receita Despesas 2019'!C:C,'Receita Despesas 2019'!AE:AE) -> -75 | K6: =_xlfn.XLOOKUP(A6,'Receita Despesa 2020'!B:B,'Receita Despesa 2020'!AD:AD) -> 35.45 | L6: =_xlfn.XLOOKUP(A6,'Receita Despesas 2021'!B:B,'Receita Despesas 2021'!AD:AD) -> 39.5 | M6: =_xlfn.XLOOKUP(A6,'Receita Despesas 2022'!B:B,'Receita Despesas 2022'!AD:AD) -> 200 | N6: =_xlfn.XLOOKUP(A6,'Receitas Despesas 2023'!B:B,'Receitas Despesas 2023'!AD:AD) -> -237.5 | O6: =_xlfn.XLOOKUP(Folha1!A6,'Receitas Despesas 2024'!B:B,'Receitas Despesas 2024'!AD:AD) -> 0 | Q6: =SUM(B6:P6) -> 177.45
A7: 5ºAndar Direito | B7: =_xlfn.XLOOKUP(A7,'Receita Despesas 2011 '!C:C,'Receita Despesas 2011 '!AE:AE) -> 0 | C7: =_xlfn.XLOOKUP(A7,'Receitas Despesas 2012'!C:C,'Receitas Despesas 2012'!AE:AE) -> 0 | D7: =_xlfn.XLOOKUP(A7,'Receitas Despesas 2013'!B:B,'Receitas Despesas 2013'!AD:AD) -> 0 | E7: =_xlfn.XLOOKUP(A7,'Receitas Despesas 2014'!C:C,'Receitas Despesas 2014'!AE:AE) -> -37.5 | F7: =_xlfn.XLOOKUP(A7,'Receitas Despesas 2014'!C:C,'Receitas Despesas 2015'!AE:AE) -> -187.5 | G7: =_xlfn.XLOOKUP(A7,'Receitas Despesas 2015'!C:C,'Receitas Despesas 2016'!AE:AE) -> 0 | H7: =_xlfn.XLOOKUP(A7,'Receita Despesas 2017'!B:B,'Receita Despesas 2017'!AD:AD) -> 225 | I7: =_xlfn.XLOOKUP(A7,'Receita Despesas 2018'!C:C,'Receita Despesas 2018'!AF:AF) -> 225 | J7: =_xlfn.XLOOKUP(A7,'Receita Despesas 2019'!C:C,'Receita Despesas 2019'!AE:AE) -> 187.5 | K7: =_xlfn.XLOOKUP(A7,'Receita Despesa 2020'!B:B,'Receita Despesa 2020'!AD:AD) -> 262.5 | L7: =_xlfn.XLOOKUP(A7,'Receita Despesas 2021'!B:B,'Receita Despesas 2021'!AD:AD) -> 225 | M7: =_xlfn.XLOOKUP(A7,'Receita Despesas 2022'!B:B,'Receita Despesas 2022'!AD:AD) -> 225 | N7: =_xlfn.XLOOKUP(A7,'Receitas Despesas 2023'!B:B,'Receitas Despesas 2023'!AD:AD) -> 0 | O7: =_xlfn.XLOOKUP(Folha1!A7,'Receitas Despesas 2024'!B:B,'Receitas Despesas 2024'!AD:AD) -> 45 | Q7: =SUM(B7:P7) -> 1170
A8: 5 Andar Esquerdo | B8: =_xlfn.XLOOKUP(A8,'Receita Despesas 2011 '!C:C,'Receita Despesas 2011 '!AE:AE) -> 0 | C8: =_xlfn.XLOOKUP(A8,'Receitas Despesas 2012'!C:C,'Receitas Despesas 2012'!AE:AE) -> 0 | D8: =_xlfn.XLOOKUP(A8,'Receitas Despesas 2013'!B:B,'Receitas Despesas 2013'!AD:AD) -> 0 | E8: =_xlfn.XLOOKUP(A8,'Receitas Despesas 2014'!C:C,'Receitas Despesas 2014'!AE:AE) -> 0 | F8: =_xlfn.XLOOKUP(A8,'Receitas Despesas 2014'!C:C,'Receitas Despesas 2015'!AE:AE) -> 0 | G8: =_xlfn.XLOOKUP(A8,'Receitas Despesas 2015'!C:C,'Receitas Despesas 2016'!AE:AE) -> 225 | H8: =_xlfn.XLOOKUP(A8,'Receita Despesas 2017'!B:B,'Receita Despesas 2017'!AD:AD) -> 37.5 | I8: =_xlfn.XLOOKUP(A8,'Receita Despesas 2018'!C:C,'Receita Despesas 2018'!AF:AF) -> 150 | J8: =_xlfn.XLOOKUP(A8,'Receita Despesas 2019'!C:C,'Receita Despesas 2019'!AE:AE) -> 0 | K8: =_xlfn.XLOOKUP(A8,'Receita Despesa 2020'!B:B,'Receita Despesa 2020'!AD:AD) -> 0 | L8: =_xlfn.XLOOKUP(A8,'Receita Despesas 2021'!B:B,'Receita Despesas 2021'!AD:AD) -> 0 | M8: =_xlfn.XLOOKUP(A8,'Receita Despesas 2022'!B:B,'Receita Despesas 2022'!AD:AD) -> 200 | N8: =_xlfn.XLOOKUP(A8,'Receitas Despesas 2023'!B:B,'Receitas Despesas 2023'!AD:AD) -> -200 | O8: =_xlfn.XLOOKUP(Folha1!A8,'Receitas Despesas 2024'!B:B,'Receitas Despesas 2024'!AD:AD) -> 0 | Q8: =SUM(B8:P8) -> 412.5
A9: 4ºAndar Direito | B9: =_xlfn.XLOOKUP(A9,'Receita Despesas 2011 '!C:C,'Receita Despesas 2011 '!AE:AE) -> 0 | C9: =_xlfn.XLOOKUP(A9,'Receitas Despesas 2012'!C:C,'Receitas Despesas 2012'!AE:AE) -> 0 | D9: =_xlfn.XLOOKUP(A9,'Receitas Despesas 2013'!B:B,'Receitas Despesas 2013'!AD:AD) -> 0 | E9: =_xlfn.XLOOKUP(A9,'Receitas Despesas 2014'!C:C,'Receitas Despesas 2014'!AE:AE) -> 0 | F9: =_xlfn.XLOOKUP(A9,'Receitas Despesas 2014'!C:C,'Receitas Despesas 2015'!AE:AE) -> 0 | G9: =_xlfn.XLOOKUP(A9,'Receitas Despesas 2015'!C:C,'Receitas Despesas 2016'!AE:AE) -> 0 | H9: =_xlfn.XLOOKUP(A9,'Receita Despesas 2017'!B:B,'Receita Despesas 2017'!AD:AD) -> 0 | I9: =_xlfn.XLOOKUP(A9,'Receita Despesas 2018'!C:C,'Receita Despesas 2018'!AF:AF) -> 0 | J9: =_xlfn.XLOOKUP(A9,'Receita Despesas 2019'!C:C,'Receita Despesas 2019'!AE:AE) -> 0 | K9: =_xlfn.XLOOKUP(A9,'Receita Despesa 2020'!B:B,'Receita Despesa 2020'!AD:AD) -> 0 | L9: =_xlfn.XLOOKUP(A9,'Receita Despesas 2021'!B:B,'Receita Despesas 2021'!AD:AD) -> 0 | M9: =_xlfn.XLOOKUP(A9,'Receita Despesas 2022'!B:B,'Receita Despesas 2022'!AD:AD) -> 225 | N9: =_xlfn.XLOOKUP(A9,'Receitas Despesas 2023'!B:B,'Receitas Despesas 2023'!AD:AD) -> -200 | O9: =_xlfn.XLOOKUP(Folha1!A9,'Receitas Despesas 2024'!B:B,'Receitas Despesas 2024'!AD:AD) -> 0 | Q9: =SUM(B9:P9) -> 25
A10: 4ºAndar Esquerdo | B10: =_xlfn.XLOOKUP(A10,'Receita Despesas 2011 '!C:C,'Receita Despesas 2011 '!AE:AE) -> -225 | C10: =_xlfn.XLOOKUP(A10,'Receitas Despesas 2012'!C:C,'Receitas Despesas 2012'!AE:AE) -> 0 | D10: =_xlfn.XLOOKUP(A10,'Receitas Despesas 2013'!B:B,'Receitas Despesas 2013'!AD:AD) -> 0 | E10: =_xlfn.XLOOKUP(A10,'Receitas Despesas 2014'!C:C,'Receitas Despesas 2014'!AE:AE) -> 0 | F10: =_xlfn.XLOOKUP(A10,'Receitas Despesas 2014'!C:C,'Receitas Despesas 2015'!AE:AE) -> 0 | G10: =_xlfn.XLOOKUP(A10,'Receitas Despesas 2015'!C:C,'Receitas Despesas 2016'!AE:AE) -> 0 | H10: =_xlfn.XLOOKUP(A10,'Receita Despesas 2017'!B:B,'Receita Despesas 2017'!AD:AD) -> 37.5 | I10: =_xlfn.XLOOKUP(A10,'Receita Despesas 2018'!C:C,'Receita Despesas 2018'!AF:AF) -> -37.5 | J10: =_xlfn.XLOOKUP(A10,'Receita Despesas 2019'!C:C,'Receita Despesas 2019'!AE:AE) -> 0 | K10: =_xlfn.XLOOKUP(A10,'Receita Despesa 2020'!B:B,'Receita Despesa 2020'!AD:AD) -> 0 | L10: =_xlfn.XLOOKUP(A10,'Receita Despesas 2021'!B:B,'Receita Despesas 2021'!AD:AD) -> 0 | M10: =_xlfn.XLOOKUP(A10,'Receita Despesas 2022'!B:B,'Receita Despesas 2022'!AD:AD) -> 0 | N10: =_xlfn.XLOOKUP(A10,'Receitas Despesas 2023'!B:B,'Receitas Despesas 2023'!AD:AD) -> 0 | O10: =_xlfn.XLOOKUP(Folha1!A10,'Receitas Despesas 2024'!B:B,'Receitas Despesas 2024'!AD:AD) -> 0 | Q10: =SUM(B10:P10) -> -225
A11: 3ºAndar Direito | B11: =_xlfn.XLOOKUP(A11,'Receita Despesas 2011 '!C:C,'Receita Despesas 2011 '!AE:AE) -> -187.5 | C11: =_xlfn.XLOOKUP(A11,'Receitas Despesas 2012'!C:C,'Receitas Despesas 2012'!AE:AE) -> 0 | D11: =_xlfn.XLOOKUP(A11,'Receitas Despesas 2013'!B:B,'Receitas Despesas 2013'!AD:AD) -> 37.5 | E11: =_xlfn.XLOOKUP(A11,'Receitas Despesas 2014'!C:C,'Receitas Despesas 2014'!AE:AE) -> 0 | F11: =_xlfn.XLOOKUP(A11,'Receitas Despesas 2014'!C:C,'Receitas Despesas 2015'!AE:AE) -> -37.5 | G11: =_xlfn.XLOOKUP(A11,'Receitas Despesas 2015'!C:C,'Receitas Despesas 2016'!AE:AE) -> 0 | H11: =_xlfn.XLOOKUP(A11,'Receita Despesas 2017'!B:B,'Receita Despesas 2017'!AD:AD) -> 32.5 | I11: =_xlfn.XLOOKUP(A11,'Receita Despesas 2018'!C:C,'Receita Despesas 2018'!AF:AF) -> -22.5 | J11: =_xlfn.XLOOKUP(A11,'Receita Despesas 2019'!C:C,'Receita Despesas 2019'!AE:AE) -> -10 | K11: =_xlfn.XLOOKUP(A11,'Receita Despesa 2020'!B:B,'Receita Despesa 2020'!AD:AD) -> 0 | L11: =_xlfn.XLOOKUP(A11,'Receita Despesas 2021'!B:B,'Receita Despesas 2021'!AD:AD) -> 0 | M11: =_xlfn.XLOOKUP(A11,'Receita Despesas 2022'!B:B,'Receita Despesas 2022'!AD:AD) -> 162.5 | N11: =_xlfn.XLOOKUP(A11,'Receitas Despesas 2023'!B:B,'Receitas Despesas 2023'!AD:AD) -> -150 | O11: =_xlfn.XLOOKUP(Folha1!A11,'Receitas Despesas 2024'!B:B,'Receitas Despesas 2024'!AD:AD) -> 45 | Q11: =SUM(B11:P11) -> -130
A12: 3ºAndar Esquerdo | B12: =_xlfn.XLOOKUP(A12,'Receita Despesas 2011 '!C:C,'Receita Despesas 2011 '!AE:AE) -> 0 | C12: =_xlfn.XLOOKUP(A12,'Receitas Despesas 2012'!C:C,'Receitas Despesas 2012'!AE:AE) -> 0 | D12: =_xlfn.XLOOKUP(A12,'Receitas Despesas 2013'!B:B,'Receitas Despesas 2013'!AD:AD) -> 0 | E12: =_xlfn.XLOOKUP(A12,'Receitas Despesas 2014'!C:C,'Receitas Despesas 2014'!AE:AE) -> 0 | F12: =_xlfn.XLOOKUP(A12,'Receitas Despesas 2014'!C:C,'Receitas Despesas 2015'!AE:AE) -> -75 | G12: =_xlfn.XLOOKUP(A12,'Receitas Despesas 2015'!C:C,'Receitas Despesas 2016'!AE:AE) -> 0 | H12: =_xlfn.XLOOKUP(A12,'Receita Despesas 2017'!B:B,'Receita Despesas 2017'!AD:AD) -> 150 | I12: =_xlfn.XLOOKUP(A12,'Receita Despesas 2018'!C:C,'Receita Despesas 2018'!AF:AF) -> -65 | J12: =_xlfn.XLOOKUP(A12,'Receita Despesas 2019'!C:C,'Receita Despesas 2019'!AE:AE) -> 37 | K12: =_xlfn.XLOOKUP(A12,'Receita Despesa 2020'!B:B,'Receita Despesa 2020'!AD:AD) -> -190 | L12: =_xlfn.XLOOKUP(A12,'Receita Despesas 2021'!B:B,'Receita Despesas 2021'!AD:AD) -> 97.5 | M12: =_xlfn.XLOOKUP(A12,'Receita Despesas 2022'!B:B,'Receita Despesas 2022'!AD:AD) -> 312.5 | N12: =_xlfn.XLOOKUP(A12,'Receitas Despesas 2023'!B:B,'Receitas Despesas 2023'!AD:AD) -> -400 | O12: =_xlfn.XLOOKUP(Folha1!A12,'Receitas Despesas 2024'!B:B,'Receitas Despesas 2024'!AD:AD) -> 7.5 | Q12: =SUM(B12:P12) -> -125.5
A13: 2ºAndar Direito | B13: =_xlfn.XLOOKUP(A13,'Receita Despesas 2011 '!C:C,'Receita Despesas 2011 '!AE:AE) -> -225 | C13: =_xlfn.XLOOKUP(A13,'Receitas Despesas 2012'!C:C,'Receitas Despesas 2012'!AE:AE) -> 0 | D13: =_xlfn.XLOOKUP(A13,'Receitas Despesas 2013'!B:B,'Receitas Despesas 2013'!AD:AD) -> 0 | E13: =_xlfn.XLOOKUP(A13,'Receitas Despesas 2014'!C:C,'Receitas Despesas 2014'!AE:AE) -> 0 | F13: =_xlfn.XLOOKUP(A13,'Receitas Despesas 2014'!C:C,'Receitas Despesas 2015'!AE:AE) -> 0 | G13: =_xlfn.XLOOKUP(A13,'Receitas Despesas 2015'!C:C,'Receitas Despesas 2016'!AE:AE) -> -75 | H13: =_xlfn.XLOOKUP(A13,'Receita Despesas 2017'!B:B,'Receita Despesas 2017'!AD:AD) -> 0 | I13: =_xlfn.XLOOKUP(A13,'Receita Despesas 2018'!C:C,'Receita Despesas 2018'!AF:AF) -> 0 | J13: =_xlfn.XLOOKUP(A13,'Receita Despesas 2019'!C:C,'Receita Despesas 2019'!AE:AE) -> 0 | K13: =_xlfn.XLOOKUP(A13,'Receita Despesa 2020'!B:B,'Receita Despesa 2020'!AD:AD) -> 0 | L13: =_xlfn.XLOOKUP(A13,'Receita Despesas 2021'!B:B,'Receita Despesas 2021'!AD:AD) -> 0 | M13: =_xlfn.XLOOKUP(A13,'Receita Despesas 2022'!B:B,'Receita Despesas 2022'!AD:AD) -> 200 | N13: =_xlfn.XLOOKUP(A13,'Receitas Despesas 2023'!B:B,'Receitas Despesas 2023'!AD:AD) -> -200 | O13: =_xlfn.XLOOKUP(Folha1!A13,'Receitas Despesas 2024'!B:B,'Receitas Despesas 2024'!AD:AD) -> 0 | Q13: =SUM(B13:P13) -> -300
A14: 2ºAndar Esquerdo | B14: =_xlfn.XLOOKUP(A14,'Receita Despesas 2011 '!C:C,'Receita Despesas 2011 '!AE:AE) -> -385 | C14: =_xlfn.XLOOKUP(A14,'Receitas Despesas 2012'!C:C,'Receitas Despesas 2012'!AE:AE) -> 317.5 | D14: =_xlfn.XLOOKUP(A14,'Receitas Despesas 2013'!B:B,'Receitas Despesas 2013'!AD:AD) -> -450 | E14: =_xlfn.XLOOKUP(A14,'Receitas Despesas 2014'!C:C,'Receitas Despesas 2014'!AE:AE) -> -450 | F14: =_xlfn.XLOOKUP(A14,'Receitas Despesas 2014'!C:C,'Receitas Despesas 2015'!AE:AE) -> -337.5 | G14: =_xlfn.XLOOKUP(A14,'Receitas Despesas 2015'!C:C,'Receitas Despesas 2016'!AE:AE) -> 0 | H14: =_xlfn.XLOOKUP(A14,'Receita Despesas 2017'!B:B,'Receita Despesas 2017'!AD:AD) -> 0 | I14: =_xlfn.XLOOKUP(A14,'Receita Despesas 2018'!C:C,'Receita Despesas 2018'!AF:AF) -> 0 | J14: =_xlfn.XLOOKUP(A14,'Receita Despesas 2019'!C:C,'Receita Despesas 2019'!AE:AE) -> 0 | K14: =_xlfn.XLOOKUP(A14,'Receita Despesa 2020'!B:B,'Receita Despesa 2020'!AD:AD) -> 0 | L14: =_xlfn.XLOOKUP(A14,'Receita Despesas 2021'!B:B,'Receita Despesas 2021'!AD:AD) -> 0 | M14: =_xlfn.XLOOKUP(A14,'Receita Despesas 2022'!B:B,'Receita Despesas 2022'!AD:AD) -> 200 | N14: =_xlfn.XLOOKUP(A14,'Receitas Despesas 2023'!B:B,'Receitas Despesas 2023'!AD:AD) -> -200 | O14: =_xlfn.XLOOKUP(Folha1!A14,'Receitas Despesas 2024'!B:B,'Receitas Despesas 2024'!AD:AD) -> 0 | Q14: =SUM(B14:P14) -> -1305
A15: 1ºAndar Direito | B15: =_xlfn.XLOOKUP(A15,'Receita Despesas 2011 '!C:C,'Receita Despesas 2011 '!AE:AE) -> -30 | C15: =_xlfn.XLOOKUP(A15,'Receitas Despesas 2012'!C:C,'Receitas Despesas 2012'!AE:AE) -> -450 | D15: =_xlfn.XLOOKUP(A15,'Receitas Despesas 2013'!B:B,'Receitas Despesas 2013'!AD:AD) -> -285 | E15: =_xlfn.XLOOKUP(A15,'Receitas Despesas 2014'!C:C,'Receitas Despesas 2014'!AE:AE) -> -450 | F15: =_xlfn.XLOOKUP(A15,'Receitas Despesas 2014'!C:C,'Receitas Despesas 2015'!AE:AE) -> 1368.63 | G15: =_xlfn.XLOOKUP(A15,'Receitas Despesas 2015'!C:C,'Receitas Despesas 2016'!AE:AE) -> 0 | H15: =_xlfn.XLOOKUP(A15,'Receita Despesas 2017'!B:B,'Receita Despesas 2017'!AD:AD) -> 0 | I15: =_xlfn.XLOOKUP(A15,'Receita Despesas 2018'!C:C,'Receita Despesas 2018'!AF:AF) -> 0 | J15: =_xlfn.XLOOKUP(A15,'Receita Despesas 2019'!C:C,'Receita Despesas 2019'!AE:AE) -> 75 | K15: =_xlfn.XLOOKUP(A15,'Receita Despesa 2020'!B:B,'Receita Despesa 2020'!AD:AD) -> 37.5 | L15: =_xlfn.XLOOKUP(A15,'Receita Despesas 2021'!B:B,'Receita Despesas 2021'!AD:AD) -> -112.5 | M15: =_xlfn.XLOOKUP(A15,'Receita Despesas 2022'!B:B,'Receita Despesas 2022'!AD:AD) -> 275 | N15: =_xlfn.XLOOKUP(A15,'Receitas Despesas 2023'!B:B,'Receitas Despesas 2023'!AD:AD) -> -275 | O15: =_xlfn.XLOOKUP(Folha1!A15,'Receitas Despesas 2024'!B:B,'Receitas Despesas 2024'!AD:AD) -> 0 | Q15: =SUM(B15:P15) -> 153.63
A16: 1ºAndar Esquerdo | B16: =_xlfn.XLOOKUP(A16,'Receita Despesas 2011 '!C:C,'Receita Despesas 2011 '!AE:AE) -> -262.5 | C16: =_xlfn.XLOOKUP(A16,'Receitas Despesas 2012'!C:C,'Receitas Despesas 2012'!AE:AE) -> 0 | D16: =_xlfn.XLOOKUP(A16,'Receitas Despesas 2013'!B:B,'Receitas Despesas 2013'!AD:AD) -> 37.5 | E16: =_xlfn.XLOOKUP(A16,'Receitas Despesas 2014'!C:C,'Receitas Despesas 2014'!AE:AE) -> -37.5 | F16: =_xlfn.XLOOKUP(A16,'Receitas Despesas 2014'!C:C,'Receitas Despesas 2015'!AE:AE) -> 37.5 | G16: =_xlfn.XLOOKUP(A16,'Receitas Despesas 2015'!C:C,'Receitas Despesas 2016'!AE:AE) -> -397.5 | H16: =_xlfn.XLOOKUP(A16,'Receita Despesas 2017'!B:B,'Receita Despesas 2017'!AD:AD) -> 0 | I16: =_xlfn.XLOOKUP(A16,'Receita Despesas 2018'!C:C,'Receita Despesas 2018'!AF:AF) -> 0 | J16: =_xlfn.XLOOKUP(A16,'Receita Despesas 2019'!C:C,'Receita Despesas 2019'!AE:AE) -> -37.5 | K16: =_xlfn.XLOOKUP(A16,'Receita Despesa 2020'!B:B,'Receita Despesa 2020'!AD:AD) -> 0 | L16: =_xlfn.XLOOKUP(A16,'Receita Despesas 2021'!B:B,'Receita Despesas 2021'!AD:AD) -> 0 | M16: =_xlfn.XLOOKUP(A16,'Receita Despesas 2022'!B:B,'Receita Despesas 2022'!AD:AD) -> 75 | N16: =_xlfn.XLOOKUP(A16,'Receitas Despesas 2023'!B:B,'Receitas Despesas 2023'!AD:AD) -> 0 | O16: =_xlfn.XLOOKUP(Folha1!A16,'Receitas Despesas 2024'!B:B,'Receitas Despesas 2024'!AD:AD) -> 135 | Q16: =SUM(B16:P16) -> -450
... A20: Cave -2 | B20: =_xlfn.XLOOKUP(A20,'Receita Despesas 2011 '!C:C,'Receita Despesas 2011 '!AE:AE) -> 0 | C20: =_xlfn.XLOOKUP(A20,'Receitas Despesas 2012'!C:C,'Receitas Despesas 2012'!AE:AE) -> 0 | D20: =_xlfn.XLOOKUP(A20,'Receitas Despesas 2013'!B:B,'Receitas Despesas 2013'!AD:AD) -> 0 | E20: =_xlfn.XLOOKUP(A20,'Receitas Despesas 2014'!C:C,'Receitas Despesas 2014'!AE:AE) -> 0 | F20: =_xlfn.XLOOKUP(A20,'Receitas Despesas 2014'!C:C,'Receitas Despesas 2015'!AE:AE) -> 0 | G20: =_xlfn.XLOOKUP(A20,'Receitas Despesas 2015'!C:C,'Receitas Despesas 2016'!AE:AE) -> 450 | H20: =_xlfn.XLOOKUP(A20,'Receita Despesas 2017'!B:B,'Receita Despesas 2017'!AD:AD) -> 0 | I20: =_xlfn.XLOOKUP(A20,'Receita Despesas 2018'!C:C,'Receita Despesas 2018'!AF:AF) -> 0 | J20: =_xlfn.XLOOKUP(A20,'Receita Despesas 2019'!C:C,'Receita Despesas 2019'!AE:AE) -> 0 | K20: =_xlfn.XLOOKUP(A20,'Receita Despesa 2020'!B:B,'Receita Despesa 2020'!AD:AD) -> 0 | L20: =_xlfn.XLOOKUP(A20,'Receita Despesas 2021'!B:B,'Receita Despesas 2021'!AD:AD) -> 0 | M20: =_xlfn.XLOOKUP(A20,'Receita Despesas 2022'!B:B,'Receita Despesas 2022'!AD:AD) -> 0 | N20: =_xlfn.XLOOKUP(A20,'Receitas Despesas 2023'!B:B,'Receitas Despesas 2023'!AD:AD) -> 0 | O20: =_xlfn.XLOOKUP(Folha1!A20,'Receitas Despesas 2024'!B:B,'Receitas Despesas 2024'!AD:AD) -> 0 | Q20: =SUM(B20:P20) -> 450
